Workbook

Sheet Hotels
A1: Hotel_ID | B1: Hotel_Name | C1: City | D1: State | E1: Star_Rating | F1: Hotel_Type | G1: Total_Rooms | H1: Opened_Year | I1: Base_ADR_INR
A2: H001 | B2: Golden Sands Goa | C2: Goa | D2: Goa | E2: 4 | F2: Boutique | G2: 89 | H2: 2018 | I2: 5100
A3: H002 | B3: Azure Bay Goa | C3: Goa | D3: Goa | E3: 5 | F3: Luxury | G3: 260 | H3: 2008 | I3: 9600
A4: H003 | B4: Lotus Grand Goa | C4: Goa | D4: Goa | E4: 3 | F4: Budget | G4: 45 | H4: 2001 | I4: 2900
A5: H004 | B5: Jade Pavilion Goa | C5: Goa | D5: Goa | E5: 4 | F5: Business | G5: 150 | H5: 1995 | I5: 5500
A6: H005 | B6: Blue Lagoon Jaipur | C6: Jaipur | D6: Rajasthan | E6: 3 | F6: Budget | G6: 84 | H6: 2000 | I6: 3000
A7: H006 | B7: Cedar Crest Jaipur | C7: Jaipur | D7: Rajasthan | E7: 5 | F7: Heritage | G7: 257 | H7: 1999 | I7: 9100
A8: H007 | B8: Jade Pavilion Jaipur | C8: Jaipur | D8: Rajasthan | E8: 4 | F8: Resort | G8: 164 | H8: 2005 | I8: 5400
A9: H008 | B9: Golden Sands Jaipur | C9: Jaipur | D9: Rajasthan | E9: 4 | F9: Business | G9: 125 | H9: 1998 | I9: 4500
A10: H009 | B10: Emerald Court Udaipur | C10: Udaipur | D10: Rajasthan | E10: 4 | F10: Heritage | G10: 158 | H10: 2004 | I10: 5000
A11: H010 | B11: Saffron Suites Udaipur | C11: Udaipur | D11: Rajasthan | E11: 5 | F11: Luxury | G11: 236 | H11: 2017 | I11: 10700
A12: H011 | B12: Orchid Terrace Udaipur | C12: Udaipur | D12: Rajasthan | E12: 4 | F12: Business | G12: 125 | H12: 2002 | I12: 5000
A13: H012 | B13: Maple Leaf Inn Udaipur | C13: Udaipur | D13: Rajasthan | E13: 3 | F13: Business | G13: 53 | H13: 2022 | I13: 3500
... A49: H048 | B49: Maple Leaf Inn Varanasi | C49: Varanasi | D49: Uttar Pradesh | E49: 4 | F49: Business | G49: 121 | H49: 2018 | I49: 3500

Sheet Hotels_Dashboard
B1: Hotels - Dashboard
B3: Total Hotels | D3: Total Rooms | F3: Cities | H3: Avg Star Rating | J3: Avg Base ADR (INR) | L3: Occupancy | N3: GOP Margin
B4: =COUNTA(Hotels!$A$2:$A$49) -> 48 | D4: =SUM(Hotels!$G$2:$G$49) -> 6720 | F4: =SUMPRODUCT(1/COUNTIF(Hotels!$C$2:$C$49,Hotels!$C$2:$C$49)) -> 12 | H4: =AVERAGE(Hotels!$E$2:$E$49) -> 4 | J4: =AVERAGE(Hotels!$I$2:$I$49) -> 5597.9167 | L4: =SUM(Hotel_Performance!$F$2:$F$1153)/SUM(Hotel_Performance!$E$2:$E$1153) -> 0.68968138 | N4: =SUM(Hotel_Performance!$M$2:$M$1153)/SUM(Hotel_Performance!$K$2:$K$1153) -> 0.38413736
B52: Chart data (live formulas - charts above read from these tables)
B54: Hotels by city | H54: Hotels by type | L54: Hotels by star rating
B55: City | C55: Hotels | D55: Rooms | E55: Avg Base ADR | F55: Occupancy | H55: Type | I55: Hotels | J55: Rooms | L55: Stars | M55: Hotels | N55: Avg Base ADR
B56: Agra | C56: =COUNTIF(Hotels!$C$2:$C$49,$B56) -> 4 | D56: =SUMIF(Hotels!$C$2:$C$49,$B56,Hotels!$G$2:$G$49) -> 595 | E56: =AVERAGEIF(Hotels!$C$2:$C$49,$B56,Hotels!$I$2:$I$49) -> 4225 | F56: =SUMIF(Hotel_Performance!$B$2:$B$1153,$B56,Hotel_Performance!$F$2:$F$1153)/SUMIF(Hotel_Performance!$B$2:$B$1153,$B56,Hotel_Performance!$E$2:$E$1153) -> 0.65624496 | H56: Boutique | I56: =COUNTIF(Hotels!$F$2:$F$49,$H56) -> 15 | J56: =SUMIF(Hotels!$F$2:$F$49,$H56,Hotels!$G$2:$G$49) -> 1984 | L56: 3 | M56: =COUNTIF(Hotels!$E$2:$E$49,$L56) -> 12 | N56: =AVERAGEIF(Hotels!$E$2:$E$49,$L56,Hotels!$I$2:$I$49) -> 3000
B57: Bengaluru | C57: =COUNTIF(Hotels!$C$2:$C$49,$B57) -> 4 | D57: =SUMIF(Hotels!$C$2:$C$49,$B57,Hotels!$G$2:$G$49) -> 534 | E57: =AVERAGEIF(Hotels!$C$2:$C$49,$B57,Hotels!$I$2:$I$49) -> 6900 | F57: =SUMIF(Hotel_Performance!$B$2:$B$1153,$B57,Hotel_Performance!$F$2:$F$1153)/SUMIF(Hotel_Performance!$B$2:$B$1153,$B57,Hotel_Performance!$E$2:$E$1153) -> 0.72422913 | H57: Business | I57: =COUNTIF(Hotels!$F$2:$F$49,$H57) -> 9 | J57: =SUMIF(Hotels!$F$2:$F$49,$H57,Hotels!$G$2:$G$49) -> 1034 | L57: 4 | M57: =COUNTIF(Hotels!$E$2:$E$49,$L57) -> 24 | N57: =AVERAGEIF(Hotels!$E$2:$E$49,$L57,Hotels!$I$2:$I$49) -> 5000
B58: Goa | C58: =COUNTIF(Hotels!$C$2:$C$49,$B58) -> 4 | D58: =SUMIF(Hotels!$C$2:$C$49,$B58,Hotels!$G$2:$G$49) -> 544 | E58: =AVERAGEIF(Hotels!$C$2:$C$49,$B58,Hotels!$I$2:$I$49) -> 5775 | F58: =SUMIF(Hotel_Performance!$B$2:$B$1153,$B58,Hotel_Performance!$F$2:$F$1153)/SUMIF(Hotel_Performance!$B$2:$B$1153,$B58,Hotel_Performance!$E$2:$E$1153) -> 0.68841156 | H58: Resort | I58: =COUNTIF(Hotels!$F$2:$F$49,$H58) -> 8 | J58: =SUMIF(Hotels!$F$2:$F$49,$H58,Hotels!$G$2:$G$49) -> 1111 | L58: 5 | M58: =COUNTIF(Hotels!$E$2:$E$49,$L58) -> 12 | N58: =AVERAGEIF(Hotels!$E$2:$E$49,$L58,Hotels!$I$2:$I$49) -> 9391.6667
B59: Jaipur | C59: =COUNTIF(Hotels!$C$2:$C$49,$B59) -> 4 | D59: =SUMIF(Hotels!$C$2:$C$49,$B59,Hotels!$G$2:$G$49) -> 630 | E59: =AVERAGEIF(Hotels!$C$2:$C$49,$B59,Hotels!$I$2:$I$49) -> 5500 | F59: =SUMIF(Hotel_Performance!$B$2:$B$1153,$B59,Hotel_Performance!$F$2:$F$1153)/SUMIF(Hotel_Performance!$B$2:$B$1153,$B59,Hotel_Performance!$E$2:$E$1153) -> 0.69938465 | H59: Luxury | I59: =COUNTIF(Hotels!$F$2:$F$49,$H59) -> 7 | J59: =SUMIF(Hotels!$F$2:$F$49,$H59,Hotels!$G$2:$G$49) -> 1589
B60: Kochi | C60: =COUNTIF(Hotels!$C$2:$C$49,$B60) -> 4 | D60: =SUMIF(Hotels!$C$2:$C$49,$B60,Hotels!$G$2:$G$49) -> 649 | E60: =AVERAGEIF(Hotels!$C$2:$C$49,$B60,Hotels!$I$2:$I$49) -> 5250 | F60: =SUMIF(Hotel_Performance!$B$2:$B$1153,$B60,Hotel_Performance!$F$2:$F$1153)/SUMIF(Hotel_Performance!$B$2:$B$1153,$B60,Hotel_Performance!$E$2:$E$1153) -> 0.70765139 | H60: Budget | I60: =COUNTIF(Hotels!$F$2:$F$49,$H60) -> 5 | J60: =SUMIF(Hotels!$F$2:$F$49,$H60,Hotels!$G$2:$G$49) -> 355
B61: Manali | C61: =COUNTIF(Hotels!$C$2:$C$49,$B61) -> 4 | D61: =SUMIF(Hotels!$C$2:$C$49,$B61,Hotels!$G$2:$G$49) -> 454 | E61: =AVERAGEIF(Hotels!$C$2:$C$49,$B61,Hotels!$I$2:$I$49) -> 4950 | F61: =SUMIF(Hotel_Performance!$B$2:$B$1153,$B61,Hotel_Performance!$F$2:$F$1153)/SUMIF(Hotel_Performance!$B$2:$B$1153,$B61,Hotel_Performance!$E$2:$E$1153) -> 0.68507634 | H61: Heritage | I61: =COUNTIF(Hotels!$F$2:$F$49,$H61) -> 4 | J61: =SUMIF(Hotels!$F$2:$F$49,$H61,Hotels!$G$2:$G$49) -> 647
B62: Mumbai | C62: =COUNTIF(Hotels!$C$2:$C$49,$B62) -> 4 | D62: =SUMIF(Hotels!$C$2:$C$49,$B62,Hotels!$G$2:$G$49) -> 503 | E62: =AVERAGEIF(Hotels!$C$2:$C$49,$B62,Hotels!$I$2:$I$49) -> 8050 | F62: =SUMIF(Hotel_Performance!$B$2:$B$1153,$B62,Hotel_Performance!$F$2:$F$1153)/SUMIF(Hotel_Performance!$B$2:$B$1153,$B62,Hotel_Performance!$E$2:$E$1153) -> 0.65009123
B63: New Delhi | C63: =COUNTIF(Hotels!$C$2:$C$49,$B63) -> 4 | D63: =SUMIF(Hotels!$C$2:$C$49,$B63,Hotels!$G$2:$G$49) -> 658 | E63: =AVERAGEIF(Hotels!$C$2:$C$49,$B63,Hotels!$I$2:$I$49) -> 7375 | F63: =SUMIF(Hotel_Performance!$B$2:$B$1153,$B63,Hotel_Performance!$F$2:$F$1153)/SUMIF(Hotel_Performance!$B$2:$B$1153,$B63,Hotel_Performance!$E$2:$E$1153) -> 0.718006
B64: Rishikesh | C64: =COUNTIF(Hotels!$C$2:$C$49,$B64) -> 4 | D64: =SUMIF(Hotels!$C$2:$C$49,$B64,Hotels!$G$2:$G$49) -> 598 | E64: =AVERAGEIF(Hotels!$C$2:$C$49,$B64,Hotels!$I$2:$I$49) -> 4125 | F64: =SUMIF(Hotel_Performance!$B$2:$B$1153,$B64,Hotel_Performance!$F$2:$F$1153)/SUMIF(Hotel_Performance!$B$2:$B$1153,$B64,Hotel_Performance!$E$2:$E$1153) -> 0.68807898
B65: Shimla | C65: =COUNTIF(Hotels!$C$2:$C$49,$B65) -> 4 | D65: =SUMIF(Hotels!$C$2:$C$49,$B65,Hotels!$G$2:$G$49) -> 554 | E65: =AVERAGEIF(Hotels!$C$2:$C$49,$B65,Hotels!$I$2:$I$49) -> 4775 | F65: =SUMIF(Hotel_Performance!$B$2:$B$1153,$B65,Hotel_Performance!$F$2:$F$1153)/SUMIF(Hotel_Performance!$B$2:$B$1153,$B65,Hotel_Performance!$E$2:$E$1153) -> 0.68081203
B66: Udaipur | C66: =COUNTIF(Hotels!$C$2:$C$49,$B66) -> 4 | D66: =SUMIF(Hotels!$C$2:$C$49,$B66,Hotels!$G$2:$G$49) -> 572 | E66: =AVERAGEIF(Hotels!$C$2:$C$49,$B66,Hotels!$I$2:$I$49) -> 6050 | F66: =SUMIF(Hotel_Performance!$B$2:$B$1153,$B66,Hotel_Performance!$F$2:$F$1153)/SUMIF(Hotel_Performance!$B$2:$B$1153,$B66,Hotel_Performance!$E$2:$E$1153) -> 0.69259508
B67: Varanasi | C67: =COUNTIF(Hotels!$C$2:$C$49,$B67) -> 4 | D67: =SUMIF(Hotels!$C$2:$C$49,$B67,Hotels!$G$2:$G$49) -> 429 | E67: =AVERAGEIF(Hotels!$C$2:$C$49,$B67,Hotels!$I$2:$I$49) -> 4200 | F67: =SUMIF(Hotel_Performance!$B$2:$B$1153,$B67,Hotel_Performance!$F$2:$F$1153)/SUMIF(Hotel_Performance!$B$2:$B$1153,$B67,Hotel_Performance!$E$2:$E$1153) -> 0.67087844

Sheet Customers
A1: Customer_ID | B1: Full_Name | C1: Gender | D1: Age | E1: Age_Group | F1: Country | G1: Home_City | H1: Customer_Type | I1: Segment | J1: Loyalty_Tier | K1: Signup_Date | L1: Acquisition_Source | M1: Email_Opt_In | N1: Total_Bookings | O1: Completed_Stays | P1: Lifetime_Revenue_INR | Q1: Customer_Status
A2: C0001 | B2: Shreya Kulkarni | C2: Female | D2: 35 | E2: =IF(D2<25,"18-24",IF(D2<35,"25-34",IF(D2<45,"35-44",IF(D2<55,"45-54","55+")))) -> 35-44 | F2: India | G2: Kolkata | H2: Domestic | I2: Leisure | J2: None | K2: 45711 | L2: Organic Search | M2: Yes | N2: =COUNTIF(Bookings!$B$2:$B$5001,A2) -> 2 | O2: =COUNTIFS(Bookings!$B$2:$B$5001,A2,Bookings!$Q$2:$Q$5001,"Completed") -> 1 | P2: =SUMIFS(Revenue!$L$2:$L$4092,Revenue!$B$2:$B$4092,A2) -> 22280 | Q2: =IF(N2=0,"Inactive",IF(N2=1,"One-time",IF(N2<4,"Repeat","Loyal"))) -> Repeat
A3: C0002 | B3: Rahul Iyer | C3: Male | D3: 38 | E3: =IF(D3<25,"18-24",IF(D3<35,"25-34",IF(D3<45,"35-44",IF(D3<55,"45-54","55+")))) -> 35-44 | F3: India | G3: Hyderabad | H3: Domestic | I3: Business | J3: None | K3: 45786 | L3: Travel Partner | M3: Yes | N3: =COUNTIF(Bookings!$B$2:$B$5001,A3) -> 2 | O3: =COUNTIFS(Bookings!$B$2:$B$5001,A3,Bookings!$Q$2:$Q$5001,"Completed") -> 2 | P3: =SUMIFS(Revenue!$L$2:$L$4092,Revenue!$B$2:$B$4092,A3) -> 35260 | Q3: =IF(N3=0,"Inactive",IF(N3=1,"One-time",IF(N3<4,"Repeat","Loyal"))) -> Repeat
A4: C0003 | B4: Rohan Bose | C4: Male | D4: 38 | E4: =IF(D4<25,"18-24",IF(D4<35,"25-34",IF(D4<45,"35-44",IF(D4<55,"45-54","55+")))) -> 35-44 | F4: India | G4: Ahmedabad | H4: Domestic | I4: Leisure | J4: None | K4: 45158 | L4: Social Media | M4: Yes | N4: =COUNTIF(Bookings!$B$2:$B$5001,A4) -> 0 | O4: =COUNTIFS(Bookings!$B$2:$B$5001,A4,Bookings!$Q$2:$Q$5001,"Completed") -> 0 | P4: =SUMIFS(Revenue!$L$2:$L$4092,Revenue!$B$2:$B$4092,A4) -> 0 | Q4: =IF(N4=0,"Inactive",IF(N4=1,"One-time",IF(N4<4,"Repeat","Loyal"))) -> Inactive
A5: C0004 | B5: Rajesh Nair | C5: Male | D5: 39 | E5: =IF(D5<25,"18-24",IF(D5<35,"25-34",IF(D5<45,"35-44",IF(D5<55,"45-54","55+")))) -> 35-44 | F5: India | G5: Chennai | H5: Domestic | I5: Leisure | J5: None | K5: 45699 | L5: Organic Search | M5: Yes | N5: =COUNTIF(Bookings!$B$2:$B$5001,A5) -> 2 | O5: =COUNTIFS(Bookings!$B$2:$B$5001,A5,Bookings!$Q$2:$Q$5001,"Completed") -> 2 | P5: =SUMIFS(Revenue!$L$2:$L$4092,Revenue!$B$2:$B$4092,A5) -> 95110 | Q5: =IF(N5=0,"Inactive",IF(N5=1,"One-time",IF(N5<4,"Repeat","Loyal"))) -> Repeat
A6: C0005 | B6: Shreya Kulkarni | C6: Male | D6: 18 | E6: =IF(D6<25,"18-24",IF(D6<35,"25-34",IF(D6<45,"35-44",IF(D6<55,"45-54","55+")))) -> 18-24 | F6: India | G6: Ahmedabad | H6: Domestic | I6: Couple | J6: None | K6: 45841 | L6: Travel Partner | M6: No | N6: =COUNTIF(Bookings!$B$2:$B$5001,A6) -> 2 | O6: =COUNTIFS(Bookings!$B$2:$B$5001,A6,Bookings!$Q$2:$Q$5001,"Completed") -> 1 | P6: =SUMIFS(Revenue!$L$2:$L$4092,Revenue!$B$2:$B$4092,A6) -> 28110 | Q6: =IF(N6=0,"Inactive",IF(N6=1,"One-time",IF(N6<4,"Repeat","Loyal"))) -> Repeat
A7: C0006 | B7: Vivaan Rao | C7: Female | D7: 37 | E7: =IF(D7<25,"18-24",IF(D7<35,"25-34",IF(D7<45,"35-44",IF(D7<55,"45-54","55+")))) -> 35-44 | F7: India | G7: Delhi | H7: Domestic | I7: Business | J7: None | K7: 45742 | L7: Travel Partner | M7: No | N7: =COUNTIF(Bookings!$B$2:$B$5001,A7) -> 2 | O7: =COUNTIFS(Bookings!$B$2:$B$5001,A7,Bookings!$Q$2:$Q$5001,"Completed") -> 2 | P7: =SUMIFS(Revenue!$L$2:$L$4092,Revenue!$B$2:$B$4092,A7) -> 95910 | Q7: =IF(N7=0,"Inactive",IF(N7=1,"One-time",IF(N7<4,"Repeat","Loyal"))) -> Repeat
A8: C0007 | B8: Aarav Singh | C8: Female | D8: 31 | E8: =IF(D8<25,"18-24",IF(D8<35,"25-34",IF(D8<45,"35-44",IF(D8<55,"45-54","55+")))) -> 25-34 | F8: India | G8: Bhopal | H8: Domestic | I8: Family | J8: None | K8: 45523 | L8: Social Media | M8: Yes | N8: =COUNTIF(Bookings!$B$2:$B$5001,A8) -> 2 | O8: =COUNTIFS(Bookings!$B$2:$B$5001,A8,Bookings!$Q$2:$Q$5001,"Completed") -> 2 | P8: =SUMIFS(Revenue!$L$2:$L$4092,Revenue!$B$2:$B$4092,A8) -> 85350 | Q8: =IF(N8=0,"Inactive",IF(N8=1,"One-time",IF(N8<4,"Repeat","Loyal"))) -> Repeat
A9: C0008 | B9: Deepak Khan | C9: Male | D9: 36 | E9: =IF(D9<25,"18-24",IF(D9<35,"25-34",IF(D9<45,"35-44",IF(D9<55,"45-54","55+")))) -> 35-44 | F9: India | G9: Bengaluru | H9: Domestic | I9: Leisure | J9: None | K9: 45547 | L9: Email Campaign | M9: No | N9: =COUNTIF(Bookings!$B$2:$B$5001,A9) -> 3 | O9: =COUNTIFS(Bookings!$B$2:$B$5001,A9,Bookings!$Q$2:$Q$5001,"Completed") -> 2 | P9: =SUMIFS(Revenue!$L$2:$L$4092,Revenue!$B$2:$B$4092,A9) -> 35710 | Q9: =IF(N9=0,"Inactive",IF(N9=1,"One-time",IF(N9<4,"Repeat","Loyal"))) -> Repeat
A10: C0009 | B10: Nisha Chopra | C10: Female | D10: 43 | E10: =IF(D10<25,"18-24",IF(D10<35,"25-34",IF(D10<45,"35-44",IF(D10<55,"45-54","55+")))) -> 35-44 | F10: India | G10: Hyderabad | H10: Domestic | I10: Business | J10: None | K10: 45912 | L10: Organic Search | M10: Yes | N10: =COUNTIF(Bookings!$B$2:$B$5001,A10) -> 1 | O10: =COUNTIFS(Bookings!$B$2:$B$5001,A10,Bookings!$Q$2:$Q$5001,"Completed") -> 1 | P10: =SUMIFS(Revenue!$L$2:$L$4092,Revenue!$B$2:$B$4092,A10) -> 37170 | Q10: =IF(N10=0,"Inactive",IF(N10=1,"One-time",IF(N10<4,"Repeat","Loyal"))) -> One-time
A11: C0010 | B11: Manish Sharma | C11: Male | D11: 35 | E11: =IF(D11<25,"18-24",IF(D11<35,"25-34",IF(D11<45,"35-44",IF(D11<55,"45-54","55+")))) -> 35-44 | F11: India | G11: Bengaluru | H11: Domestic | I11: Leisure | J11: None | K11: 45994 | L11: Email Campaign | M11: Yes | N11: =COUNTIF(Bookings!$B$2:$B$5001,A11) -> 2 | O11: =COUNTIFS(Bookings!$B$2:$B$5001,A11,Bookings!$Q$2:$Q$5001,"Completed") -> 1 | P11: =SUMIFS(Revenue!$L$2:$L$4092,Revenue!$B$2:$B$4092,A11) -> 89550 | Q11: =IF(N11=0,"Inactive",IF(N11=1,"One-time",IF(N11<4,"Repeat","Loyal"))) -> Repeat
A12: C0011 | B12: Hugo Clarke | C12: Male | D12: 23 | E12: =IF(D12<25,"18-24",IF(D12<35,"25-34",IF(D12<45,"35-44",IF(D12<55,"45-54","55+")))) -> 18-24 | F12: UAE | G12: Dubai | H12: International | I12: Leisure | J12: Gold | K12: 45380 | L12: Email Campaign | M12: No | N12: =COUNTIF(Bookings!$B$2:$B$5001,A12) -> 7 | O12: =COUNTIFS(Bookings!$B$2:$B$5001,A12,Bookings!$Q$2:$Q$5001,"Completed") -> 7 | P12: =SUMIFS(Revenue!$L$2:$L$4092,Revenue!$B$2:$B$4092,A12) -> 275570 | Q12: =IF(N12=0,"Inactive",IF(N12=1,"One-time",IF(N12<4,"Repeat","Loyal"))) -> Loyal
A13: C0012 | B13: Meera Tiwari | C13: Male | D13: 36 | E13: =IF(D13<25,"18-24",IF(D13<35,"25-34",IF(D13<45,"35-44",IF(D13<55,"45-54","55+")))) -> 35-44 | F13: India | G13: Surat | H13: Domestic | I13: Couple | J13: None | K13: 45932 | L13: Travel Partner | M13: No | N13: =COUNTIF(Bookings!$B$2:$B$5001,A13) -> 3 | O13: =COUNTIFS(Bookings!$B$2:$B$5001,A13,Bookings!$Q$2:$Q$5001,"Completed") -> 3 | P13: =SUMIFS(Revenue!$L$2:$L$4092,Revenue!$B$2:$B$4092,A13) -> 127930 | Q13: =IF(N13=0,"Inactive",IF(N13=1,"One-time",IF(N13<4,"Repeat","Loyal"))) -> Repeat
... A1501: C1500 | B1501: Sneha Shah | C1501: Male | D1501: 63 | E1501: =IF(D1501<25,"18-24",IF(D1501<35,"25-34",IF(D1501<45,"35-44",IF(D1501<55,"45-54","55+")))) -> 55+ | F1501: India | G1501: Chandigarh | H1501: Domestic | I1501: Leisure | J1501: Silver | K1501: 45543 | L1501: Referral | M1501: Yes | N1501: =COUNTIF(Bookings!$B$2:$B$5001,A1501) -> 3 | O1501: =COUNTIFS(Bookings!$B$2:$B$5001,A1501,Bookings!$Q$2:$Q$5001,"Completed") -> 1 | P1501: =SUMIFS(Revenue!$L$2:$L$4092,Revenue!$B$2:$B$4092,A1501) -> 40840 | Q1501: =IF(N1501=0,"Inactive",IF(N1501=1,"One-time",IF(N1501<4,"Repeat","Loyal"))) -> Repeat

Sheet Customers_Dashboard
B1: Customers - Dashboard
B3: Total Customers | D3: Active (1+ booking) | F3: Repeat Rate | H3: Lifetime Revenue (Cr) | J3: Avg CLV (INR) | L3: International Share | N3: Loyalty Members
B4: =COUNTA(Customers!$A$2:$A$1501) -> 1500 | D4: =COUNTIF(Customers!$N$2:$N$1501,">=1") -> 1122 | F4: =COUNTIF(Customers!$N$2:$N$1501,">=2")/COUNTIF(Customers!$N$2:$N$1501,">=1") -> 0.79055258 | H4: =SUM(Customers!$P$2:$P$1501)/10000000 -> 20.838432 | J4: =SUM(Customers!$P$2:$P$1501)/COUNTIF(Customers!$N$2:$N$1501,">=1") -> 185725.78 | L4: =COUNTIF(Customers!$H$2:$H$1501,"International")/COUNTA(Customers!$A$2:$A$1501) -> 0.22 | N4: =1-COUNTIF(Customers!$J$2:$J$1501,"None")/COUNTA(Customers!$A$2:$A$1501) -> 0.34266667
B52: Chart data (live formulas - charts above read from these tables)
B54: By segment | H54: By loyalty tier | L54: By age group
B55: Segment | C55: Customers | D55: Active | E55: Lifetime Rev (Lakh) | F55: Avg CLV | H55: Tier | I55: Customers | J55: Lifetime Rev (Lakh) | L55: Age | M55: Customers
B56: Leisure | C56: =COUNTIF(Customers!$I$2:$I$1501,$B56) -> 548 | D56: =COUNTIFS(Customers!$I$2:$I$1501,$B56,Customers!$N$2:$N$1501,">=1") -> 405 | E56: =SUMIF(Customers!$I$2:$I$1501,$B56,Customers!$P$2:$P$1501)/100000 -> 563.9898 | F56: =SUMIF(Customers!$I$2:$I$1501,$B56,Customers!$P$2:$P$1501)/COUNTIFS(Customers!$I$2:$I$1501,$B56,Customers!$N$2:$N$1501,">=1") -> 139256.74 | H56: None | I56: =COUNTIF(Customers!$J$2:$J$1501,$H56) -> 986 | J56: =SUMIF(Customers!$J$2:$J$1501,$H56,Customers!$P$2:$P$1501)/100000 -> 483.0047 | L56: 18-24 | M56: =COUNTIF(Customers!$E$2:$E$1501,$L56) -> 201
B57: Family | C57: =COUNTIF(Customers!$I$2:$I$1501,$B57) -> 328 | D57: =COUNTIFS(Customers!$I$2:$I$1501,$B57,Customers!$N$2:$N$1501,">=1") -> 242 | E57: =SUMIF(Customers!$I$2:$I$1501,$B57,Customers!$P$2:$P$1501)/100000 -> 560.1033 | F57: =SUMIF(Customers!$I$2:$I$1501,$B57,Customers!$P$2:$P$1501)/COUNTIFS(Customers!$I$2:$I$1501,$B57,Customers!$N$2:$N$1501,">=1") -> 231447.64 | H57: Silver | I57: =COUNTIF(Customers!$J$2:$J$1501,$H57) -> 221 | J57: =SUMIF(Customers!$J$2:$J$1501,$H57,Customers!$P$2:$P$1501)/100000 -> 362.7514 | L57: 25-34 | M57: =COUNTIF(Customers!$E$2:$E$1501,$L57) -> 481
B58: Business | C58: =COUNTIF(Customers!$I$2:$I$1501,$B58) -> 258 | D58: =COUNTIFS(Customers!$I$2:$I$1501,$B58,Customers!$N$2:$N$1501,">=1") -> 204 | E58: =SUMIF(Customers!$I$2:$I$1501,$B58,Customers!$P$2:$P$1501)/100000 -> 284.6405 | F58: =SUMIF(Customers!$I$2:$I$1501,$B58,Customers!$P$2:$P$1501)/COUNTIFS(Customers!$I$2:$I$1501,$B58,Customers!$N$2:$N$1501,">=1") -> 139529.66 | H58: Gold | I58: =COUNTIF(Customers!$J$2:$J$1501,$H58) -> 145 | J58: =SUMIF(Customers!$J$2:$J$1501,$H58,Customers!$P$2:$P$1501)/100000 -> 395.5721 | L58: 35-44 | M58: =COUNTIF(Customers!$E$2:$E$1501,$L58) -> 544
B59: Couple | C59: =COUNTIF(Customers!$I$2:$I$1501,$B59) -> 257 | D59: =COUNTIFS(Customers!$I$2:$I$1501,$B59,Customers!$N$2:$N$1501,">=1") -> 190 | E59: =SUMIF(Customers!$I$2:$I$1501,$B59,Customers!$P$2:$P$1501)/100000 -> 258.361 | F59: =SUMIF(Customers!$I$2:$I$1501,$B59,Customers!$P$2:$P$1501)/COUNTIFS(Customers!$I$2:$I$1501,$B59,Customers!$N$2:$N$1501,">=1") -> 135979.47 | H59: Platinum | I59: =COUNTIF(Customers!$J$2:$J$1501,$H59) -> 148 | J59: =SUMIF(Customers!$J$2:$J$1501,$H59,Customers!$P$2:$P$1501)/100000 -> 842.515 | L59: 45-54 | M59: =COUNTIF(Customers!$E$2:$E$1501,$L59) -> 234
B60: Group | C60: =COUNTIF(Customers!$I$2:$I$1501,$B60) -> 109 | D60: =COUNTIFS(Customers!$I$2:$I$1501,$B60,Customers!$N$2:$N$1501,">=1") -> 81 | E60: =SUMIF(Customers!$I$2:$I$1501,$B60,Customers!$P$2:$P$1501)/100000 -> 416.7486 | F60: =SUMIF(Customers!$I$2:$I$1501,$B60,Customers!$P$2:$P$1501)/COUNTIFS(Customers!$I$2:$I$1501,$B60,Customers!$N$2:$N$1501,">=1") -> 514504.44 | L60: 55+ | M60: =COUNTIF(Customers!$E$2:$E$1501,$L60) -> 40
B63: By acquisition source | E63: By customer type
B64: Source | C64: Customers | E64: Type | F64: Customers
B65: Corporate Tie-up | C65: =COUNTIF(Customers!$L$2:$L$1501,$B65) -> 127 | E65: Domestic | F65: =COUNTIF(Customers!$H$2:$H$1501,$E65) -> 1170
B66: Organic Search | C66: =COUNTIF(Customers!$L$2:$L$1501,$B66) -> 257 | E66: International | F66: =COUNTIF(Customers!$H$2:$H$1501,$E66) -> 330
B67: Referral | C67: =COUNTIF(Customers!$L$2:$L$1501,$B67) -> 271
B68: Email Campaign | C68: =COUNTIF(Customers!$L$2:$L$1501,$B68) -> 273
B69: Social Media | C69: =COUNTIF(Customers!$L$2:$L$1501,$B69) -> 282
B70: Travel Partner | C70: =COUNTIF(Customers!$L$2:$L$1501,$B70) -> 290

Sheet Bookings
A1: Booking_ID | B1: Customer_ID | C1: Hotel_ID | D1: Hotel_City | E1: Booking_Date | F1: Check_In | G1: Check_Out | H1: Check_In_Month | I1: Nights | J1: Lead_Time_Days | K1: Room_Type | L1: Rooms_Booked | M1: Adults | N1: Children | O1: Channel | P1: Payment_Method | Q1: Booking_Status | R1: Room_Rate_INR | S1: Booking_Value_INR | T1: Total_Guests
A2: BK00001 | B2: C1269 | C2: H020 | D2: =INDEX(Hotels!$C$2:$C$49,MATCH(C2,Hotels!$A$2:$A$49,0)) -> Mumbai | E2: 45302 | F2: 45572 | G2: 45575 | H2: =DATE(YEAR(F2),MONTH(F2),1) -> 45566 | I2: =G2-F2 -> 3 | J2: =F2-E2 -> 270 | K2: Suite | L2: 2 | M2: 4 | N2: 2 | O2: Mobile App | P2: Digital Wallet | Q2: Completed | R2: 26500 | S2: =I2*L2*R2 -> 159000 | T2: =M2+N2 -> 6
A3: BK00002 | B3: C0630 | C3: H002 | D3: =INDEX(Hotels!$C$2:$C$49,MATCH(C3,Hotels!$A$2:$A$49,0)) -> Goa | E3: 45323 | F3: 45584 | G3: 45587 | H3: =DATE(YEAR(F3),MONTH(F3),1) -> 45566 | I3: =G3-F3 -> 3 | J3: =F3-E3 -> 261 | K3: Suite | L3: 1 | M3: 2 | N3: 3 | O3: OTA - Agoda | P3: UPI | Q3: Cancelled | R3: 19400 | S3: =I3*L3*R3 -> 58200 | T3: =M3+N3 -> 5
A4: BK00003 | B4: C0747 | C4: H014 | D4: =INDEX(Hotels!$C$2:$C$49,MATCH(C4,Hotels!$A$2:$A$49,0)) -> Agra | E4: 45332 | F4: 45602 | G4: 45605 | H4: =DATE(YEAR(F4),MONTH(F4),1) -> 45597 | I4: =G4-F4 -> 3 | J4: =F4-E4 -> 270 | K4: Deluxe | L4: 1 | M4: 1 | N4: 0 | O4: OTA - Agoda | P4: Credit Card | Q4: Completed | R4: 6200 | S4: =I4*L4*R4 -> 18600 | T4: =M4+N4 -> 1
A5: BK00004 | B5: C0547 | C5: H004 | D5: =INDEX(Hotels!$C$2:$C$49,MATCH(C5,Hotels!$A$2:$A$49,0)) -> Goa | E5: 45362 | F5: 45632 | G5: 45636 | H5: =DATE(YEAR(F5),MONTH(F5),1) -> 45627 | I5: =G5-F5 -> 4 | J5: =F5-E5 -> 270 | K5: Suite | L5: 2 | M5: 4 | N5: 0 | O5: Travel Agent | P5: Cash | Q5: Completed | R5: 13900 | S5: =I5*L5*R5 -> 111200 | T5: =M5+N5 -> 4
A6: BK00005 | B6: C0702 | C6: H020 | D6: =INDEX(Hotels!$C$2:$C$49,MATCH(C6,Hotels!$A$2:$A$49,0)) -> Mumbai | E6: 45364 | F6: 45568 | G6: 45572 | H6: =DATE(YEAR(F6),MONTH(F6),1) -> 45566 | I6: =G6-F6 -> 4 | J6: =F6-E6 -> 204 | K6: Deluxe | L6: 1 | M6: 2 | N6: 2 | O6: Walk-in | P6: Debit Card | Q6: Completed | R6: 18050 | S6: =I6*L6*R6 -> 72200 | T6: =M6+N6 -> 4
A7: BK00006 | B7: C1184 | C7: H038 | D7: =INDEX(Hotels!$C$2:$C$49,MATCH(C7,Hotels!$A$2:$A$49,0)) -> Manali | E7: 45369 | F7: 45639 | G7: 45643 | H7: =DATE(YEAR(F7),MONTH(F7),1) -> 45627 | I7: =G7-F7 -> 4 | J7: =F7-E7 -> 270 | K7: Suite | L7: 1 | M7: 2 | N7: 2 | O7: Mobile App | P7: Credit Card | Q7: No-Show | R7: 11100 | S7: =I7*L7*R7 -> 44400 | T7: =M7+N7 -> 4
A8: BK00007 | B8: C1337 | C8: H021 | D8: =INDEX(Hotels!$C$2:$C$49,MATCH(C8,Hotels!$A$2:$A$49,0)) -> New Delhi | E8: 45369 | F8: 45605 | G8: 45609 | H8: =DATE(YEAR(F8),MONTH(F8),1) -> 45597 | I8: =G8-F8 -> 4 | J8: =F8-E8 -> 236 | K8: Premium Suite | L8: 4 | M8: 8 | N8: 0 | O8: Travel Agent | P8: UPI | Q8: Completed | R8: 25050 | S8: =I8*L8*R8 -> 400800 | T8: =M8+N8 -> 8
A9: BK00008 | B9: C0100 | C9: H030 | D9: =INDEX(Hotels!$C$2:$C$49,MATCH(C9,Hotels!$A$2:$A$49,0)) -> Kochi | E9: 45376 | F9: 45585 | G9: 45587 | H9: =DATE(YEAR(F9),MONTH(F9),1) -> 45566 | I9: =G9-F9 -> 2 | J9: =F9-E9 -> 209 | K9: Standard | L9: 2 | M9: 4 | N9: 0 | O9: Travel Agent | P9: UPI | Q9: Completed | R9: 5500 | S9: =I9*L9*R9 -> 22000 | T9: =M9+N9 -> 4
A10: BK00009 | B10: C0062 | C10: H016 | D10: =INDEX(Hotels!$C$2:$C$49,MATCH(C10,Hotels!$A$2:$A$49,0)) -> Agra | E10: 45378 | F10: 45648 | G10: 45653 | H10: =DATE(YEAR(F10),MONTH(F10),1) -> 45627 | I10: =G10-F10 -> 5 | J10: =F10-E10 -> 270 | K10: Standard | L10: 1 | M10: 3 | N10: 0 | O10: Direct Website | P10: Credit Card | Q10: Completed | R10: 8950 | S10: =I10*L10*R10 -> 44750 | T10: =M10+N10 -> 3
A11: BK00010 | B11: C0100 | C11: H010 | D11: =INDEX(Hotels!$C$2:$C$49,MATCH(C11,Hotels!$A$2:$A$49,0)) -> Udaipur | E11: 45385 | F11: 45655 | G11: 45659 | H11: =DATE(YEAR(F11),MONTH(F11),1) -> 45627 | I11: =G11-F11 -> 4 | J11: =F11-E11 -> 270 | K11: Deluxe | L11: 3 | M11: 6 | N11: 0 | O11: OTA - Agoda | P11: Net Banking | Q11: Cancelled | R11: 18250 | S11: =I11*L11*R11 -> 219000 | T11: =M11+N11 -> 6
A12: BK00011 | B12: C1323 | C12: H005 | D12: =INDEX(Hotels!$C$2:$C$49,MATCH(C12,Hotels!$A$2:$A$49,0)) -> Jaipur | E12: 45387 | F12: 45579 | G12: 45583 | H12: =DATE(YEAR(F12),MONTH(F12),1) -> 45566 | I12: =G12-F12 -> 4 | J12: =F12-E12 -> 192 | K12: Deluxe | L12: 1 | M12: 2 | N12: 0 | O12: Mobile App | P12: Credit Card | Q12: Completed | R12: 5100 | S12: =I12*L12*R12 -> 20400 | T12: =M12+N12 -> 2
A13: BK00012 | B13: C0682 | C13: H022 | D13: =INDEX(Hotels!$C$2:$C$49,MATCH(C13,Hotels!$A$2:$A$49,0)) -> New Delhi | E13: 45390 | F13: 45660 | G13: 45664 | H13: =DATE(YEAR(F13),MONTH(F13),1) -> 45658 | I13: =G13-F13 -> 4 | J13: =F13-E13 -> 270 | K13: Standard | L13: 1 | M13: 1 | N13: 0 | O13: OTA - Agoda | P13: Debit Card | Q13: Cancelled | R13: 5250 | S13: =I13*L13*R13 -> 21000 | T13: =M13+N13 -> 1
... A5001: BK05000 | B5001: C1223 | C5001: H006 | D5001: =INDEX(Hotels!$C$2:$C$49,MATCH(C5001,Hotels!$A$2:$A$49,0)) -> Jaipur | E5001: 46293 | F5001: 46295 | G5001: 46297 | H5001: =DATE(YEAR(F5001),MONTH(F5001),1) -> 46266 | I5001: =G5001-F5001 -> 2 | J5001: =F5001-E5001 -> 2 | K5001: Deluxe | L5001: 1 | M5001: 1 | N5001: 0 | O5001: OTA - Agoda | P5001: Credit Card | Q5001: Completed | R5001: 10000 | S5001: =I5001*L5001*R5001 -> 20000 | T5001: =M5001+N5001 -> 1

Sheet Bookings_Dashboard
B1: Bookings - Dashboard
B3: Total Bookings | D3: Cancellation Rate | F3: No-show Rate | H3: Avg Lead Time (days) | J3: Avg Stay (nights) | L3: Avg Booking Value | N3: Avg Guests
B4: =COUNTA(Bookings!$A$2:$A$5001) -> 5000 | D4: =COUNTIF(Bookings!$Q$2:$Q$5001,"Cancelled")/COUNTA(Bookings!$A$2:$A$5001) -> 0.1544 | F4: =COUNTIF(Bookings!$Q$2:$Q$5001,"No-Show")/COUNTA(Bookings!$A$2:$A$5001) -> 0.0274 | H4: =AVERAGE(Bookings!$J$2:$J$5001) -> 41.0406 | J4: =AVERAGEIF(Bookings!$Q$2:$Q$5001,"Completed",Bookings!$I$2:$I$5001) -> 3.1532633 | L4: =AVERAGEIF(Bookings!$Q$2:$Q$5001,"Completed",Bookings!$S$2:$S$5001) -> 43144.195 | N4: =AVERAGE(Bookings!$T$2:$T$5001) -> 2.6092
B67: Chart data (live formulas - charts above read from these tables)
B69: By status | E69: By channel | K69: By room type
B70: Status | C70: Bookings | E70: Channel | F70: Bookings | G70: Cancel Rate | H70: Avg Lead (d) | I70: Avg Value | K70: Room | L70: Bookings | M70: Avg Value
B71: Completed | C71: =COUNTIF(Bookings!$Q$2:$Q$5001,$B71) -> 4091 | E71: Walk-in | F71: =COUNTIF(Bookings!$O$2:$O$5001,$E71) -> 130 | G71: =COUNTIFS(Bookings!$O$2:$O$5001,$E71,Bookings!$Q$2:$Q$5001,"Cancelled")/COUNTIF(Bookings!$O$2:$O$5001,$E71) -> 0.038461538 | H71: =AVERAGEIF(Bookings!$O$2:$O$5001,$E71,Bookings!$J$2:$J$5001) -> 44.138462 | I71: =AVERAGEIFS(Bookings!$S$2:$S$5001,Bookings!$O$2:$O$5001,$E71,Bookings!$Q$2:$Q$5001,"Completed") -> 40091.6 | K71: Standard | L71: =COUNTIF(Bookings!$K$2:$K$5001,$K71) -> 1581 | M71: =AVERAGEIFS(Bookings!$S$2:$S$5001,Bookings!$K$2:$K$5001,$K71,Bookings!$Q$2:$Q$5001,"Completed") -> 26103.711
B72: Cancelled | C72: =COUNTIF(Bookings!$Q$2:$Q$5001,$B72) -> 772 | E72: OTA - Agoda | F72: =COUNTIF(Bookings!$O$2:$O$5001,$E72) -> 361 | G72: =COUNTIFS(Bookings!$O$2:$O$5001,$E72,Bookings!$Q$2:$Q$5001,"Cancelled")/COUNTIF(Bookings!$O$2:$O$5001,$E72) -> 0.2299169 | H72: =AVERAGEIF(Bookings!$O$2:$O$5001,$E72,Bookings!$J$2:$J$5001) -> 46.67867 | I72: =AVERAGEIFS(Bookings!$S$2:$S$5001,Bookings!$O$2:$O$5001,$E72,Bookings!$Q$2:$Q$5001,"Completed") -> 48889.739 | K72: Deluxe | L72: =COUNTIF(Bookings!$K$2:$K$5001,$K72) -> 1859 | M72: =AVERAGEIFS(Bookings!$S$2:$S$5001,Bookings!$K$2:$K$5001,$K72,Bookings!$Q$2:$Q$5001,"Completed") -> 36364.673
B73: No-Show | C73: =COUNTIF(Bookings!$Q$2:$Q$5001,$B73) -> 137 | E73: Travel Agent | F73: =COUNTIF(Bookings!$O$2:$O$5001,$E73) -> 654 | G73: =COUNTIFS(Bookings!$O$2:$O$5001,$E73,Bookings!$Q$2:$Q$5001,"Cancelled")/COUNTIF(Bookings!$O$2:$O$5001,$E73) -> 0.1559633 | H73: =AVERAGEIF(Bookings!$O$2:$O$5001,$E73,Bookings!$J$2:$J$5001) -> 61.111621 | I73: =AVERAGEIFS(Bookings!$S$2:$S$5001,Bookings!$O$2:$O$5001,$E73,Bookings!$Q$2:$Q$5001,"Completed") -> 68903.289 | K73: Suite | L73: =COUNTIF(Bookings!$K$2:$K$5001,$K73) -> 1108 | M73: =AVERAGEIFS(Bookings!$S$2:$S$5001,Bookings!$K$2:$K$5001,$K73,Bookings!$Q$2:$Q$5001,"Completed") -> 58694.239
E74: Corporate Booking | F74: =COUNTIF(Bookings!$O$2:$O$5001,$E74) -> 664 | G74: =COUNTIFS(Bookings!$O$2:$O$5001,$E74,Bookings!$Q$2:$Q$5001,"Cancelled")/COUNTIF(Bookings!$O$2:$O$5001,$E74) -> 0.063253012 | H74: =AVERAGEIF(Bookings!$O$2:$O$5001,$E74,Bookings!$J$2:$J$5001) -> 12.537651 | I74: =AVERAGEIFS(Bookings!$S$2:$S$5001,Bookings!$O$2:$O$5001,$E74,Bookings!$Q$2:$Q$5001,"Completed") -> 24626.578 | K74: Premium Suite | L74: =COUNTIF(Bookings!$K$2:$K$5001,$K74) -> 452 | M74: =AVERAGEIFS(Bookings!$S$2:$S$5001,Bookings!$K$2:$K$5001,$K74,Bookings!$Q$2:$Q$5001,"Completed") -> 92554.244
E75: Mobile App | F75: =COUNTIF(Bookings!$O$2:$O$5001,$E75) -> 696 | G75: =COUNTIFS(Bookings!$O$2:$O$5001,$E75,Bookings!$Q$2:$Q$5001,"Cancelled")/COUNTIF(Bookings!$O$2:$O$5001,$E75) -> 0.11063218 | H75: =AVERAGEIF(Bookings!$O$2:$O$5001,$E75,Bookings!$J$2:$J$5001) -> 39.593391 | I75: =AVERAGEIFS(Bookings!$S$2:$S$5001,Bookings!$O$2:$O$5001,$E75,Bookings!$Q$2:$Q$5001,"Completed") -> 40032.862
E76: OTA - Booking.com | F76: =COUNTIF(Bookings!$O$2:$O$5001,$E76) -> 702 | G76: =COUNTIFS(Bookings!$O$2:$O$5001,$E76,Bookings!$Q$2:$Q$5001,"Cancelled")/COUNTIF(Bookings!$O$2:$O$5001,$E76) -> 0.26210826 | H76: =AVERAGEIF(Bookings!$O$2:$O$5001,$E76,Bookings!$J$2:$J$5001) -> 41.578348 | I76: =AVERAGEIFS(Bookings!$S$2:$S$5001,Bookings!$O$2:$O$5001,$E76,Bookings!$Q$2:$Q$5001,"Completed") -> 41444.311
E77: OTA - MakeMyTrip | F77: =COUNTIF(Bookings!$O$2:$O$5001,$E77) -> 896 | G77: =COUNTIFS(Bookings!$O$2:$O$5001,$E77,Bookings!$Q$2:$Q$5001,"Cancelled")/COUNTIF(Bookings!$O$2:$O$5001,$E77) -> 0.21763393 | H77: =AVERAGEIF(Bookings!$O$2:$O$5001,$E77,Bookings!$J$2:$J$5001) -> 44.733259 | I77: =AVERAGEIFS(Bookings!$S$2:$S$5001,Bookings!$O$2:$O$5001,$E77,Bookings!$Q$2:$Q$5001,"Completed") -> 44009.925
E78: Direct Website | F78: =COUNTIF(Bookings!$O$2:$O$5001,$E78) -> 897 | G78: =COUNTIFS(Bookings!$O$2:$O$5001,$E78,Bookings!$Q$2:$Q$5001,"Cancelled")/COUNTIF(Bookings!$O$2:$O$5001,$E78) -> 0.093645485 | H78: =AVERAGEIF(Bookings!$O$2:$O$5001,$E78,Bookings!$J$2:$J$5001) -> 41.801561 | I78: =AVERAGEIFS(Bookings!$S$2:$S$5001,Bookings!$O$2:$O$5001,$E78,Bookings!$Q$2:$Q$5001,"Completed") -> 41158.144
B81: By payment method | E81: By city | I81: By check-in month
B82: Payment | C82: Bookings | E82: City | F82: Bookings | G82: Cancel Rate | I82: Month | J82: Bookings | K82: Cancelled | L82: Completed Value (Lakh) | M82: Key
B83: UPI | C83: =COUNTIF(Bookings!$P$2:$P$5001,$B83) -> 1694 | E83: Kochi | F83: =COUNTIF(Bookings!$D$2:$D$5001,$E83) -> 515 | G83: =COUNTIFS(Bookings!$D$2:$D$5001,$E83,Bookings!$Q$2:$Q$5001,"Cancelled")/COUNTIF(Bookings!$D$2:$D$5001,$E83) -> 0.16699029 | I83: =TEXT($M83,"mmm yy") -> Oct 24 | J83: =COUNTIF(Bookings!$H$2:$H$5001,$M83) -> 212 | K83: =COUNTIFS(Bookings!$H$2:$H$5001,$M83,Bookings!$Q$2:$Q$5001,"Cancelled") -> 29 | L83: =SUMIFS(Bookings!$S$2:$S$5001,Bookings!$H$2:$H$5001,$M83,Bookings!$Q$2:$Q$5001,"Completed")/100000 -> 78.3475 | M83: 45566
B84: Credit Card | C84: =COUNTIF(Bookings!$P$2:$P$5001,$B84) -> 1383 | E84: New Delhi | F84: =COUNTIF(Bookings!$D$2:$D$5001,$E84) -> 474 | G84: =COUNTIFS(Bookings!$D$2:$D$5001,$E84,Bookings!$Q$2:$Q$5001,"Cancelled")/COUNTIF(Bookings!$D$2:$D$5001,$E84) -> 0.15611814 | I84: =TEXT($M84,"mmm yy") -> Nov 24 | J84: =COUNTIF(Bookings!$H$2:$H$5001,$M84) -> 217 | K84: =COUNTIFS(Bookings!$H$2:$H$5001,$M84,Bookings!$Q$2:$Q$5001,"Cancelled") -> 40 | L84: =SUMIFS(Bookings!$S$2:$S$5001,Bookings!$H$2:$H$5001,$M84,Bookings!$Q$2:$Q$5001,"Completed")/100000 -> 82.0815 | M84: 45597
B85: Debit Card | C85: =COUNTIF(Bookings!$P$2:$P$5001,$B85) -> 734 | E85: Agra | F85: =COUNTIF(Bookings!$D$2:$D$5001,$E85) -> 461 | G85: =COUNTIFS(Bookings!$D$2:$D$5001,$E85,Bookings!$Q$2:$Q$5001,"Cancelled")/COUNTIF(Bookings!$D$2:$D$5001,$E85) -> 0.17570499 | I85: =TEXT($M85,"mmm yy") -> Dec 24 | J85: =COUNTIF(Bookings!$H$2:$H$5001,$M85) -> 239 | K85: =COUNTIFS(Bookings!$H$2:$H$5001,$M85,Bookings!$Q$2:$Q$5001,"Cancelled") -> 41 | L85: =SUMIFS(Bookings!$S$2:$S$5001,Bookings!$H$2:$H$5001,$M85,Bookings!$Q$2:$Q$5001,"Completed")/100000 -> 91.4995 | M85: 45627
B86: Net Banking | C86: =COUNTIF(Bookings!$P$2:$P$5001,$B86) -> 494 | E86: Rishikesh | F86: =COUNTIF(Bookings!$D$2:$D$5001,$E86) -> 458 | G86: =COUNTIFS(Bookings!$D$2:$D$5001,$E86,Bookings!$Q$2:$Q$5001,"Cancelled")/COUNTIF(Bookings!$D$2:$D$5001,$E86) -> 0.1790393 | I86: =TEXT($M86,"mmm yy") -> Jan 25 | J86: =COUNTIF(Bookings!$H$2:$H$5001,$M86) -> 233 | K86: =COUNTIFS(Bookings!$H$2:$H$5001,$M86,Bookings!$Q$2:$Q$5001,"Cancelled") -> 34 | L86: =SUMIFS(Bookings!$S$2:$S$5001,Bookings!$H$2:$H$5001,$M86,Bookings!$Q$2:$Q$5001,"Completed")/100000 -> 105.4095 | M86: 45658
B87: Digital Wallet | C87: =COUNTIF(Bookings!$P$2:$P$5001,$B87) -> 401 | E87: Jaipur | F87: =COUNTIF(Bookings!$D$2:$D$5001,$E87) -> 454 | G87: =COUNTIFS(Bookings!$D$2:$D$5001,$E87,Bookings!$Q$2:$Q$5001,"Cancelled")/COUNTIF(Bookings!$D$2:$D$5001,$E87) -> 0.14537445 | I87: =TEXT($M87,"mmm yy") -> Feb 25 | J87: =COUNTIF(Bookings!$H$2:$H$5001,$M87) -> 288 | K87: =COUNTIFS(Bookings!$H$2:$H$5001,$M87,Bookings!$Q$2:$Q$5001,"Cancelled") -> 41 | L87: =SUMIFS(Bookings!$S$2:$S$5001,Bookings!$H$2:$H$5001,$M87,Bookings!$Q$2:$Q$5001,"Completed")/100000 -> 111.7295 | M87: 45689
B88: Cash | C88: =COUNTIF(Bookings!$P$2:$P$5001,$B88) -> 294 | E88: Goa | F88: =COUNTIF(Bookings!$D$2:$D$5001,$E88) -> 422 | G88: =COUNTIFS(Bookings!$D$2:$D$5001,$E88,Bookings!$Q$2:$Q$5001,"Cancelled")/COUNTIF(Bookings!$D$2:$D$5001,$E88) -> 0.16824645 | I88: =TEXT($M88,"mmm yy") -> Mar 25 | J88: =COUNTIF(Bookings!$H$2:$H$5001,$M88) -> 197 | K88: =COUNTIFS(Bookings!$H$2:$H$5001,$M88,Bookings!$Q$2:$Q$5001,"Cancelled") -> 28 | L88: =SUMIFS(Bookings!$S$2:$S$5001,Bookings!$H$2:$H$5001,$M88,Bookings!$Q$2:$Q$5001,"Completed")/100000 -> 63.721 | M88: 45717
E89: Shimla | F89: =COUNTIF(Bookings!$D$2:$D$5001,$E89) -> 402 | G89: =COUNTIFS(Bookings!$D$2:$D$5001,$E89,Bookings!$Q$2:$Q$5001,"Cancelled")/COUNTIF(Bookings!$D$2:$D$5001,$E89) -> 0.16169154 | I89: =TEXT($M89,"mmm yy") -> Apr 25 | J89: =COUNTIF(Bookings!$H$2:$H$5001,$M89) -> 175 | K89: =COUNTIFS(Bookings!$H$2:$H$5001,$M89,Bookings!$Q$2:$Q$5001,"Cancelled") -> 34 | L89: =SUMIFS(Bookings!$S$2:$S$5001,Bookings!$H$2:$H$5001,$M89,Bookings!$Q$2:$Q$5001,"Completed")/100000 -> 51.89 | M89: 45748
E90: Udaipur | F90: =COUNTIF(Bookings!$D$2:$D$5001,$E90) -> 399 | G90: =COUNTIFS(Bookings!$D$2:$D$5001,$E90,Bookings!$Q$2:$Q$5001,"Cancelled")/COUNTIF(Bookings!$D$2:$D$5001,$E90) -> 0.15789474 | I90: =TEXT($M90,"mmm yy") -> May 25 | J90: =COUNTIF(Bookings!$H$2:$H$5001,$M90) -> 189 | K90: =COUNTIFS(Bookings!$H$2:$H$5001,$M90,Bookings!$Q$2:$Q$5001,"Cancelled") -> 21 | L90: =SUMIFS(Bookings!$S$2:$S$5001,Bookings!$H$2:$H$5001,$M90,Bookings!$Q$2:$Q$5001,"Completed")/100000 -> 73.869 | M90: 45778
E91: Bengaluru | F91: =COUNTIF(Bookings!$D$2:$D$5001,$E91) -> 372 | G91: =COUNTIFS(Bookings!$D$2:$D$5001,$E91,Bookings!$Q$2:$Q$5001,"Cancelled")/COUNTIF(Bookings!$D$2:$D$5001,$E91) -> 0.11827957 | I91: =TEXT($M91,"mmm yy") -> Jun 25 | J91: =COUNTIF(Bookings!$H$2:$H$5001,$M91) -> 143 | K91: =COUNTIFS(Bookings!$H$2:$H$5001,$M91,Bookings!$Q$2:$Q$5001,"Cancelled") -> 13 | L91: =SUMIFS(Bookings!$S$2:$S$5001,Bookings!$H$2:$H$5001,$M91,Bookings!$Q$2:$Q$5001,"Completed")/100000 -> 38.826 | M91: 45809
E92: Manali | F92: =COUNTIF(Bookings!$D$2:$D$5001,$E92) -> 357 | G92: =COUNTIFS(Bookings!$D$2:$D$5001,$E92,Bookings!$Q$2:$Q$5001,"Cancelled")/COUNTIF(Bookings!$D$2:$D$5001,$E92) -> 0.10644258 | I92: =TEXT($M92,"mmm yy") -> Jul 25 | J92: =COUNTIF(Bookings!$H$2:$H$5001,$M92) -> 129 | K92: =COUNTIFS(Bookings!$H$2:$H$5001,$M92,Bookings!$Q$2:$Q$5001,"Cancelled") -> 18 | L92: =SUMIFS(Bookings!$S$2:$S$5001,Bookings!$H$2:$H$5001,$M92,Bookings!$Q$2:$Q$5001,"Completed")/100000 -> 42.963 | M92: 45839
E93: Varanasi | F93: =COUNTIF(Bookings!$D$2:$D$5001,$E93) -> 346 | G93: =COUNTIFS(Bookings!$D$2:$D$5001,$E93,Bookings!$Q$2:$Q$5001,"Cancelled")/COUNTIF(Bookings!$D$2:$D$5001,$E93) -> 0.13583815 | I93: =TEXT($M93,"mmm yy") -> Aug 25 | J93: =COUNTIF(Bookings!$H$2:$H$5001,$M93) -> 109 | K93: =COUNTIFS(Bookings!$H$2:$H$5001,$M93,Bookings!$Q$2:$Q$5001,"Cancelled") -> 19 | L93: =SUMIFS(Bookings!$S$2:$S$5001,Bookings!$H$2:$H$5001,$M93,Bookings!$Q$2:$Q$5001,"Completed")/100000 -> 26.5385 | M93: 45870
E94: Mumbai | F94: =COUNTIF(Bookings!$D$2:$D$5001,$E94) -> 340 | G94: =COUNTIFS(Bookings!$D$2:$D$5001,$E94,Bookings!$Q$2:$Q$5001,"Cancelled")/COUNTIF(Bookings!$D$2:$D$5001,$E94) -> 0.16176471 | I94: =TEXT($M94,"mmm yy") -> Sep 25 | J94: =COUNTIF(Bookings!$H$2:$H$5001,$M94) -> 146 | K94: =COUNTIFS(Bookings!$H$2:$H$5001,$M94,Bookings!$Q$2:$Q$5001,"Cancelled") -> 14 | L94: =SUMIFS(Bookings!$S$2:$S$5001,Bookings!$H$2:$H$5001,$M94,Bookings!$Q$2:$Q$5001,"Completed")/100000 -> 43.8735 | M94: 45901
I95: =TEXT($M95,"mmm yy") -> Oct 25 | J95: =COUNTIF(Bookings!$H$2:$H$5001,$M95) -> 259 | K95: =COUNTIFS(Bookings!$H$2:$H$5001,$M95,Bookings!$Q$2:$Q$5001,"Cancelled") -> 41 | L95: =SUMIFS(Bookings!$S$2:$S$5001,Bookings!$H$2:$H$5001,$M95,Bookings!$Q$2:$Q$5001,"Completed")/100000 -> 98.477 | M95: 45931
I96: =TEXT($M96,"mmm yy") -> Nov 25 | J96: =COUNTIF(Bookings!$H$2:$H$5001,$M96) -> 254 | K96: =COUNTIFS(Bookings!$H$2:$H$5001,$M96,Bookings!$Q$2:$Q$5001,"Cancelled") -> 41 | L96: =SUMIFS(Bookings!$S$2:$S$5001,Bookings!$H$2:$H$5001,$M96,Bookings!$Q$2:$Q$5001,"Completed")/100000 -> 100.507 | M96: 45962
I97: =TEXT($M97,"mmm yy") -> Dec 25 | J97: =COUNTIF(Bookings!$H$2:$H$5001,$M97) -> 321 | K97: =COUNTIFS(Bookings!$H$2:$H$5001,$M97,Bookings!$Q$2:$Q$5001,"Cancelled") -> 43 | L97: =SUMIFS(Bookings!$S$2:$S$5001,Bookings!$H$2:$H$5001,$M97,Bookings!$Q$2:$Q$5001,"Completed")/100000 -> 119.175 | M97: 45992
I98: =TEXT($M98,"mmm yy") -> Jan 26 | J98: =COUNTIF(Bookings!$H$2:$H$5001,$M98) -> 318 | K98: =COUNTIFS(Bookings!$H$2:$H$5001,$M98,Bookings!$Q$2:$Q$5001,"Cancelled") -> 53 | L98: =SUMIFS(Bookings!$S$2:$S$5001,Bookings!$H$2:$H$5001,$M98,Bookings!$Q$2:$Q$5001,"Completed")/100000 -> 119.4145 | M98: 46023
I99: =TEXT($M99,"mmm yy") -> Feb 26 | J99: =COUNTIF(Bookings!$H$2:$H$5001,$M99) -> 265 | K99: =COUNTIFS(Bookings!$H$2:$H$5001,$M99,Bookings!$Q$2:$Q$5001,"Cancelled") -> 39 | L99: =SUMIFS(Bookings!$S$2:$S$5001,Bookings!$H$2:$H$5001,$M99,Bookings!$Q$2:$Q$5001,"Completed")/100000 -> 108.7645 | M99: 46054
I100: =TEXT($M100,"mmm yy") -> Mar 26 | J100: =COUNTIF(Bookings!$H$2:$H$5001,$M100) -> 264 | K100: =COUNTIFS(Bookings!$H$2:$H$5001,$M100,Bookings!$Q$2:$Q$5001,"Cancelled") -> 53 | L100: =SUMIFS(Bookings!$S$2:$S$5001,Bookings!$H$2:$H$5001,$M100,Bookings!$Q$2:$Q$5001,"Completed")/100000 -> 95.0455 | M100: 46082
I101: =TEXT($M101,"mmm yy") -> Apr 26 | J101: =COUNTIF(Bookings!$H$2:$H$5001,$M101) -> 229 | K101: =COUNTIFS(Bookings!$H$2:$H$5001,$M101,Bookings!$Q$2:$Q$5001,"Cancelled") -> 48 | L101: =SUMIFS(Bookings!$S$2:$S$5001,Bookings!$H$2:$H$5001,$M101,Bookings!$Q$2:$Q$5001,"Completed")/100000 -> 70.164 | M101: 46113
I102: =TEXT($M102,"mmm yy") -> May 26 | J102: =COUNTIF(Bookings!$H$2:$H$5001,$M102) -> 239 | K102: =COUNTIFS(Bookings!$H$2:$H$5001,$M102,Bookings!$Q$2:$Q$5001,"Cancelled") -> 36 | L102: =SUMIFS(Bookings!$S$2:$S$5001,Bookings!$H$2:$H$5001,$M102,Bookings!$Q$2:$Q$5001,"Completed")/100000 -> 81.3385 | M102: 46143
I103: =TEXT($M103,"mmm yy") -> Jun 26 | J103: =COUNTIF(Bookings!$H$2:$H$5001,$M103) -> 166 | K103: =COUNTIFS(Bookings!$H$2:$H$5001,$M103,Bookings!$Q$2:$Q$5001,"Cancelled") -> 27 | L103: =SUMIFS(Bookings!$S$2:$S$5001,Bookings!$H$2:$H$5001,$M103,Bookings!$Q$2:$Q$5001,"Completed")/100000 -> 48.646 | M103: 46174
I104: =TEXT($M104,"mmm yy") -> Jul 26 | J104: =COUNTIF(Bookings!$H$2:$H$5001,$M104) -> 126 | K104: =COUNTIFS(Bookings!$H$2:$H$5001,$M104,Bookings!$Q$2:$Q$5001,"Cancelled") -> 14 | L104: =SUMIFS(Bookings!$S$2:$S$5001,Bookings!$H$2:$H$5001,$M104,Bookings!$Q$2:$Q$5001,"Completed")/100000 -> 28.5675 | M104: 46204
I105: =TEXT($M105,"mmm yy") -> Aug 26 | J105: =COUNTIF(Bookings!$H$2:$H$5001,$M105) -> 134 | K105: =COUNTIFS(Bookings!$H$2:$H$5001,$M105,Bookings!$Q$2:$Q$5001,"Cancelled") -> 23 | L105: =SUMIFS(Bookings!$S$2:$S$5001,Bookings!$H$2:$H$5001,$M105,Bookings!$Q$2:$Q$5001,"Completed")/100000 -> 41.27 | M105: 46235
I106: =TEXT($M106,"mmm yy") -> Sep 26 | J106: =COUNTIF(Bookings!$H$2:$H$5001,$M106) -> 148 | K106: =COUNTIFS(Bookings!$H$2:$H$5001,$M106,Bookings!$Q$2:$Q$5001,"Cancelled") -> 22 | L106: =SUMIFS(Bookings!$S$2:$S$5001,Bookings!$H$2:$H$5001,$M106,Bookings!$Q$2:$Q$5001,"Completed")/100000 -> 42.911 | M106: 46266

Sheet Revenue
A1: Booking_ID | B1: Customer_ID | C1: Hotel_ID | D1: City | E1: Stay_Month | F1: Channel | G1: Room_Nights | H1: Room_Revenue_INR | I1: FnB_Revenue_INR | J1: Spa_Revenue_INR | K1: Other_Revenue_INR | L1: Total_Revenue_INR | M1: Commission_Pct | N1: Commission_INR | O1: Net_Revenue_INR
A2: BK00001 | B2: C1269 | C2: H020 | D2: Mumbai | E2: 45566 | F2: Mobile App | G2: 6 | H2: 159000 | I2: 15590 | J2: 0 | K2: 0 | L2: =SUM(H2:K2) -> 174590 | M2: 0 | N2: =H2*M2 -> 0 | O2: =L2-N2 -> 174590
A3: BK00003 | B3: C0747 | C3: H014 | D3: Agra | E3: 45597 | F3: OTA - Agoda | G3: 3 | H3: 18600 | I3: 1070 | J3: 0 | K3: 0 | L3: =SUM(H3:K3) -> 19670 | M3: 0.16 | N3: =H3*M3 -> 2976 | O3: =L3-N3 -> 16694
A4: BK00004 | B4: C0547 | C4: H004 | D4: Goa | E4: 45627 | F4: Travel Agent | G4: 8 | H4: 111200 | I4: 9270 | J4: 5030 | K4: 0 | L4: =SUM(H4:K4) -> 125500 | M4: 0.1 | N4: =H4*M4 -> 11120 | O4: =L4-N4 -> 114380
A5: BK00005 | B5: C0702 | C5: H020 | D5: Mumbai | E5: 45566 | F5: Walk-in | G5: 4 | H5: 72200 | I5: 20160 | J5: 0 | K5: 2130 | L5: =SUM(H5:K5) -> 94490 | M5: 0 | N5: =H5*M5 -> 0 | O5: =L5-N5 -> 94490
A6: BK00007 | B6: C1337 | C6: H021 | D6: New Delhi | E6: 45597 | F6: Travel Agent | G6: 16 | H6: 400800 | I6: 11250 | J6: 0 | K6: 0 | L6: =SUM(H6:K6) -> 412050 | M6: 0.1 | N6: =H6*M6 -> 40080 | O6: =L6-N6 -> 371970
A7: BK00008 | B7: C0100 | C7: H030 | D7: Kochi | E7: 45566 | F7: Travel Agent | G7: 4 | H7: 22000 | I7: 5910 | J7: 6550 | K7: 0 | L7: =SUM(H7:K7) -> 34460 | M7: 0.1 | N7: =H7*M7 -> 2200 | O7: =L7-N7 -> 32260
A8: BK00009 | B8: C0062 | C8: H016 | D8: Agra | E8: 45627 | F8: Direct Website | G8: 5 | H8: 44750 | I8: 5760 | J8: 0 | K8: 0 | L8: =SUM(H8:K8) -> 50510 | M8: 0 | N8: =H8*M8 -> 0 | O8: =L8-N8 -> 50510
A9: BK00011 | B9: C1323 | C9: H005 | D9: Jaipur | E9: 45566 | F9: Mobile App | G9: 4 | H9: 20400 | I9: 4870 | J9: 0 | K9: 0 | L9: =SUM(H9:K9) -> 25270 | M9: 0 | N9: =H9*M9 -> 0 | O9: =L9-N9 -> 25270
A10: BK00014 | B10: C1002 | C10: H006 | D10: Jaipur | E10: 45658 | F10: Travel Agent | G10: 6 | H10: 190800 | I10: 2270 | J10: 0 | K10: 1650 | L10: =SUM(H10:K10) -> 194720 | M10: 0.1 | N10: =H10*M10 -> 19080 | O10: =L10-N10 -> 175640
A11: BK00015 | B11: C0011 | C11: H013 | D11: Agra | E11: 45658 | F11: Mobile App | G11: 2 | H11: 18400 | I11: 1960 | J11: 0 | K11: 0 | L11: =SUM(H11:K11) -> 20360 | M11: 0 | N11: =H11*M11 -> 0 | O11: =L11-N11 -> 20360
A12: BK00016 | B12: C0462 | C12: H009 | D12: Udaipur | E12: 45566 | F12: Travel Agent | G12: 12 | H12: 94800 | I12: 6460 | J12: 0 | K12: 2200 | L12: =SUM(H12:K12) -> 103460 | M12: 0.1 | N12: =H12*M12 -> 9480 | O12: =L12-N12 -> 93980
A13: BK00018 | B13: C1346 | C13: H043 | D13: Rishikesh | E13: 45627 | F13: Travel Agent | G13: 4 | H13: 27200 | I13: 8660 | J13: 6180 | K13: 1470 | L13: =SUM(H13:K13) -> 43510 | M13: 0.1 | N13: =H13*M13 -> 2720 | O13: =L13-N13 -> 40790
... A4092: BK05000 | B4092: C1223 | C4092: H006 | D4092: Jaipur | E4092: 46266 | F4092: OTA - Agoda | G4092: 2 | H4092: 20000 | I4092: 1770 | J4092: 0 | K4092: 0 | L4092: =SUM(H4092:K4092) -> 21770 | M4092: 0.16 | N4092: =H4092*M4092 -> 3200 | O4092: =L4092-N4092 -> 18570

Sheet Revenue_Dashboard
B1: Revenue - Dashboard
B3: Gross Revenue (Cr) | D3: Net Revenue (Cr) | F3: Commission (Cr) | H3: Ancillary Share | J3: Avg Revenue / Stay | L3: Room Nights | N3: Commission % of Gross
B4: =SUM(Revenue!$L$2:$L$4092)/10000000 -> 20.838432 | D4: =SUM(Revenue!$O$2:$O$4092)/10000000 -> 19.39282 | F4: =SUM(Revenue!$N$2:$N$4092)/10000000 -> 1.4456117 | H4: =1-SUM(Revenue!$H$2:$H$4092)/SUM(Revenue!$L$2:$L$4092) -> 0.15299337 | J4: =AVERAGE(Revenue!$L$2:$L$4092) -> 50937.257 | L4: =SUM(Revenue!$G$2:$G$4092) -> 15866 | N4: =SUM(Revenue!$N$2:$N$4092)/SUM(Revenue!$L$2:$L$4092) -> 0.069372381
B52: Chart data (live formulas - charts above read from these tables)
B54: By stay month | I54: Revenue mix | L54: By city
B55: Month | C55: Gross (Lakh) | D55: Net (Lakh) | E55: Commission (Lakh) | F55: Room Nights | G55: Key | I55: Stream | J55: Revenue (Cr) | L55: City | M55: Gross (Cr) | N55: Stays | O55: Avg / Stay
B56: =TEXT($G56,"mmm yy") -> Oct 24 | C56: =SUMIF(Revenue!$E$2:$E$4092,$G56,Revenue!$L$2:$L$4092)/100000 -> 92.0966 | D56: =SUMIF(Revenue!$E$2:$E$4092,$G56,Revenue!$O$2:$O$4092)/100000 -> 85.31832 | E56: =SUMIF(Revenue!$E$2:$E$4092,$G56,Revenue!$N$2:$N$4092)/100000 -> 6.77828 | F56: =SUMIF(Revenue!$E$2:$E$4092,$G56,Revenue!$G$2:$G$4092) -> 680 | G56: 45566 | I56: Room | J56: =SUM(Revenue!$H$2:$H$4092)/10000000 -> 17.65029 | L56: Varanasi | M56: =SUMIF(Revenue!$D$2:$D$4092,$L56,Revenue!$L$2:$L$4092)/10000000 -> 1.097568 | N56: =COUNTIF(Revenue!$D$2:$D$4092,$L56) -> 292 | O56: =SUMIF(Revenue!$D$2:$D$4092,$L56,Revenue!$L$2:$L$4092)/COUNTIF(Revenue!$D$2:$D$4092,$L56) -> 37587.945
B57: =TEXT($G57,"mmm yy") -> Nov 24 | C57: =SUMIF(Revenue!$E$2:$E$4092,$G57,Revenue!$L$2:$L$4092)/100000 -> 95.5519 | D57: =SUMIF(Revenue!$E$2:$E$4092,$G57,Revenue!$O$2:$O$4092)/100000 -> 89.41324 | E57: =SUMIF(Revenue!$E$2:$E$4092,$G57,Revenue!$N$2:$N$4092)/100000 -> 6.13866 | F57: =SUMIF(Revenue!$E$2:$E$4092,$G57,Revenue!$G$2:$G$4092) -> 659 | G57: 45597 | I57: F&B | J57: =SUM(Revenue!$I$2:$I$4092)/10000000 -> 2.266839 | L57: Shimla | M57: =SUMIF(Revenue!$D$2:$D$4092,$L57,Revenue!$L$2:$L$4092)/10000000 -> 1.2776 | N57: =COUNTIF(Revenue!$D$2:$D$4092,$L57) -> 327 | O57: =SUMIF(Revenue!$D$2:$D$4092,$L57,Revenue!$L$2:$L$4092)/COUNTIF(Revenue!$D$2:$D$4092,$L57) -> 39070.336
B58: =TEXT($G58,"mmm yy") -> Dec 24 | C58: =SUMIF(Revenue!$E$2:$E$4092,$G58,Revenue!$L$2:$L$4092)/100000 -> 105.893 | D58: =SUMIF(Revenue!$E$2:$E$4092,$G58,Revenue!$O$2:$O$4092)/100000 -> 98.3468 | E58: =SUMIF(Revenue!$E$2:$E$4092,$G58,Revenue!$N$2:$N$4092)/100000 -> 7.5462 | F58: =SUMIF(Revenue!$E$2:$E$4092,$G58,Revenue!$G$2:$G$4092) -> 766 | G58: 45627 | I58: Spa | J58: =SUM(Revenue!$J$2:$J$4092)/10000000 -> 0.695981 | L58: Manali | M58: =SUMIF(Revenue!$D$2:$D$4092,$L58,Revenue!$L$2:$L$4092)/10000000 -> 1.417134 | N58: =COUNTIF(Revenue!$D$2:$D$4092,$L58) -> 304 | O58: =SUMIF(Revenue!$D$2:$D$4092,$L58,Revenue!$L$2:$L$4092)/COUNTIF(Revenue!$D$2:$D$4092,$L58) -> 46616.25
B59: =TEXT($G59,"mmm yy") -> Jan 25 | C59: =SUMIF(Revenue!$E$2:$E$4092,$G59,Revenue!$L$2:$L$4092)/100000 -> 122.6831 | D59: =SUMIF(Revenue!$E$2:$E$4092,$G59,Revenue!$O$2:$O$4092)/100000 -> 113.87999 | E59: =SUMIF(Revenue!$E$2:$E$4092,$G59,Revenue!$N$2:$N$4092)/100000 -> 8.803115 | F59: =SUMIF(Revenue!$E$2:$E$4092,$G59,Revenue!$G$2:$G$4092) -> 802 | G59: 45658 | I59: Other | J59: =SUM(Revenue!$K$2:$K$4092)/10000000 -> 0.225322 | L59: Agra | M59: =SUMIF(Revenue!$D$2:$D$4092,$L59,Revenue!$L$2:$L$4092)/10000000 -> 1.538503 | N59: =COUNTIF(Revenue!$D$2:$D$4092,$L59) -> 371 | O59: =SUMIF(Revenue!$D$2:$D$4092,$L59,Revenue!$L$2:$L$4092)/COUNTIF(Revenue!$D$2:$D$4092,$L59) -> 41469.084
B60: =TEXT($G60,"mmm yy") -> Feb 25 | C60: =SUMIF(Revenue!$E$2:$E$4092,$G60,Revenue!$L$2:$L$4092)/100000 -> 130.0396 | D60: =SUMIF(Revenue!$E$2:$E$4092,$G60,Revenue!$O$2:$O$4092)/100000 -> 121.19155 | E60: =SUMIF(Revenue!$E$2:$E$4092,$G60,Revenue!$N$2:$N$4092)/100000 -> 8.848055 | F60: =SUMIF(Revenue!$E$2:$E$4092,$G60,Revenue!$G$2:$G$4092) -> 929 | G60: 45689 | L60: Rishikesh | M60: =SUMIF(Revenue!$D$2:$D$4092,$L60,Revenue!$L$2:$L$4092)/10000000 -> 1.56418 | N60: =COUNTIF(Revenue!$D$2:$D$4092,$L60) -> 363 | O60: =SUMIF(Revenue!$D$2:$D$4092,$L60,Revenue!$L$2:$L$4092)/COUNTIF(Revenue!$D$2:$D$4092,$L60) -> 43090.358
B61: =TEXT($G61,"mmm yy") -> Mar 25 | C61: =SUMIF(Revenue!$E$2:$E$4092,$G61,Revenue!$L$2:$L$4092)/100000 -> 77.3563 | D61: =SUMIF(Revenue!$E$2:$E$4092,$G61,Revenue!$O$2:$O$4092)/100000 -> 72.273365 | E61: =SUMIF(Revenue!$E$2:$E$4092,$G61,Revenue!$N$2:$N$4092)/100000 -> 5.082935 | F61: =SUMIF(Revenue!$E$2:$E$4092,$G61,Revenue!$G$2:$G$4092) -> 593 | G61: 45717 | L61: Bengaluru | M61: =SUMIF(Revenue!$D$2:$D$4092,$L61,Revenue!$L$2:$L$4092)/10000000 -> 1.789945 | N61: =COUNTIF(Revenue!$D$2:$D$4092,$L61) -> 313 | O61: =SUMIF(Revenue!$D$2:$D$4092,$L61,Revenue!$L$2:$L$4092)/COUNTIF(Revenue!$D$2:$D$4092,$L61) -> 57186.741
B62: =TEXT($G62,"mmm yy") -> Apr 25 | C62: =SUMIF(Revenue!$E$2:$E$4092,$G62,Revenue!$L$2:$L$4092)/100000 -> 62.5535 | D62: =SUMIF(Revenue!$E$2:$E$4092,$G62,Revenue!$O$2:$O$4092)/100000 -> 57.962025 | E62: =SUMIF(Revenue!$E$2:$E$4092,$G62,Revenue!$N$2:$N$4092)/100000 -> 4.591475 | F62: =SUMIF(Revenue!$E$2:$E$4092,$G62,Revenue!$G$2:$G$4092) -> 504 | G62: 45748 | L62: Jaipur | M62: =SUMIF(Revenue!$D$2:$D$4092,$L62,Revenue!$L$2:$L$4092)/10000000 -> 1.828537 | N62: =COUNTIF(Revenue!$D$2:$D$4092,$L62) -> 373 | O62: =SUMIF(Revenue!$D$2:$D$4092,$L62,Revenue!$L$2:$L$4092)/COUNTIF(Revenue!$D$2:$D$4092,$L62) -> 49022.44
B63: =TEXT($G63,"mmm yy") -> May 25 | C63: =SUMIF(Revenue!$E$2:$E$4092,$G63,Revenue!$L$2:$L$4092)/100000 -> 87.4262 | D63: =SUMIF(Revenue!$E$2:$E$4092,$G63,Revenue!$O$2:$O$4092)/100000 -> 81.645415 | E63: =SUMIF(Revenue!$E$2:$E$4092,$G63,Revenue!$N$2:$N$4092)/100000 -> 5.780785 | F63: =SUMIF(Revenue!$E$2:$E$4092,$G63,Revenue!$G$2:$G$4092) -> 626 | G63: 45778 | L63: Goa | M63: =SUMIF(Revenue!$D$2:$D$4092,$L63,Revenue!$L$2:$L$4092)/10000000 -> 1.9095 | N63: =COUNTIF(Revenue!$D$2:$D$4092,$L63) -> 346 | O63: =SUMIF(Revenue!$D$2:$D$4092,$L63,Revenue!$L$2:$L$4092)/COUNTIF(Revenue!$D$2:$D$4092,$L63) -> 55187.861
B64: =TEXT($G64,"mmm yy") -> Jun 25 | C64: =SUMIF(Revenue!$E$2:$E$4092,$G64,Revenue!$L$2:$L$4092)/100000 -> 48.1573 | D64: =SUMIF(Revenue!$E$2:$E$4092,$G64,Revenue!$O$2:$O$4092)/100000 -> 45.557605 | E64: =SUMIF(Revenue!$E$2:$E$4092,$G64,Revenue!$N$2:$N$4092)/100000 -> 2.599695 | F64: =SUMIF(Revenue!$E$2:$E$4092,$G64,Revenue!$G$2:$G$4092) -> 438 | G64: 45809 | L64: Udaipur | M64: =SUMIF(Revenue!$D$2:$D$4092,$L64,Revenue!$L$2:$L$4092)/10000000 -> 1.928092 | N64: =COUNTIF(Revenue!$D$2:$D$4092,$L64) -> 325 | O64: =SUMIF(Revenue!$D$2:$D$4092,$L64,Revenue!$L$2:$L$4092)/COUNTIF(Revenue!$D$2:$D$4092,$L64) -> 59325.908
B65: =TEXT($G65,"mmm yy") -> Jul 25 | C65: =SUMIF(Revenue!$E$2:$E$4092,$G65,Revenue!$L$2:$L$4092)/100000 -> 52.0091 | D65: =SUMIF(Revenue!$E$2:$E$4092,$G65,Revenue!$O$2:$O$4092)/100000 -> 48.267245 | E65: =SUMIF(Revenue!$E$2:$E$4092,$G65,Revenue!$N$2:$N$4092)/100000 -> 3.741855 | F65: =SUMIF(Revenue!$E$2:$E$4092,$G65,Revenue!$G$2:$G$4092) -> 455 | G65: 45839 | L65: Mumbai | M65: =SUMIF(Revenue!$D$2:$D$4092,$L65,Revenue!$L$2:$L$4092)/10000000 -> 1.973138 | N65: =COUNTIF(Revenue!$D$2:$D$4092,$L65) -> 273 | O65: =SUMIF(Revenue!$D$2:$D$4092,$L65,Revenue!$L$2:$L$4092)/COUNTIF(Revenue!$D$2:$D$4092,$L65) -> 72276.117
B66: =TEXT($G66,"mmm yy") -> Aug 25 | C66: =SUMIF(Revenue!$E$2:$E$4092,$G66,Revenue!$L$2:$L$4092)/100000 -> 33.113 | D66: =SUMIF(Revenue!$E$2:$E$4092,$G66,Revenue!$O$2:$O$4092)/100000 -> 31.199655 | E66: =SUMIF(Revenue!$E$2:$E$4092,$G66,Revenue!$N$2:$N$4092)/100000 -> 1.913345 | F66: =SUMIF(Revenue!$E$2:$E$4092,$G66,Revenue!$G$2:$G$4092) -> 324 | G66: 45870 | L66: Kochi | M66: =SUMIF(Revenue!$D$2:$D$4092,$L66,Revenue!$L$2:$L$4092)/10000000 -> 2.067608 | N66: =COUNTIF(Revenue!$D$2:$D$4092,$L66) -> 417 | O66: =SUMIF(Revenue!$D$2:$D$4092,$L66,Revenue!$L$2:$L$4092)/COUNTIF(Revenue!$D$2:$D$4092,$L66) -> 49582.926
B67: =TEXT($G67,"mmm yy") -> Sep 25 | C67: =SUMIF(Revenue!$E$2:$E$4092,$G67,Revenue!$L$2:$L$4092)/100000 -> 55.1641 | D67: =SUMIF(Revenue!$E$2:$E$4092,$G67,Revenue!$O$2:$O$4092)/100000 -> 51.93477 | E67: =SUMIF(Revenue!$E$2:$E$4092,$G67,Revenue!$N$2:$N$4092)/100000 -> 3.22933 | F67: =SUMIF(Revenue!$E$2:$E$4092,$G67,Revenue!$G$2:$G$4092) -> 534 | G67: 45901 | L67: New Delhi | M67: =SUMIF(Revenue!$D$2:$D$4092,$L67,Revenue!$L$2:$L$4092)/10000000 -> 2.446627 | N67: =COUNTIF(Revenue!$D$2:$D$4092,$L67) -> 387 | O67: =SUMIF(Revenue!$D$2:$D$4092,$L67,Revenue!$L$2:$L$4092)/COUNTIF(Revenue!$D$2:$D$4092,$L67) -> 63220.336
B68: =TEXT($G68,"mmm yy") -> Oct 25 | C68: =SUMIF(Revenue!$E$2:$E$4092,$G68,Revenue!$L$2:$L$4092)/100000 -> 114.8843 | D68: =SUMIF(Revenue!$E$2:$E$4092,$G68,Revenue!$O$2:$O$4092)/100000 -> 106.40882 | E68: =SUMIF(Revenue!$E$2:$E$4092,$G68,Revenue!$N$2:$N$4092)/100000 -> 8.47548 | F68: =SUMIF(Revenue!$E$2:$E$4092,$G68,Revenue!$G$2:$G$4092) -> 828 | G68: 45931
B69: =TEXT($G69,"mmm yy") -> Nov 25 | C69: =SUMIF(Revenue!$E$2:$E$4092,$G69,Revenue!$L$2:$L$4092)/100000 -> 117.3513 | D69: =SUMIF(Revenue!$E$2:$E$4092,$G69,Revenue!$O$2:$O$4092)/100000 -> 110.20204 | E69: =SUMIF(Revenue!$E$2:$E$4092,$G69,Revenue!$N$2:$N$4092)/100000 -> 7.14926 | F69: =SUMIF(Revenue!$E$2:$E$4092,$G69,Revenue!$G$2:$G$4092) -> 799 | G69: 45962
B70: =TEXT($G70,"mmm yy") -> Dec 25 | C70: =SUMIF(Revenue!$E$2:$E$4092,$G70,Revenue!$L$2:$L$4092)/100000 -> 139.3968 | D70: =SUMIF(Revenue!$E$2:$E$4092,$G70,Revenue!$O$2:$O$4092)/100000 -> 129.1721 | E70: =SUMIF(Revenue!$E$2:$E$4092,$G70,Revenue!$N$2:$N$4092)/100000 -> 10.224695 | F70: =SUMIF(Revenue!$E$2:$E$4092,$G70,Revenue!$G$2:$G$4092) -> 1037 | G70: 45992
B71: =TEXT($G71,"mmm yy") -> Jan 26 | C71: =SUMIF(Revenue!$E$2:$E$4092,$G71,Revenue!$L$2:$L$4092)/100000 -> 137.7538 | D71: =SUMIF(Revenue!$E$2:$E$4092,$G71,Revenue!$O$2:$O$4092)/100000 -> 127.28205 | E71: =SUMIF(Revenue!$E$2:$E$4092,$G71,Revenue!$N$2:$N$4092)/100000 -> 10.471745 | F71: =SUMIF(Revenue!$E$2:$E$4092,$G71,Revenue!$G$2:$G$4092) -> 978 | G71: 46023
B72: =TEXT($G72,"mmm yy") -> Feb 26 | C72: =SUMIF(Revenue!$E$2:$E$4092,$G72,Revenue!$L$2:$L$4092)/100000 -> 125.5117 | D72: =SUMIF(Revenue!$E$2:$E$4092,$G72,Revenue!$O$2:$O$4092)/100000 -> 116.34386 | E72: =SUMIF(Revenue!$E$2:$E$4092,$G72,Revenue!$N$2:$N$4092)/100000 -> 9.167845 | F72: =SUMIF(Revenue!$E$2:$E$4092,$G72,Revenue!$G$2:$G$4092) -> 845 | G72: 46054
B73: =TEXT($G73,"mmm yy") -> Mar 26 | C73: =SUMIF(Revenue!$E$2:$E$4092,$G73,Revenue!$L$2:$L$4092)/100000 -> 110.5096 | D73: =SUMIF(Revenue!$E$2:$E$4092,$G73,Revenue!$O$2:$O$4092)/100000 -> 102.52057 | E73: =SUMIF(Revenue!$E$2:$E$4092,$G73,Revenue!$N$2:$N$4092)/100000 -> 7.989025 | F73: =SUMIF(Revenue!$E$2:$E$4092,$G73,Revenue!$G$2:$G$4092) -> 751 | G73: 46082
B74: =TEXT($G74,"mmm yy") -> Apr 26 | C74: =SUMIF(Revenue!$E$2:$E$4092,$G74,Revenue!$L$2:$L$4092)/100000 -> 83.0251 | D74: =SUMIF(Revenue!$E$2:$E$4092,$G74,Revenue!$O$2:$O$4092)/100000 -> 76.755805 | E74: =SUMIF(Revenue!$E$2:$E$4092,$G74,Revenue!$N$2:$N$4092)/100000 -> 6.269295 | F74: =SUMIF(Revenue!$E$2:$E$4092,$G74,Revenue!$G$2:$G$4092) -> 691 | G74: 46113
B75: =TEXT($G75,"mmm yy") -> May 26 | C75: =SUMIF(Revenue!$E$2:$E$4092,$G75,Revenue!$L$2:$L$4092)/100000 -> 95.7539 | D75: =SUMIF(Revenue!$E$2:$E$4092,$G75,Revenue!$O$2:$O$4092)/100000 -> 88.27137 | E75: =SUMIF(Revenue!$E$2:$E$4092,$G75,Revenue!$N$2:$N$4092)/100000 -> 7.48253 | F75: =SUMIF(Revenue!$E$2:$E$4092,$G75,Revenue!$G$2:$G$4092) -> 774 | G75: 46143
B76: =TEXT($G76,"mmm yy") -> Jun 26 | C76: =SUMIF(Revenue!$E$2:$E$4092,$G76,Revenue!$L$2:$L$4092)/100000 -> 58.3623 | D76: =SUMIF(Revenue!$E$2:$E$4092,$G76,Revenue!$O$2:$O$4092)/100000 -> 54.69573 | E76: =SUMIF(Revenue!$E$2:$E$4092,$G76,Revenue!$N$2:$N$4092)/100000 -> 3.66657 | F76: =SUMIF(Revenue!$E$2:$E$4092,$G76,Revenue!$G$2:$G$4092) -> 540 | G76: 46174
B77: =TEXT($G77,"mmm yy") -> Jul 26 | C77: =SUMIF(Revenue!$E$2:$E$4092,$G77,Revenue!$L$2:$L$4092)/100000 -> 36.1165 | D77: =SUMIF(Revenue!$E$2:$E$4092,$G77,Revenue!$O$2:$O$4092)/100000 -> 33.792555 | E77: =SUMIF(Revenue!$E$2:$E$4092,$G77,Revenue!$N$2:$N$4092)/100000 -> 2.323945 | F77: =SUMIF(Revenue!$E$2:$E$4092,$G77,Revenue!$G$2:$G$4092) -> 379 | G77: 46204
B78: =TEXT($G78,"mmm yy") -> Aug 26 | C78: =SUMIF(Revenue!$E$2:$E$4092,$G78,Revenue!$L$2:$L$4092)/100000 -> 51.1104 | D78: =SUMIF(Revenue!$E$2:$E$4092,$G78,Revenue!$O$2:$O$4092)/100000 -> 48.16393 | E78: =SUMIF(Revenue!$E$2:$E$4092,$G78,Revenue!$N$2:$N$4092)/100000 -> 2.94647 | F78: =SUMIF(Revenue!$E$2:$E$4092,$G78,Revenue!$G$2:$G$4092) -> 444 | G78: 46235
B79: =TEXT($G79,"mmm yy") -> Sep 26 | C79: =SUMIF(Revenue!$E$2:$E$4092,$G79,Revenue!$L$2:$L$4092)/100000 -> 52.0238 | D79: =SUMIF(Revenue!$E$2:$E$4092,$G79,Revenue!$O$2:$O$4092)/100000 -> 48.683225 | E79: =SUMIF(Revenue!$E$2:$E$4092,$G79,Revenue!$N$2:$N$4092)/100000 -> 3.340575 | F79: =SUMIF(Revenue!$E$2:$E$4092,$G79,Revenue!$G$2:$G$4092) -> 490 | G79: 46266
B82: By channel
B83: Channel | C83: Gross (Cr) | D83: Commission (Cr) | E83: Commission %
B84: Walk-in | C84: =SUMIF(Revenue!$F$2:$F$4092,$B84,Revenue!$L$2:$L$4092)/10000000 -> 0.611855 | D84: =SUMIF(Revenue!$F$2:$F$4092,$B84,Revenue!$N$2:$N$4092)/10000000 -> 0 | E84: =SUMIF(Revenue!$F$2:$F$4092,$B84,Revenue!$N$2:$N$4092)/SUMIF(Revenue!$F$2:$F$4092,$B84,Revenue!$L$2:$L$4092) -> 0
B85: OTA - Agoda | C85: =SUMIF(Revenue!$F$2:$F$4092,$B85,Revenue!$L$2:$L$4092)/10000000 -> 1.554501 | D85: =SUMIF(Revenue!$F$2:$F$4092,$B85,Revenue!$N$2:$N$4092)/10000000 -> 0.2096392 | E85: =SUMIF(Revenue!$F$2:$F$4092,$B85,Revenue!$N$2:$N$4092)/SUMIF(Revenue!$F$2:$F$4092,$B85,Revenue!$L$2:$L$4092) -> 0.13485948
B86: Corporate Booking | C86: =SUMIF(Revenue!$F$2:$F$4092,$B86,Revenue!$L$2:$L$4092)/10000000 -> 1.712247 | D86: =SUMIF(Revenue!$F$2:$F$4092,$B86,Revenue!$N$2:$N$4092)/10000000 -> 0.074126 | E86: =SUMIF(Revenue!$F$2:$F$4092,$B86,Revenue!$N$2:$N$4092)/SUMIF(Revenue!$F$2:$F$4092,$B86,Revenue!$L$2:$L$4092) -> 0.043291651
B87: OTA - Booking.com | C87: =SUMIF(Revenue!$F$2:$F$4092,$B87,Revenue!$L$2:$L$4092)/10000000 -> 2.467977 | D87: =SUMIF(Revenue!$F$2:$F$4092,$B87,Revenue!$N$2:$N$4092)/10000000 -> 0.3529812 | E87: =SUMIF(Revenue!$F$2:$F$4092,$B87,Revenue!$N$2:$N$4092)/SUMIF(Revenue!$F$2:$F$4092,$B87,Revenue!$L$2:$L$4092) -> 0.14302451
B88: Mobile App | C88: =SUMIF(Revenue!$F$2:$F$4092,$B88,Revenue!$L$2:$L$4092)/10000000 -> 2.870666 | D88: =SUMIF(Revenue!$F$2:$F$4092,$B88,Revenue!$N$2:$N$4092)/10000000 -> 0 | E88: =SUMIF(Revenue!$F$2:$F$4092,$B88,Revenue!$N$2:$N$4092)/SUMIF(Revenue!$F$2:$F$4092,$B88,Revenue!$L$2:$L$4092) -> 0
B89: OTA - MakeMyTrip | C89: =SUMIF(Revenue!$F$2:$F$4092,$B89,Revenue!$L$2:$L$4092)/10000000 -> 3.470034 | D89: =SUMIF(Revenue!$F$2:$F$4092,$B89,Revenue!$N$2:$N$4092)/10000000 -> 0.44229975 | E89: =SUMIF(Revenue!$F$2:$F$4092,$B89,Revenue!$N$2:$N$4092)/SUMIF(Revenue!$F$2:$F$4092,$B89,Revenue!$L$2:$L$4092) -> 0.12746266
B90: Direct Website | C90: =SUMIF(Revenue!$F$2:$F$4092,$B90,Revenue!$L$2:$L$4092)/10000000 -> 3.878794 | D90: =SUMIF(Revenue!$F$2:$F$4092,$B90,Revenue!$N$2:$N$4092)/10000000 -> 0 | E90: =SUMIF(Revenue!$F$2:$F$4092,$B90,Revenue!$N$2:$N$4092)/SUMIF(Revenue!$F$2:$F$4092,$B90,Revenue!$L$2:$L$4092) -> 0
B91: Travel Agent | C91: =SUMIF(Revenue!$F$2:$F$4092,$B91,Revenue!$L$2:$L$4092)/10000000 -> 4.272358 | D91: =SUMIF(Revenue!$F$2:$F$4092,$B91,Revenue!$N$2:$N$4092)/10000000 -> 0.3665655 | E91: =SUMIF(Revenue!$F$2:$F$4092,$B91,Revenue!$N$2:$N$4092)/SUMIF(Revenue!$F$2:$F$4092,$B91,Revenue!$L$2:$L$4092) -> 0.085799341

Sheet Reviews
A1: Review_ID | B1: Booking_ID | C1: Customer_ID | D1: Hotel_ID | E1: Review_Date | F1: Overall_Rating | G1: Cleanliness | H1: Service | I1: Location | J1: Value_For_Money | K1: Likelihood_To_Recommend | L1: Sentiment | M1: NPS_Category | N1: Review_Source
A2: RV00001 | B2: BK00005 | C2: C0702 | D2: H020 | E2: 45573 | F2: 5 | G2: 5 | H2: 4 | I2: 5 | J2: 5 | K2: 8 | L2: =IF(F2>=4,"Positive",IF(F2=3,"Neutral","Negative")) -> Positive | M2: =IF(K2>=9,"Promoter",IF(K2>=7,"Passive","Detractor")) -> Passive | N2: Booking.com
A3: RV00002 | B3: BK00109 | C3: C0649 | D3: H031 | E3: 45573 | F3: 5 | G3: 5 | H3: 4 | I3: 5 | J3: 4 | K3: 9 | L3: =IF(F3>=4,"Positive",IF(F3=3,"Neutral","Negative")) -> Positive | M3: =IF(K3>=9,"Promoter",IF(K3>=7,"Passive","Detractor")) -> Promoter | N3: TripAdvisor
A4: RV00003 | B4: BK00142 | C4: C1017 | D4: H010 | E4: 45573 | F4: 4 | G4: 5 | H4: 5 | I4: 4 | J4: 4 | K4: 7 | L4: =IF(F4>=4,"Positive",IF(F4=3,"Neutral","Negative")) -> Positive | M4: =IF(K4>=9,"Promoter",IF(K4>=7,"Passive","Detractor")) -> Passive | N4: MakeMyTrip
A5: RV00004 | B5: BK00291 | C5: C0422 | D5: H033 | E5: 45573 | F5: 3 | G5: 3 | H5: 2 | I5: 2 | J5: 4 | K5: 7 | L5: =IF(F5>=4,"Positive",IF(F5=3,"Neutral","Negative")) -> Neutral | M5: =IF(K5>=9,"Promoter",IF(K5>=7,"Passive","Detractor")) -> Passive | N5: Booking.com
A6: RV00005 | B6: BK00272 | C6: C1478 | D6: H029 | E6: 45574 | F6: 5 | G6: 5 | H6: 5 | I6: 5 | J6: 4 | K6: 9 | L6: =IF(F6>=4,"Positive",IF(F6=3,"Neutral","Negative")) -> Positive | M6: =IF(K6>=9,"Promoter",IF(K6>=7,"Passive","Detractor")) -> Promoter | N6: Booking.com
A7: RV00006 | B7: BK00173 | C7: C1371 | D7: H048 | E7: 45575 | F7: 5 | G7: 5 | H7: 4 | I7: 5 | J7: 5 | K7: 9 | L7: =IF(F7>=4,"Positive",IF(F7=3,"Neutral","Negative")) -> Positive | M7: =IF(K7>=9,"Promoter",IF(K7>=7,"Passive","Detractor")) -> Promoter | N7: Booking.com
A8: RV00007 | B8: BK00216 | C8: C1261 | D8: H013 | E8: 45576 | F8: 3 | G8: 4 | H8: 3 | I8: 3 | J8: 3 | K8: 6 | L8: =IF(F8>=4,"Positive",IF(F8=3,"Neutral","Negative")) -> Neutral | M8: =IF(K8>=9,"Promoter",IF(K8>=7,"Passive","Detractor")) -> Detractor | N8: TripAdvisor
A9: RV00008 | B9: BK00191 | C9: C0243 | D9: H012 | E9: 45577 | F9: 3 | G9: 3 | H9: 3 | I9: 4 | J9: 2 | K9: 6 | L9: =IF(F9>=4,"Positive",IF(F9=3,"Neutral","Negative")) -> Neutral | M9: =IF(K9>=9,"Promoter",IF(K9>=7,"Passive","Detractor")) -> Detractor | N9: Google
A10: RV00009 | B10: BK00290 | C10: C0415 | D10: H010 | E10: 45577 | F10: 5 | G10: 5 | H10: 5 | I10: 4 | J10: 5 | K10: 8 | L10: =IF(F10>=4,"Positive",IF(F10=3,"Neutral","Negative")) -> Positive | M10: =IF(K10>=9,"Promoter",IF(K10>=7,"Passive","Detractor")) -> Passive | N10: Google
A11: RV00010 | B11: BK00001 | C11: C1269 | D11: H020 | E11: 45578 | F11: 3 | G11: 2 | H11: 4 | I11: 3 | J11: 3 | K11: 5 | L11: =IF(F11>=4,"Positive",IF(F11=3,"Neutral","Negative")) -> Neutral | M11: =IF(K11>=9,"Promoter",IF(K11>=7,"Passive","Detractor")) -> Detractor | N11: TripAdvisor
A12: RV00011 | B12: BK00140 | C12: C1367 | D12: H027 | E12: 45578 | F12: 5 | G12: 5 | H12: 4 | I12: 5 | J12: 4 | K12: 10 | L12: =IF(F12>=4,"Positive",IF(F12=3,"Neutral","Negative")) -> Positive | M12: =IF(K12>=9,"Promoter",IF(K12>=7,"Passive","Detractor")) -> Promoter | N12: MakeMyTrip
A13: RV00012 | B13: BK00181 | C13: C1054 | D13: H009 | E13: 45578 | F13: 4 | G13: 4 | H13: 5 | I13: 4 | J13: 4 | K13: 7 | L13: =IF(F13>=4,"Positive",IF(F13=3,"Neutral","Negative")) -> Positive | M13: =IF(K13>=9,"Promoter",IF(K13>=7,"Passive","Detractor")) -> Passive | N13: Google
... A2582: RV02581 | B2582: BK05000 | C2582: C1223 | D2582: H006 | E2582: 46300 | F2582: 5 | G2582: 5 | H2582: 5 | I2582: 5 | J2582: 5 | K2582: 9 | L2582: =IF(F2582>=4,"Positive",IF(F2582=3,"Neutral","Negative")) -> Positive | M2582: =IF(K2582>=9,"Promoter",IF(K2582>=7,"Passive","Detractor")) -> Promoter | N2582: TripAdvisor

Sheet Reviews_Dashboard
B1: Reviews - Dashboard
B3: Total Reviews | D3: Avg Overall Rating | F3: NPS | H3: Positive Sentiment | J3: Promoters | L3: Detractors | N3: Avg Likelihood to Recommend
B4: =COUNTA(Reviews!$A$2:$A$2582) -> 2581 | D4: =AVERAGE(Reviews!$F$2:$F$2582) -> 4.105773 | F4: =(COUNTIF(Reviews!$M$2:$M$2582,"Promoter")-COUNTIF(Reviews!$M$2:$M$2582,"Detractor"))/COUNTA(Reviews!$A$2:$A$2582)*100 -> 22.394421 | H4: =COUNTIF(Reviews!$L$2:$L$2582,"Positive")/COUNTA(Reviews!$A$2:$A$2582) -> 0.77799303 | J4: =COUNTIF(Reviews!$M$2:$M$2582,"Promoter")/COUNTA(Reviews!$A$2:$A$2582) -> 0.37853545 | L4: =COUNTIF(Reviews!$M$2:$M$2582,"Detractor")/COUNTA(Reviews!$A$2:$A$2582) -> 0.15459124 | N4: =AVERAGE(Reviews!$K$2:$K$2582) -> 7.8426966
B52: Chart data (live formulas - charts above read from these tables)
B54: Rating distribution | E54: NPS category | H54: Sentiment | K54: Avg score by category
B55: Stars | C55: Reviews | E55: Category | F55: Reviews | H55: Sentiment | I55: Reviews | K55: Category | L55: Avg (1-5)
B56: 5 | C56: =COUNTIF(Reviews!$F$2:$F$2582,$B56) -> 926 | E56: Promoter | F56: =COUNTIF(Reviews!$M$2:$M$2582,$E56) -> 977 | H56: Positive | I56: =COUNTIF(Reviews!$L$2:$L$2582,$H56) -> 2008 | K56: Overall | L56: =AVERAGE(Reviews!$F$2:$F$2582) -> 4.105773
B57: 4 | C57: =COUNTIF(Reviews!$F$2:$F$2582,$B57) -> 1082 | E57: Passive | F57: =COUNTIF(Reviews!$M$2:$M$2582,$E57) -> 1205 | H57: Neutral | I57: =COUNTIF(Reviews!$L$2:$L$2582,$H57) -> 495 | K57: Cleanliness | L57: =AVERAGE(Reviews!$G$2:$G$2582) -> 4.0464936
B58: 3 | C58: =COUNTIF(Reviews!$F$2:$F$2582,$B58) -> 495 | E58: Detractor | F58: =COUNTIF(Reviews!$M$2:$M$2582,$E58) -> 399 | H58: Negative | I58: =COUNTIF(Reviews!$L$2:$L$2582,$H58) -> 78 | K58: Service | L58: =AVERAGE(Reviews!$H$2:$H$2582) -> 4.0267338
B59: 2 | C59: =COUNTIF(Reviews!$F$2:$F$2582,$B59) -> 76 | K59: Location | L59: =AVERAGE(Reviews!$I$2:$I$2582) -> 4.0085238
B60: 1 | C60: =COUNTIF(Reviews!$F$2:$F$2582,$B60) -> 2 | K60: Value | L60: =AVERAGE(Reviews!$J$2:$J$2582) -> 4.0151104
B63: By review source | F63: Likelihood to recommend
B64: Source | C64: Reviews | D64: Avg Rating | F64: Score | G64: Reviews
B65: Google | C65: =COUNTIF(Reviews!$N$2:$N$2582,$B65) -> 886 | D65: =AVERAGEIF(Reviews!$N$2:$N$2582,$B65,Reviews!$F$2:$F$2582) -> 4.1365688 | F65: 0 | G65: =COUNTIF(Reviews!$K$2:$K$2582,$F65) -> 0
B66: TripAdvisor | C66: =COUNTIF(Reviews!$N$2:$N$2582,$B66) -> 630 | D66: =AVERAGEIF(Reviews!$N$2:$N$2582,$B66,Reviews!$F$2:$F$2582) -> 4.0603175 | F66: 1 | G66: =COUNTIF(Reviews!$K$2:$K$2582,$F66) -> 1
B67: Booking.com | C67: =COUNTIF(Reviews!$N$2:$N$2582,$B67) -> 415 | D67: =AVERAGEIF(Reviews!$N$2:$N$2582,$B67,Reviews!$F$2:$F$2582) -> 4.0481928 | F67: 2 | G67: =COUNTIF(Reviews!$K$2:$K$2582,$F67) -> 16
B68: MakeMyTrip | C68: =COUNTIF(Reviews!$N$2:$N$2582,$B68) -> 375 | D68: =AVERAGEIF(Reviews!$N$2:$N$2582,$B68,Reviews!$F$2:$F$2582) -> 4.1546667 | F68: 3 | G68: =COUNTIF(Reviews!$K$2:$K$2582,$F68) -> 23
B69: Hotel Website | C69: =COUNTIF(Reviews!$N$2:$N$2582,$B69) -> 275 | D69: =AVERAGEIF(Reviews!$N$2:$N$2582,$B69,Reviews!$F$2:$F$2582) -> 4.1309091 | F69: 4 | G69: =COUNTIF(Reviews!$K$2:$K$2582,$F69) -> 17
F70: 5 | G70: =COUNTIF(Reviews!$K$2:$K$2582,$F70) -> 178
F71: 6 | G71: =COUNTIF(Reviews!$K$2:$K$2582,$F71) -> 164
F72: 7 | G72: =COUNTIF(Reviews!$K$2:$K$2582,$F72) -> 540
F73: 8 | G73: =COUNTIF(Reviews!$K$2:$K$2582,$F73) -> 665
F74: 9 | G74: =COUNTIF(Reviews!$K$2:$K$2582,$F74) -> 672
F75: 10 | G75: =COUNTIF(Reviews!$K$2:$K$2582,$F75) -> 305

Sheet Hotel_Performance
A1: Hotel_ID | B1: City | C1: Star_Rating | D1: Month | E1: Rooms_Available | F1: Rooms_Sold | G1: Occupancy_Pct | H1: ADR_INR | I1: Room_Revenue_INR | J1: Other_Revenue_INR | K1: Total_Revenue_INR | L1: Operating_Cost_INR | M1: GOP_INR | N1: RevPAR_INR | O1: GOPPAR_INR | P1: Avg_Guest_Rating | Q1: Complaints | R1: Staff_Count
A2: H001 | B2: Goa | C2: 4 | D2: 45566 | E2: 2759 | F2: 1754 | G2: =F2/E2 -> 0.63573759 | H2: 5250 | I2: =F2*H2 -> 9208500 | J2: 4021275 | K2: =I2+J2 -> 13229775 | L2: 8437194 | M2: =K2-L2 -> 4792581 | N2: =I2/E2 -> 3337.6223 | O2: =M2/E2 -> 1737.0718 | P2: 3.6 | Q2: 0 | R2: 90
A3: H001 | B3: Goa | C3: 4 | D3: 45597 | E3: 2670 | F3: 2100 | G3: =F3/E3 -> 0.78651685 | H3: 6410 | I3: =F3*H3 -> 13461000 | J3: 5362447 | K3: =I3+J3 -> 18823447 | L3: 10471661 | M3: =K3-L3 -> 8351786 | N3: =I3/E3 -> 5041.573 | O3: =M3/E3 -> 3128.0097 | P3: 3.9 | Q3: 1 | R3: 89
A4: H001 | B4: Goa | C4: 4 | D4: 45627 | E4: 2759 | F4: 2101 | G4: =F4/E4 -> 0.76150779 | H4: 6630 | I4: =F4*H4 -> 13929630 | J4: 4838790 | K4: =I4+J4 -> 18768420 | L4: 10653927 | M4: =K4-L4 -> 8114493 | N4: =I4/E4 -> 5048.7967 | O4: =M4/E4 -> 2941.0993 | P4: 4.2 | Q4: 3 | R4: 88
A5: H001 | B5: Goa | C5: 4 | D5: 45658 | E5: 2759 | F5: 2008 | G5: =F5/E5 -> 0.72779993 | H5: 6480 | I5: =F5*H5 -> 13011840 | J5: 3406240 | K5: =I5+J5 -> 16418080 | L5: 9580954 | M5: =K5-L5 -> 6837126 | N5: =I5/E5 -> 4716.1435 | O5: =M5/E5 -> 2478.1174 | P5: 4 | Q5: 3 | R5: 86
A6: H001 | B6: Goa | C6: 4 | D6: 45689 | E6: 2492 | F6: 1979 | G6: =F6/E6 -> 0.79414125 | H6: 6460 | I6: =F6*H6 -> 12784340 | J6: 2998746 | K6: =I6+J6 -> 15783086 | L6: 9190309 | M6: =K6-L6 -> 6592777 | N6: =I6/E6 -> 5130.1525 | O6: =M6/E6 -> 2645.5766 | P6: 4 | Q6: 2 | R6: 86
A7: H001 | B7: Goa | C7: 4 | D7: 45717 | E7: 2759 | F7: 1798 | G7: =F7/E7 -> 0.65168539 | H7: 5320 | I7: =F7*H7 -> 9565360 | J7: 3706670 | K7: =I7+J7 -> 13272030 | L7: 8967267 | M7: =K7-L7 -> 4304763 | N7: =I7/E7 -> 3466.9663 | O7: =M7/E7 -> 1560.2621 | P7: 3.8 | Q7: 3 | R7: 90
A8: H001 | B8: Goa | C8: 4 | D8: 45748 | E8: 2670 | F8: 1788 | G8: =F8/E8 -> 0.66966292 | H8: 5420 | I8: =F8*H8 -> 9690960 | J8: 4264399 | K8: =I8+J8 -> 13955359 | L8: 9060653 | M8: =K8-L8 -> 4894706 | N8: =I8/E8 -> 3629.573 | O8: =M8/E8 -> 1833.2232 | P8: 3.8 | Q8: 3 | R8: 87
A9: H001 | B9: Goa | C9: 4 | D9: 45778 | E9: 2759 | F9: 1806 | G9: =F9/E9 -> 0.65458499 | H9: 5110 | I9: =F9*H9 -> 9228660 | J9: 3254293 | K9: =I9+J9 -> 12482953 | L9: 8396422 | M9: =K9-L9 -> 4086531 | N9: =I9/E9 -> 3344.9293 | O9: =M9/E9 -> 1481.1638 | P9: 4.1 | Q9: 3 | R9: 90
A10: H001 | B10: Goa | C10: 4 | D10: 45809 | E10: 2670 | F10: 1378 | G10: =F10/E10 -> 0.51610487 | H10: 4290 | I10: =F10*H10 -> 5911620 | J10: 2499187 | K10: =I10+J10 -> 8410807 | L10: 7173061 | M10: =K10-L10 -> 1237746 | N10: =I10/E10 -> 2214.0899 | O10: =M10/E10 -> 463.57528 | P10: 4.2 | Q10: 3 | R10: 91
A11: H001 | B11: Goa | C11: 4 | D11: 45839 | E11: 2759 | F11: 1389 | G11: =F11/E11 -> 0.50344328 | H11: 4330 | I11: =F11*H11 -> 6014370 | J11: 2232334 | K11: =I11+J11 -> 8246704 | L11: 7001817 | M11: =K11-L11 -> 1244887 | N11: =I11/E11 -> 2179.9094 | O11: =M11/E11 -> 451.2095 | P11: 3.9 | Q11: 1 | R11: 90
A12: H001 | B12: Goa | C12: 4 | D12: 45870 | E12: 2759 | F12: 1473 | G12: =F12/E12 -> 0.53388909 | H12: 4150 | I12: =F12*H12 -> 6112950 | J12: 2119063 | K12: =I12+J12 -> 8232013 | L12: 6754990 | M12: =K12-L12 -> 1477023 | N12: =I12/E12 -> 2215.6397 | O12: =M12/E12 -> 535.34723 | P12: 3.8 | Q12: 3 | R12: 86
A13: H001 | B13: Goa | C13: 4 | D13: 45901 | E13: 2670 | F13: 1505 | G13: =F13/E13 -> 0.56367041 | H13: 4310 | I13: =F13*H13 -> 6486550 | J13: 2475060 | K13: =I13+J13 -> 8961610 | L13: 6862512 | M13: =K13-L13 -> 2099098 | N13: =I13/E13 -> 2429.4195 | O13: =M13/E13 -> 786.17903 | P13: 3.7 | Q13: 1 | R13: 90
... A1153: H048 | B1153: Varanasi | C1153: 4 | D1153: 46266 | E1153: 3630 | F1153: 2132 | G1153: =F1153/E1153 -> 0.58732782 | H1153: 3060 | I1153: =F1153*H1153 -> 6523920 | J1153: 2812437 | K1153: =I1153+J1153 -> 9336357 | L1153: 6721477 | M1153: =K1153-L1153 -> 2614880 | N1153: =I1153/E1153 -> 1797.2231 | O1153: =M1153/E1153 -> 720.35262 | P1153: 3.9 | Q1153: 1 | R1153: 116

Sheet Hotel_Performance_Dashboard
B1: Hotel Performance - Dashboard
B3: Occupancy | D3: ADR (INR) | F3: RevPAR (INR) | H3: Total Revenue (Cr) | J3: GOP (Cr) | L3: GOP Margin | N3: Avg Guest Rating
B4: =SUM(Hotel_Performance!$F$2:$F$1153)/SUM(Hotel_Performance!$E$2:$E$1153) -> 0.68968138 | D4: =SUM(Hotel_Performance!$I$2:$I$1153)/SUM(Hotel_Performance!$F$2:$F$1153) -> 7281.5536 | F4: =SUM(Hotel_Performance!$I$2:$I$1153)/SUM(Hotel_Performance!$E$2:$E$1153) -> 5021.952 | H4: =SUM(Hotel_Performance!$K$2:$K$1153)/10000000 -> 3292.7632 | J4: =SUM(Hotel_Performance!$M$2:$M$1153)/10000000 -> 1264.8733 | L4: =SUM(Hotel_Performance!$M$2:$M$1153)/SUM(Hotel_Performance!$K$2:$K$1153) -> 0.38413736 | N4: =AVERAGE(Hotel_Performance!$P$2:$P$1153) -> 4.0993924
B67: Chart data (live formulas - charts above read from these tables)
B69: By month | J69: By city
B70: Month | C70: Occupancy | D70: ADR | E70: RevPAR | F70: Revenue (Cr) | G70: GOP (Cr) | H70: Key | J70: City | K70: Occupancy | L70: RevPAR | M70: GOP (Cr) | N70: Complaints
B71: =TEXT($H71,"mmm yy") -> Oct 24 | C71: =SUMIF(Hotel_Performance!$D$2:$D$1153,$H71,Hotel_Performance!$F$2:$F$1153)/SUMIF(Hotel_Performance!$D$2:$D$1153,$H71,Hotel_Performance!$E$2:$E$1153) -> 0.73785522 | D71: =SUMIF(Hotel_Performance!$D$2:$D$1153,$H71,Hotel_Performance!$I$2:$I$1153)/SUMIF(Hotel_Performance!$D$2:$D$1153,$H71,Hotel_Performance!$F$2:$F$1153) -> 7470.0965 | E71: =SUMIF(Hotel_Performance!$D$2:$D$1153,$H71,Hotel_Performance!$I$2:$I$1153)/SUMIF(Hotel_Performance!$D$2:$D$1153,$H71,Hotel_Performance!$E$2:$E$1153) -> 5511.8498 | F71: =SUMIF(Hotel_Performance!$D$2:$D$1153,$H71,Hotel_Performance!$K$2:$K$1153)/10000000 -> 153.37755 | G71: =SUMIF(Hotel_Performance!$D$2:$D$1153,$H71,Hotel_Performance!$M$2:$M$1153)/10000000 -> 62.176632 | H71: 45566 | J71: Mumbai | K71: =SUMIF(Hotel_Performance!$B$2:$B$1153,$J71,Hotel_Performance!$F$2:$F$1153)/SUMIF(Hotel_Performance!$B$2:$B$1153,$J71,Hotel_Performance!$E$2:$E$1153) -> 0.65009123 | L71: =SUMIF(Hotel_Performance!$B$2:$B$1153,$J71,Hotel_Performance!$I$2:$I$1153)/SUMIF(Hotel_Performance!$B$2:$B$1153,$J71,Hotel_Performance!$E$2:$E$1153) -> 5980.918 | M71: =SUMIF(Hotel_Performance!$B$2:$B$1153,$J71,Hotel_Performance!$M$2:$M$1153)/10000000 -> 104.01434 | N71: =SUMIF(Hotel_Performance!$B$2:$B$1153,$J71,Hotel_Performance!$Q$2:$Q$1153) -> 211
B72: =TEXT($H72,"mmm yy") -> Nov 24 | C72: =SUMIF(Hotel_Performance!$D$2:$D$1153,$H72,Hotel_Performance!$F$2:$F$1153)/SUMIF(Hotel_Performance!$D$2:$D$1153,$H72,Hotel_Performance!$E$2:$E$1153) -> 0.76106647 | D72: =SUMIF(Hotel_Performance!$D$2:$D$1153,$H72,Hotel_Performance!$I$2:$I$1153)/SUMIF(Hotel_Performance!$D$2:$D$1153,$H72,Hotel_Performance!$F$2:$F$1153) -> 7914.1232 | E72: =SUMIF(Hotel_Performance!$D$2:$D$1153,$H72,Hotel_Performance!$I$2:$I$1153)/SUMIF(Hotel_Performance!$D$2:$D$1153,$H72,Hotel_Performance!$E$2:$E$1153) -> 6023.1738 | F72: =SUMIF(Hotel_Performance!$D$2:$D$1153,$H72,Hotel_Performance!$K$2:$K$1153)/10000000 -> 160.95425 | G72: =SUMIF(Hotel_Performance!$D$2:$D$1153,$H72,Hotel_Performance!$M$2:$M$1153)/10000000 -> 68.950771 | H72: 45597 | J72: Agra | K72: =SUMIF(Hotel_Performance!$B$2:$B$1153,$J72,Hotel_Performance!$F$2:$F$1153)/SUMIF(Hotel_Performance!$B$2:$B$1153,$J72,Hotel_Performance!$E$2:$E$1153) -> 0.65624496 | L72: =SUMIF(Hotel_Performance!$B$2:$B$1153,$J72,Hotel_Performance!$I$2:$I$1153)/SUMIF(Hotel_Performance!$B$2:$B$1153,$J72,Hotel_Performance!$E$2:$E$1153) -> 3415.0022 | M72: =SUMIF(Hotel_Performance!$B$2:$B$1153,$J72,Hotel_Performance!$M$2:$M$1153)/10000000 -> 72.940014 | N72: =SUMIF(Hotel_Performance!$B$2:$B$1153,$J72,Hotel_Performance!$Q$2:$Q$1153) -> 240
B73: =TEXT($H73,"mmm yy") -> Dec 24 | C73: =SUMIF(Hotel_Performance!$D$2:$D$1153,$H73,Hotel_Performance!$F$2:$F$1153)/SUMIF(Hotel_Performance!$D$2:$D$1153,$H73,Hotel_Performance!$E$2:$E$1153) -> 0.77545603 | D73: =SUMIF(Hotel_Performance!$D$2:$D$1153,$H73,Hotel_Performance!$I$2:$I$1153)/SUMIF(Hotel_Performance!$D$2:$D$1153,$H73,Hotel_Performance!$F$2:$F$1153) -> 8171.1302 | E73: =SUMIF(Hotel_Performance!$D$2:$D$1153,$H73,Hotel_Performance!$I$2:$I$1153)/SUMIF(Hotel_Performance!$D$2:$D$1153,$H73,Hotel_Performance!$E$2:$E$1153) -> 6336.3522 | F73: =SUMIF(Hotel_Performance!$D$2:$D$1153,$H73,Hotel_Performance!$K$2:$K$1153)/10000000 -> 176.41706 | G73: =SUMIF(Hotel_Performance!$D$2:$D$1153,$H73,Hotel_Performance!$M$2:$M$1153)/10000000 -> 78.619851 | H73: 45627 | J73: Varanasi | K73: =SUMIF(Hotel_Performance!$B$2:$B$1153,$J73,Hotel_Performance!$F$2:$F$1153)/SUMIF(Hotel_Performance!$B$2:$B$1153,$J73,Hotel_Performance!$E$2:$E$1153) -> 0.67087844 | L73: =SUMIF(Hotel_Performance!$B$2:$B$1153,$J73,Hotel_Performance!$I$2:$I$1153)/SUMIF(Hotel_Performance!$B$2:$B$1153,$J73,Hotel_Performance!$E$2:$E$1153) -> 3254.8814 | M73: =SUMIF(Hotel_Performance!$B$2:$B$1153,$J73,Hotel_Performance!$M$2:$M$1153)/10000000 -> 49.678742 | N73: =SUMIF(Hotel_Performance!$B$2:$B$1153,$J73,Hotel_Performance!$Q$2:$Q$1153) -> 220
B74: =TEXT($H74,"mmm yy") -> Jan 25 | C74: =SUMIF(Hotel_Performance!$D$2:$D$1153,$H74,Hotel_Performance!$F$2:$F$1153)/SUMIF(Hotel_Performance!$D$2:$D$1153,$H74,Hotel_Performance!$E$2:$E$1153) -> 0.77561444 | D74: =SUMIF(Hotel_Performance!$D$2:$D$1153,$H74,Hotel_Performance!$I$2:$I$1153)/SUMIF(Hotel_Performance!$D$2:$D$1153,$H74,Hotel_Performance!$F$2:$F$1153) -> 8019.2855 | E74: =SUMIF(Hotel_Performance!$D$2:$D$1153,$H74,Hotel_Performance!$I$2:$I$1153)/SUMIF(Hotel_Performance!$D$2:$D$1153,$H74,Hotel_Performance!$E$2:$E$1153) -> 6219.8737 | F74: =SUMIF(Hotel_Performance!$D$2:$D$1153,$H74,Hotel_Performance!$K$2:$K$1153)/10000000 -> 174.22897 | G74: =SUMIF(Hotel_Performance!$D$2:$D$1153,$H74,Hotel_Performance!$M$2:$M$1153)/10000000 -> 76.905941 | H74: 45658 | J74: Shimla | K74: =SUMIF(Hotel_Performance!$B$2:$B$1153,$J74,Hotel_Performance!$F$2:$F$1153)/SUMIF(Hotel_Performance!$B$2:$B$1153,$J74,Hotel_Performance!$E$2:$E$1153) -> 0.68081203 | L74: =SUMIF(Hotel_Performance!$B$2:$B$1153,$J74,Hotel_Performance!$I$2:$I$1153)/SUMIF(Hotel_Performance!$B$2:$B$1153,$J74,Hotel_Performance!$E$2:$E$1153) -> 3840.5256 | M74: =SUMIF(Hotel_Performance!$B$2:$B$1153,$J74,Hotel_Performance!$M$2:$M$1153)/10000000 -> 78.08813 | N74: =SUMIF(Hotel_Performance!$B$2:$B$1153,$J74,Hotel_Performance!$Q$2:$Q$1153) -> 233
B75: =TEXT($H75,"mmm yy") -> Feb 25 | C75: =SUMIF(Hotel_Performance!$D$2:$D$1153,$H75,Hotel_Performance!$F$2:$F$1153)/SUMIF(Hotel_Performance!$D$2:$D$1153,$H75,Hotel_Performance!$E$2:$E$1153) -> 0.77424532 | D75: =SUMIF(Hotel_Performance!$D$2:$D$1153,$H75,Hotel_Performance!$I$2:$I$1153)/SUMIF(Hotel_Performance!$D$2:$D$1153,$H75,Hotel_Performance!$F$2:$F$1153) -> 8020.8689 | E75: =SUMIF(Hotel_Performance!$D$2:$D$1153,$H75,Hotel_Performance!$I$2:$I$1153)/SUMIF(Hotel_Performance!$D$2:$D$1153,$H75,Hotel_Performance!$E$2:$E$1153) -> 6210.1202 | F75: =SUMIF(Hotel_Performance!$D$2:$D$1153,$H75,Hotel_Performance!$K$2:$K$1153)/10000000 -> 154.26889 | G75: =SUMIF(Hotel_Performance!$D$2:$D$1153,$H75,Hotel_Performance!$M$2:$M$1153)/10000000 -> 67.885167 | H75: 45689 | J75: Goa | K75: =SUMIF(Hotel_Performance!$B$2:$B$1153,$J75,Hotel_Performance!$F$2:$F$1153)/SUMIF(Hotel_Performance!$B$2:$B$1153,$J75,Hotel_Performance!$E$2:$E$1153) -> 0.68841156 | L75: =SUMIF(Hotel_Performance!$B$2:$B$1153,$J75,Hotel_Performance!$I$2:$I$1153)/SUMIF(Hotel_Performance!$B$2:$B$1153,$J75,Hotel_Performance!$E$2:$E$1153) -> 5476.4008 | M75: =SUMIF(Hotel_Performance!$B$2:$B$1153,$J75,Hotel_Performance!$M$2:$M$1153)/10000000 -> 109.07292 | N75: =SUMIF(Hotel_Performance!$B$2:$B$1153,$J75,Hotel_Performance!$Q$2:$Q$1153) -> 232
B76: =TEXT($H76,"mmm yy") -> Mar 25 | C76: =SUMIF(Hotel_Performance!$D$2:$D$1153,$H76,Hotel_Performance!$F$2:$F$1153)/SUMIF(Hotel_Performance!$D$2:$D$1153,$H76,Hotel_Performance!$E$2:$E$1153) -> 0.75643721 | D76: =SUMIF(Hotel_Performance!$D$2:$D$1153,$H76,Hotel_Performance!$I$2:$I$1153)/SUMIF(Hotel_Performance!$D$2:$D$1153,$H76,Hotel_Performance!$F$2:$F$1153) -> 7774.5835 | E76: =SUMIF(Hotel_Performance!$D$2:$D$1153,$H76,Hotel_Performance!$I$2:$I$1153)/SUMIF(Hotel_Performance!$D$2:$D$1153,$H76,Hotel_Performance!$E$2:$E$1153) -> 5880.9843 | F76: =SUMIF(Hotel_Performance!$D$2:$D$1153,$H76,Hotel_Performance!$K$2:$K$1153)/10000000 -> 163.65771 | G76: =SUMIF(Hotel_Performance!$D$2:$D$1153,$H76,Hotel_Performance!$M$2:$M$1153)/10000000 -> 69.793875 | H76: 45717 | J76: Manali | K76: =SUMIF(Hotel_Performance!$B$2:$B$1153,$J76,Hotel_Performance!$F$2:$F$1153)/SUMIF(Hotel_Performance!$B$2:$B$1153,$J76,Hotel_Performance!$E$2:$E$1153) -> 0.68507634 | L76: =SUMIF(Hotel_Performance!$B$2:$B$1153,$J76,Hotel_Performance!$I$2:$I$1153)/SUMIF(Hotel_Performance!$B$2:$B$1153,$J76,Hotel_Performance!$E$2:$E$1153) -> 4216.9687 | M76: =SUMIF(Hotel_Performance!$B$2:$B$1153,$J76,Hotel_Performance!$M$2:$M$1153)/10000000 -> 69.735819 | N76: =SUMIF(Hotel_Performance!$B$2:$B$1153,$J76,Hotel_Performance!$Q$2:$Q$1153) -> 182
B77: =TEXT($H77,"mmm yy") -> Apr 25 | C77: =SUMIF(Hotel_Performance!$D$2:$D$1153,$H77,Hotel_Performance!$F$2:$F$1153)/SUMIF(Hotel_Performance!$D$2:$D$1153,$H77,Hotel_Performance!$E$2:$E$1153) -> 0.70620536 | D77: =SUMIF(Hotel_Performance!$D$2:$D$1153,$H77,Hotel_Performance!$I$2:$I$1153)/SUMIF(Hotel_Performance!$D$2:$D$1153,$H77,Hotel_Performance!$F$2:$F$1153) -> 6926.4772 | E77: =SUMIF(Hotel_Performance!$D$2:$D$1153,$H77,Hotel_Performance!$I$2:$I$1153)/SUMIF(Hotel_Performance!$D$2:$D$1153,$H77,Hotel_Performance!$E$2:$E$1153) -> 4891.5153 | F77: =SUMIF(Hotel_Performance!$D$2:$D$1153,$H77,Hotel_Performance!$K$2:$K$1153)/10000000 -> 133.29518 | G77: =SUMIF(Hotel_Performance!$D$2:$D$1153,$H77,Hotel_Performance!$M$2:$M$1153)/10000000 -> 50.511862 | H77: 45748 | J77: Jaipur | K77: =SUMIF(Hotel_Performance!$B$2:$B$1153,$J77,Hotel_Performance!$F$2:$F$1153)/SUMIF(Hotel_Performance!$B$2:$B$1153,$J77,Hotel_Performance!$E$2:$E$1153) -> 0.69938465 | L77: =SUMIF(Hotel_Performance!$B$2:$B$1153,$J77,Hotel_Performance!$I$2:$I$1153)/SUMIF(Hotel_Performance!$B$2:$B$1153,$J77,Hotel_Performance!$E$2:$E$1153) -> 5187.6127 | M77: =SUMIF(Hotel_Performance!$B$2:$B$1153,$J77,Hotel_Performance!$M$2:$M$1153)/10000000 -> 124.90992 | N77: =SUMIF(Hotel_Performance!$B$2:$B$1153,$J77,Hotel_Performance!$Q$2:$Q$1153) -> 233
B78: =TEXT($H78,"mmm yy") -> May 25 | C78: =SUMIF(Hotel_Performance!$D$2:$D$1153,$H78,Hotel_Performance!$F$2:$F$1153)/SUMIF(Hotel_Performance!$D$2:$D$1153,$H78,Hotel_Performance!$E$2:$E$1153) -> 0.70369624 | D78: =SUMIF(Hotel_Performance!$D$2:$D$1153,$H78,Hotel_Performance!$I$2:$I$1153)/SUMIF(Hotel_Performance!$D$2:$D$1153,$H78,Hotel_Performance!$F$2:$F$1153) -> 6897.8336 | E78: =SUMIF(Hotel_Performance!$D$2:$D$1153,$H78,Hotel_Performance!$I$2:$I$1153)/SUMIF(Hotel_Performance!$D$2:$D$1153,$H78,Hotel_Performance!$E$2:$E$1153) -> 4853.9796 | F78: =SUMIF(Hotel_Performance!$D$2:$D$1153,$H78,Hotel_Performance!$K$2:$K$1153)/10000000 -> 135.24879 | G78: =SUMIF(Hotel_Performance!$D$2:$D$1153,$H78,Hotel_Performance!$M$2:$M$1153)/10000000 -> 50.198319 | H78: 45778 | J78: Rishikesh | K78: =SUMIF(Hotel_Performance!$B$2:$B$1153,$J78,Hotel_Performance!$F$2:$F$1153)/SUMIF(Hotel_Performance!$B$2:$B$1153,$J78,Hotel_Performance!$E$2:$E$1153) -> 0.68807898 | L78: =SUMIF(Hotel_Performance!$B$2:$B$1153,$J78,Hotel_Performance!$I$2:$I$1153)/SUMIF(Hotel_Performance!$B$2:$B$1153,$J78,Hotel_Performance!$E$2:$E$1153) -> 3597.9819 | M78: =SUMIF(Hotel_Performance!$B$2:$B$1153,$J78,Hotel_Performance!$M$2:$M$1153)/10000000 -> 80.119521 | N78: =SUMIF(Hotel_Performance!$B$2:$B$1153,$J78,Hotel_Performance!$Q$2:$Q$1153) -> 225
B79: =TEXT($H79,"mmm yy") -> Jun 25 | C79: =SUMIF(Hotel_Performance!$D$2:$D$1153,$H79,Hotel_Performance!$F$2:$F$1153)/SUMIF(Hotel_Performance!$D$2:$D$1153,$H79,Hotel_Performance!$E$2:$E$1153) -> 0.54855655 | D79: =SUMIF(Hotel_Performance!$D$2:$D$1153,$H79,Hotel_Performance!$I$2:$I$1153)/SUMIF(Hotel_Performance!$D$2:$D$1153,$H79,Hotel_Performance!$F$2:$F$1153) -> 5785.1029 | E79: =SUMIF(Hotel_Performance!$D$2:$D$1153,$H79,Hotel_Performance!$I$2:$I$1153)/SUMIF(Hotel_Performance!$D$2:$D$1153,$H79,Hotel_Performance!$E$2:$E$1153) -> 3173.4561 | F79: =SUMIF(Hotel_Performance!$D$2:$D$1153,$H79,Hotel_Performance!$K$2:$K$1153)/10000000 -> 85.566456 | G79: =SUMIF(Hotel_Performance!$D$2:$D$1153,$H79,Hotel_Performance!$M$2:$M$1153)/10000000 -> 18.738207 | H79: 45809 | J79: Udaipur | K79: =SUMIF(Hotel_Performance!$B$2:$B$1153,$J79,Hotel_Performance!$F$2:$F$1153)/SUMIF(Hotel_Performance!$B$2:$B$1153,$J79,Hotel_Performance!$E$2:$E$1153) -> 0.69259508 | L79: =SUMIF(Hotel_Performance!$B$2:$B$1153,$J79,Hotel_Performance!$I$2:$I$1153)/SUMIF(Hotel_Performance!$B$2:$B$1153,$J79,Hotel_Performance!$E$2:$E$1153) -> 5783.0323 | M79: =SUMIF(Hotel_Performance!$B$2:$B$1153,$J79,Hotel_Performance!$M$2:$M$1153)/10000000 -> 127.72749 | N79: =SUMIF(Hotel_Performance!$B$2:$B$1153,$J79,Hotel_Performance!$Q$2:$Q$1153) -> 200
B80: =TEXT($H80,"mmm yy") -> Jul 25 | C80: =SUMIF(Hotel_Performance!$D$2:$D$1153,$H80,Hotel_Performance!$F$2:$F$1153)/SUMIF(Hotel_Performance!$D$2:$D$1153,$H80,Hotel_Performance!$E$2:$E$1153) -> 0.51018625 | D80: =SUMIF(Hotel_Performance!$D$2:$D$1153,$H80,Hotel_Performance!$I$2:$I$1153)/SUMIF(Hotel_Performance!$D$2:$D$1153,$H80,Hotel_Performance!$F$2:$F$1153) -> 5408.7453 | E80: =SUMIF(Hotel_Performance!$D$2:$D$1153,$H80,Hotel_Performance!$I$2:$I$1153)/SUMIF(Hotel_Performance!$D$2:$D$1153,$H80,Hotel_Performance!$E$2:$E$1153) -> 2759.4675 | F80: =SUMIF(Hotel_Performance!$D$2:$D$1153,$H80,Hotel_Performance!$K$2:$K$1153)/10000000 -> 76.28546 | G80: =SUMIF(Hotel_Performance!$D$2:$D$1153,$H80,Hotel_Performance!$M$2:$M$1153)/10000000 -> 11.037151 | H80: 45839 | J80: New Delhi | K80: =SUMIF(Hotel_Performance!$B$2:$B$1153,$J80,Hotel_Performance!$F$2:$F$1153)/SUMIF(Hotel_Performance!$B$2:$B$1153,$J80,Hotel_Performance!$E$2:$E$1153) -> 0.718006 | L80: =SUMIF(Hotel_Performance!$B$2:$B$1153,$J80,Hotel_Performance!$I$2:$I$1153)/SUMIF(Hotel_Performance!$B$2:$B$1153,$J80,Hotel_Performance!$E$2:$E$1153) -> 7206.195 | M80: =SUMIF(Hotel_Performance!$B$2:$B$1153,$J80,Hotel_Performance!$M$2:$M$1153)/10000000 -> 183.60215 | N80: =SUMIF(Hotel_Performance!$B$2:$B$1153,$J80,Hotel_Performance!$Q$2:$Q$1153) -> 251
B81: =TEXT($H81,"mmm yy") -> Aug 25 | C81: =SUMIF(Hotel_Performance!$D$2:$D$1153,$H81,Hotel_Performance!$F$2:$F$1153)/SUMIF(Hotel_Performance!$D$2:$D$1153,$H81,Hotel_Performance!$E$2:$E$1153) -> 0.51386329 | D81: =SUMIF(Hotel_Performance!$D$2:$D$1153,$H81,Hotel_Performance!$I$2:$I$1153)/SUMIF(Hotel_Performance!$D$2:$D$1153,$H81,Hotel_Performance!$F$2:$F$1153) -> 5340.6939 | E81: =SUMIF(Hotel_Performance!$D$2:$D$1153,$H81,Hotel_Performance!$I$2:$I$1153)/SUMIF(Hotel_Performance!$D$2:$D$1153,$H81,Hotel_Performance!$E$2:$E$1153) -> 2744.3865 | F81: =SUMIF(Hotel_Performance!$D$2:$D$1153,$H81,Hotel_Performance!$K$2:$K$1153)/10000000 -> 77.264458 | G81: =SUMIF(Hotel_Performance!$D$2:$D$1153,$H81,Hotel_Performance!$M$2:$M$1153)/10000000 -> 11.809068 | H81: 45870 | J81: Bengaluru | K81: =SUMIF(Hotel_Performance!$B$2:$B$1153,$J81,Hotel_Performance!$F$2:$F$1153)/SUMIF(Hotel_Performance!$B$2:$B$1153,$J81,Hotel_Performance!$E$2:$E$1153) -> 0.72422913 | L81: =SUMIF(Hotel_Performance!$B$2:$B$1153,$J81,Hotel_Performance!$I$2:$I$1153)/SUMIF(Hotel_Performance!$B$2:$B$1153,$J81,Hotel_Performance!$E$2:$E$1153) -> 6909.5153 | M81: =SUMIF(Hotel_Performance!$B$2:$B$1153,$J81,Hotel_Performance!$M$2:$M$1153)/10000000 -> 143.7147 | N81: =SUMIF(Hotel_Performance!$B$2:$B$1153,$J81,Hotel_Performance!$Q$2:$Q$1153) -> 245
B82: =TEXT($H82,"mmm yy") -> Sep 25 | C82: =SUMIF(Hotel_Performance!$D$2:$D$1153,$H82,Hotel_Performance!$F$2:$F$1153)/SUMIF(Hotel_Performance!$D$2:$D$1153,$H82,Hotel_Performance!$E$2:$E$1153) -> 0.53368056 | D82: =SUMIF(Hotel_Performance!$D$2:$D$1153,$H82,Hotel_Performance!$I$2:$I$1153)/SUMIF(Hotel_Performance!$D$2:$D$1153,$H82,Hotel_Performance!$F$2:$F$1153) -> 5631.0565 | E82: =SUMIF(Hotel_Performance!$D$2:$D$1153,$H82,Hotel_Performance!$I$2:$I$1153)/SUMIF(Hotel_Performance!$D$2:$D$1153,$H82,Hotel_Performance!$E$2:$E$1153) -> 3005.1854 | F82: =SUMIF(Hotel_Performance!$D$2:$D$1153,$H82,Hotel_Performance!$K$2:$K$1153)/10000000 -> 82.059044 | G82: =SUMIF(Hotel_Performance!$D$2:$D$1153,$H82,Hotel_Performance!$M$2:$M$1153)/10000000 -> 15.817715 | H82: 45901 | J82: Kochi | K82: =SUMIF(Hotel_Performance!$B$2:$B$1153,$J82,Hotel_Performance!$F$2:$F$1153)/SUMIF(Hotel_Performance!$B$2:$B$1153,$J82,Hotel_Performance!$E$2:$E$1153) -> 0.70765139 | L82: =SUMIF(Hotel_Performance!$B$2:$B$1153,$J82,Hotel_Performance!$I$2:$I$1153)/SUMIF(Hotel_Performance!$B$2:$B$1153,$J82,Hotel_Performance!$E$2:$E$1153) -> 4823.5546 | M82: =SUMIF(Hotel_Performance!$B$2:$B$1153,$J82,Hotel_Performance!$M$2:$M$1153)/10000000 -> 121.26961 | N82: =SUMIF(Hotel_Performance!$B$2:$B$1153,$J82,Hotel_Performance!$Q$2:$Q$1153) -> 247
B83: =TEXT($H83,"mmm yy") -> Oct 25 | C83: =SUMIF(Hotel_Performance!$D$2:$D$1153,$H83,Hotel_Performance!$F$2:$F$1153)/SUMIF(Hotel_Performance!$D$2:$D$1153,$H83,Hotel_Performance!$E$2:$E$1153) -> 0.77590246 | D83: =SUMIF(Hotel_Performance!$D$2:$D$1153,$H83,Hotel_Performance!$I$2:$I$1153)/SUMIF(Hotel_Performance!$D$2:$D$1153,$H83,Hotel_Performance!$F$2:$F$1153) -> 7811.088 | E83: =SUMIF(Hotel_Performance!$D$2:$D$1153,$H83,Hotel_Performance!$I$2:$I$1153)/SUMIF(Hotel_Performance!$D$2:$D$1153,$H83,Hotel_Performance!$E$2:$E$1153) -> 6060.6424 | F83: =SUMIF(Hotel_Performance!$D$2:$D$1153,$H83,Hotel_Performance!$K$2:$K$1153)/10000000 -> 168.69368 | G83: =SUMIF(Hotel_Performance!$D$2:$D$1153,$H83,Hotel_Performance!$M$2:$M$1153)/10000000 -> 72.48566 | H83: 45931
B84: =TEXT($H84,"mmm yy") -> Nov 25 | C84: =SUMIF(Hotel_Performance!$D$2:$D$1153,$H84,Hotel_Performance!$F$2:$F$1153)/SUMIF(Hotel_Performance!$D$2:$D$1153,$H84,Hotel_Performance!$E$2:$E$1153) -> 0.79963294 | D84: =SUMIF(Hotel_Performance!$D$2:$D$1153,$H84,Hotel_Performance!$I$2:$I$1153)/SUMIF(Hotel_Performance!$D$2:$D$1153,$H84,Hotel_Performance!$F$2:$F$1153) -> 8363.7929 | E84: =SUMIF(Hotel_Performance!$D$2:$D$1153,$H84,Hotel_Performance!$I$2:$I$1153)/SUMIF(Hotel_Performance!$D$2:$D$1153,$H84,Hotel_Performance!$E$2:$E$1153) -> 6687.9643 | F84: =SUMIF(Hotel_Performance!$D$2:$D$1153,$H84,Hotel_Performance!$K$2:$K$1153)/10000000 -> 182.54119 | G84: =SUMIF(Hotel_Performance!$D$2:$D$1153,$H84,Hotel_Performance!$M$2:$M$1153)/10000000 -> 84.440942 | H84: 45962
B85: =TEXT($H85,"mmm yy") -> Dec 25 | C85: =SUMIF(Hotel_Performance!$D$2:$D$1153,$H85,Hotel_Performance!$F$2:$F$1153)/SUMIF(Hotel_Performance!$D$2:$D$1153,$H85,Hotel_Performance!$E$2:$E$1153) -> 0.82139977 | D85: =SUMIF(Hotel_Performance!$D$2:$D$1153,$H85,Hotel_Performance!$I$2:$I$1153)/SUMIF(Hotel_Performance!$D$2:$D$1153,$H85,Hotel_Performance!$F$2:$F$1153) -> 8359.8766 | E85: =SUMIF(Hotel_Performance!$D$2:$D$1153,$H85,Hotel_Performance!$I$2:$I$1153)/SUMIF(Hotel_Performance!$D$2:$D$1153,$H85,Hotel_Performance!$E$2:$E$1153) -> 6866.8007 | F85: =SUMIF(Hotel_Performance!$D$2:$D$1153,$H85,Hotel_Performance!$K$2:$K$1153)/10000000 -> 189.9128 | G85: =SUMIF(Hotel_Performance!$D$2:$D$1153,$H85,Hotel_Performance!$M$2:$M$1153)/10000000 -> 87.640009 | H85: 45992
B86: =TEXT($H86,"mmm yy") -> Jan 26 | C86: =SUMIF(Hotel_Performance!$D$2:$D$1153,$H86,Hotel_Performance!$F$2:$F$1153)/SUMIF(Hotel_Performance!$D$2:$D$1153,$H86,Hotel_Performance!$E$2:$E$1153) -> 0.80709005 | D86: =SUMIF(Hotel_Performance!$D$2:$D$1153,$H86,Hotel_Performance!$I$2:$I$1153)/SUMIF(Hotel_Performance!$D$2:$D$1153,$H86,Hotel_Performance!$F$2:$F$1153) -> 8464.6899 | E86: =SUMIF(Hotel_Performance!$D$2:$D$1153,$H86,Hotel_Performance!$I$2:$I$1153)/SUMIF(Hotel_Performance!$D$2:$D$1153,$H86,Hotel_Performance!$E$2:$E$1153) -> 6831.767 | F86: =SUMIF(Hotel_Performance!$D$2:$D$1153,$H86,Hotel_Performance!$K$2:$K$1153)/10000000 -> 189.87546 | G86: =SUMIF(Hotel_Performance!$D$2:$D$1153,$H86,Hotel_Performance!$M$2:$M$1153)/10000000 -> 87.494493 | H86: 46023
B87: =TEXT($H87,"mmm yy") -> Feb 26 | C87: =SUMIF(Hotel_Performance!$D$2:$D$1153,$H87,Hotel_Performance!$F$2:$F$1153)/SUMIF(Hotel_Performance!$D$2:$D$1153,$H87,Hotel_Performance!$E$2:$E$1153) -> 0.79892645 | D87: =SUMIF(Hotel_Performance!$D$2:$D$1153,$H87,Hotel_Performance!$I$2:$I$1153)/SUMIF(Hotel_Performance!$D$2:$D$1153,$H87,Hotel_Performance!$F$2:$F$1153) -> 8399.0684 | E87: =SUMIF(Hotel_Performance!$D$2:$D$1153,$H87,Hotel_Performance!$I$2:$I$1153)/SUMIF(Hotel_Performance!$D$2:$D$1153,$H87,Hotel_Performance!$E$2:$E$1153) -> 6710.2379 | F87: =SUMIF(Hotel_Performance!$D$2:$D$1153,$H87,Hotel_Performance!$K$2:$K$1153)/10000000 -> 166.34861 | G87: =SUMIF(Hotel_Performance!$D$2:$D$1153,$H87,Hotel_Performance!$M$2:$M$1153)/10000000 -> 75.982349 | H87: 46054
B88: =TEXT($H88,"mmm yy") -> Mar 26 | C88: =SUMIF(Hotel_Performance!$D$2:$D$1153,$H88,Hotel_Performance!$F$2:$F$1153)/SUMIF(Hotel_Performance!$D$2:$D$1153,$H88,Hotel_Performance!$E$2:$E$1153) -> 0.79286674 | D88: =SUMIF(Hotel_Performance!$D$2:$D$1153,$H88,Hotel_Performance!$I$2:$I$1153)/SUMIF(Hotel_Performance!$D$2:$D$1153,$H88,Hotel_Performance!$F$2:$F$1153) -> 8092.5611 | E88: =SUMIF(Hotel_Performance!$D$2:$D$1153,$H88,Hotel_Performance!$I$2:$I$1153)/SUMIF(Hotel_Performance!$D$2:$D$1153,$H88,Hotel_Performance!$E$2:$E$1153) -> 6416.3225 | F88: =SUMIF(Hotel_Performance!$D$2:$D$1153,$H88,Hotel_Performance!$K$2:$K$1153)/10000000 -> 178.21249 | G88: =SUMIF(Hotel_Performance!$D$2:$D$1153,$H88,Hotel_Performance!$M$2:$M$1153)/10000000 -> 79.64468 | H88: 46082
B89: =TEXT($H89,"mmm yy") -> Apr 26 | C89: =SUMIF(Hotel_Performance!$D$2:$D$1153,$H89,Hotel_Performance!$F$2:$F$1153)/SUMIF(Hotel_Performance!$D$2:$D$1153,$H89,Hotel_Performance!$E$2:$E$1153) -> 0.72667163 | D89: =SUMIF(Hotel_Performance!$D$2:$D$1153,$H89,Hotel_Performance!$I$2:$I$1153)/SUMIF(Hotel_Performance!$D$2:$D$1153,$H89,Hotel_Performance!$F$2:$F$1153) -> 7238.4512 | E89: =SUMIF(Hotel_Performance!$D$2:$D$1153,$H89,Hotel_Performance!$I$2:$I$1153)/SUMIF(Hotel_Performance!$D$2:$D$1153,$H89,Hotel_Performance!$E$2:$E$1153) -> 5259.9771 | F89: =SUMIF(Hotel_Performance!$D$2:$D$1153,$H89,Hotel_Performance!$K$2:$K$1153)/10000000 -> 142.6136 | G89: =SUMIF(Hotel_Performance!$D$2:$D$1153,$H89,Hotel_Performance!$M$2:$M$1153)/10000000 -> 56.661521 | H89: 46113
B90: =TEXT($H90,"mmm yy") -> May 26 | C90: =SUMIF(Hotel_Performance!$D$2:$D$1153,$H90,Hotel_Performance!$F$2:$F$1153)/SUMIF(Hotel_Performance!$D$2:$D$1153,$H90,Hotel_Performance!$E$2:$E$1153) -> 0.73113479 | D90: =SUMIF(Hotel_Performance!$D$2:$D$1153,$H90,Hotel_Performance!$I$2:$I$1153)/SUMIF(Hotel_Performance!$D$2:$D$1153,$H90,Hotel_Performance!$F$2:$F$1153) -> 7337.816 | E90: =SUMIF(Hotel_Performance!$D$2:$D$1153,$H90,Hotel_Performance!$I$2:$I$1153)/SUMIF(Hotel_Performance!$D$2:$D$1153,$H90,Hotel_Performance!$E$2:$E$1153) -> 5364.9326 | F90: =SUMIF(Hotel_Performance!$D$2:$D$1153,$H90,Hotel_Performance!$K$2:$K$1153)/10000000 -> 148.7886 | G90: =SUMIF(Hotel_Performance!$D$2:$D$1153,$H90,Hotel_Performance!$M$2:$M$1153)/10000000 -> 59.049181 | H90: 46143
B91: =TEXT($H91,"mmm yy") -> Jun 26 | C91: =SUMIF(Hotel_Performance!$D$2:$D$1153,$H91,Hotel_Performance!$F$2:$F$1153)/SUMIF(Hotel_Performance!$D$2:$D$1153,$H91,Hotel_Performance!$E$2:$E$1153) -> 0.58123512 | D91: =SUMIF(Hotel_Performance!$D$2:$D$1153,$H91,Hotel_Performance!$I$2:$I$1153)/SUMIF(Hotel_Performance!$D$2:$D$1153,$H91,Hotel_Performance!$F$2:$F$1153) -> 6072.0613 | E91: =SUMIF(Hotel_Performance!$D$2:$D$1153,$H91,Hotel_Performance!$I$2:$I$1153)/SUMIF(Hotel_Performance!$D$2:$D$1153,$H91,Hotel_Performance!$E$2:$E$1153) -> 3529.2953 | F91: =SUMIF(Hotel_Performance!$D$2:$D$1153,$H91,Hotel_Performance!$K$2:$K$1153)/10000000 -> 96.463319 | G91: =SUMIF(Hotel_Performance!$D$2:$D$1153,$H91,Hotel_Performance!$M$2:$M$1153)/10000000 -> 25.539062 | H91: 46174
B92: =TEXT($H92,"mmm yy") -> Jul 26 | C92: =SUMIF(Hotel_Performance!$D$2:$D$1153,$H92,Hotel_Performance!$F$2:$F$1153)/SUMIF(Hotel_Performance!$D$2:$D$1153,$H92,Hotel_Performance!$E$2:$E$1153) -> 0.53394777 | D92: =SUMIF(Hotel_Performance!$D$2:$D$1153,$H92,Hotel_Performance!$I$2:$I$1153)/SUMIF(Hotel_Performance!$D$2:$D$1153,$H92,Hotel_Performance!$F$2:$F$1153) -> 5642.4879 | E92: =SUMIF(Hotel_Performance!$D$2:$D$1153,$H92,Hotel_Performance!$I$2:$I$1153)/SUMIF(Hotel_Performance!$D$2:$D$1153,$H92,Hotel_Performance!$E$2:$E$1153) -> 3012.7938 | F92: =SUMIF(Hotel_Performance!$D$2:$D$1153,$H92,Hotel_Performance!$K$2:$K$1153)/10000000 -> 82.942164 | G92: =SUMIF(Hotel_Performance!$D$2:$D$1153,$H92,Hotel_Performance!$M$2:$M$1153)/10000000 -> 15.87198 | H92: 46204
B93: =TEXT($H93,"mmm yy") -> Aug 26 | C93: =SUMIF(Hotel_Performance!$D$2:$D$1153,$H93,Hotel_Performance!$F$2:$F$1153)/SUMIF(Hotel_Performance!$D$2:$D$1153,$H93,Hotel_Performance!$E$2:$E$1153) -> 0.53293011 | D93: =SUMIF(Hotel_Performance!$D$2:$D$1153,$H93,Hotel_Performance!$I$2:$I$1153)/SUMIF(Hotel_Performance!$D$2:$D$1153,$H93,Hotel_Performance!$F$2:$F$1153) -> 5644.632 | E93: =SUMIF(Hotel_Performance!$D$2:$D$1153,$H93,Hotel_Performance!$I$2:$I$1153)/SUMIF(Hotel_Performance!$D$2:$D$1153,$H93,Hotel_Performance!$E$2:$E$1153) -> 3008.1943 | F93: =SUMIF(Hotel_Performance!$D$2:$D$1153,$H93,Hotel_Performance!$K$2:$K$1153)/10000000 -> 84.140318 | G93: =SUMIF(Hotel_Performance!$D$2:$D$1153,$H93,Hotel_Performance!$M$2:$M$1153)/10000000 -> 16.116507 | H93: 46235
B94: =TEXT($H94,"mmm yy") -> Sep 26 | C94: =SUMIF(Hotel_Performance!$D$2:$D$1153,$H94,Hotel_Performance!$F$2:$F$1153)/SUMIF(Hotel_Performance!$D$2:$D$1153,$H94,Hotel_Performance!$E$2:$E$1153) -> 0.56291171 | D94: =SUMIF(Hotel_Performance!$D$2:$D$1153,$H94,Hotel_Performance!$I$2:$I$1153)/SUMIF(Hotel_Performance!$D$2:$D$1153,$H94,Hotel_Performance!$F$2:$F$1153) -> 5875.3528 | E94: =SUMIF(Hotel_Performance!$D$2:$D$1153,$H94,Hotel_Performance!$I$2:$I$1153)/SUMIF(Hotel_Performance!$D$2:$D$1153,$H94,Hotel_Performance!$E$2:$E$1153) -> 3307.3049 | F94: =SUMIF(Hotel_Performance!$D$2:$D$1153,$H94,Hotel_Performance!$K$2:$K$1153)/10000000 -> 89.607125 | G94: =SUMIF(Hotel_Performance!$D$2:$D$1153,$H94,Hotel_Performance!$M$2:$M$1153)/10000000 -> 21.502391 | H94: 46266
B97: By star rating | G97: Top 10 hotels by GOP
B98: Stars | C98: Occupancy | D98: RevPAR | E98: GOP Margin | G98: Hotel | H98: GOP (Cr) | I98: Occupancy | J98: Key
B99: 3 | C99: =SUMIF(Hotel_Performance!$C$2:$C$1153,$B99,Hotel_Performance!$F$2:$F$1153)/SUMIF(Hotel_Performance!$C$2:$C$1153,$B99,Hotel_Performance!$E$2:$E$1153) -> 0.70711882 | D99: =SUMIF(Hotel_Performance!$C$2:$C$1153,$B99,Hotel_Performance!$I$2:$I$1153)/SUMIF(Hotel_Performance!$C$2:$C$1153,$B99,Hotel_Performance!$E$2:$E$1153) -> 2382.1761 | E99: =SUMIF(Hotel_Performance!$C$2:$C$1153,$B99,Hotel_Performance!$M$2:$M$1153)/SUMIF(Hotel_Performance!$C$2:$C$1153,$B99,Hotel_Performance!$K$2:$K$1153) -> 0.38631158 | G99: =INDEX(Hotels!$B$2:$B$49,MATCH($J99,Hotels!$A$2:$A$49,0)) -> Maple Leaf Inn Shimla | H99: =SUMIF(Hotel_Performance!$A$2:$A$1153,$J99,Hotel_Performance!$M$2:$M$1153)/10000000 -> 34.926684 | I99: =SUMIF(Hotel_Performance!$A$2:$A$1153,$J99,Hotel_Performance!$F$2:$F$1153)/SUMIF(Hotel_Performance!$A$2:$A$1153,$J99,Hotel_Performance!$E$2:$E$1153) -> 0.67704601 | J99: H034
B100: 4 | C100: =SUMIF(Hotel_Performance!$C$2:$C$1153,$B100,Hotel_Performance!$F$2:$F$1153)/SUMIF(Hotel_Performance!$C$2:$C$1153,$B100,Hotel_Performance!$E$2:$E$1153) -> 0.68572487 | D100: =SUMIF(Hotel_Performance!$C$2:$C$1153,$B100,Hotel_Performance!$I$2:$I$1153)/SUMIF(Hotel_Performance!$C$2:$C$1153,$B100,Hotel_Performance!$E$2:$E$1153) -> 3848.8688 | E100: =SUMIF(Hotel_Performance!$C$2:$C$1153,$B100,Hotel_Performance!$M$2:$M$1153)/SUMIF(Hotel_Performance!$C$2:$C$1153,$B100,Hotel_Performance!$K$2:$K$1153) -> 0.37723577 | G100: =INDEX(Hotels!$B$2:$B$49,MATCH($J100,Hotels!$A$2:$A$49,0)) -> Royal Mirage New Delhi | H100: =SUMIF(Hotel_Performance!$A$2:$A$1153,$J100,Hotel_Performance!$M$2:$M$1153)/10000000 -> 38.277156 | I100: =SUMIF(Hotel_Performance!$A$2:$A$1153,$J100,Hotel_Performance!$F$2:$F$1153)/SUMIF(Hotel_Performance!$A$2:$A$1153,$J100,Hotel_Performance!$E$2:$E$1153) -> 0.74735133 | J100: H021
B101: 5 | C101: =SUMIF(Hotel_Performance!$C$2:$C$1153,$B101,Hotel_Performance!$F$2:$F$1153)/SUMIF(Hotel_Performance!$C$2:$C$1153,$B101,Hotel_Performance!$E$2:$E$1153) -> 0.68899204 | D101: =SUMIF(Hotel_Performance!$C$2:$C$1153,$B101,Hotel_Performance!$I$2:$I$1153)/SUMIF(Hotel_Performance!$C$2:$C$1153,$B101,Hotel_Performance!$E$2:$E$1153) -> 7487.1529 | E101: =SUMIF(Hotel_Performance!$C$2:$C$1153,$B101,Hotel_Performance!$M$2:$M$1153)/SUMIF(Hotel_Performance!$C$2:$C$1153,$B101,Hotel_Performance!$K$2:$K$1153) -> 0.38860543 | G101: =INDEX(Hotels!$B$2:$B$49,MATCH($J101,Hotels!$A$2:$A$49,0)) -> Lotus Grand Rishikesh | H101: =SUMIF(Hotel_Performance!$A$2:$A$1153,$J101,Hotel_Performance!$M$2:$M$1153)/10000000 -> 39.238109 | I101: =SUMIF(Hotel_Performance!$A$2:$A$1153,$J101,Hotel_Performance!$F$2:$F$1153)/SUMIF(Hotel_Performance!$A$2:$A$1153,$J101,Hotel_Performance!$E$2:$E$1153) -> 0.64790201 | J101: H043
G102: =INDEX(Hotels!$B$2:$B$49,MATCH($J102,Hotels!$A$2:$A$49,0)) -> Blue Lagoon Mumbai | H102: =SUMIF(Hotel_Performance!$A$2:$A$1153,$J102,Hotel_Performance!$M$2:$M$1153)/10000000 -> 45.045197 | I102: =SUMIF(Hotel_Performance!$A$2:$A$1153,$J102,Hotel_Performance!$F$2:$F$1153)/SUMIF(Hotel_Performance!$A$2:$A$1153,$J102,Hotel_Performance!$E$2:$E$1153) -> 0.68266638 | J102: H020
G103: =INDEX(Hotels!$B$2:$B$49,MATCH($J103,Hotels!$A$2:$A$49,0)) -> Sunrise Residency Kochi | H103: =SUMIF(Hotel_Performance!$A$2:$A$1153,$J103,Hotel_Performance!$M$2:$M$1153)/10000000 -> 60.412978 | I103: =SUMIF(Hotel_Performance!$A$2:$A$1153,$J103,Hotel_Performance!$F$2:$F$1153)/SUMIF(Hotel_Performance!$A$2:$A$1153,$J103,Hotel_Performance!$E$2:$E$1153) -> 0.6397101 | J103: H029
G104: =INDEX(Hotels!$B$2:$B$49,MATCH($J104,Hotels!$A$2:$A$49,0)) -> Azure Bay Goa | H104: =SUMIF(Hotel_Performance!$A$2:$A$1153,$J104,Hotel_Performance!$M$2:$M$1153)/10000000 -> 74.53329 | I104: =SUMIF(Hotel_Performance!$A$2:$A$1153,$J104,Hotel_Performance!$F$2:$F$1153)/SUMIF(Hotel_Performance!$A$2:$A$1153,$J104,Hotel_Performance!$E$2:$E$1153) -> 0.72620653 | J104: H002
G105: =INDEX(Hotels!$B$2:$B$49,MATCH($J105,Hotels!$A$2:$A$49,0)) -> Cedar Crest Jaipur | H105: =SUMIF(Hotel_Performance!$A$2:$A$1153,$J105,Hotel_Performance!$M$2:$M$1153)/10000000 -> 77.518357 | I105: =SUMIF(Hotel_Performance!$A$2:$A$1153,$J105,Hotel_Performance!$F$2:$F$1153)/SUMIF(Hotel_Performance!$A$2:$A$1153,$J105,Hotel_Performance!$E$2:$E$1153) -> 0.7297159 | J105: H006
G106: =INDEX(Hotels!$B$2:$B$49,MATCH($J106,Hotels!$A$2:$A$49,0)) -> Saffron Suites Udaipur | H106: =SUMIF(Hotel_Performance!$A$2:$A$1153,$J106,Hotel_Performance!$M$2:$M$1153)/10000000 -> 82.525949 | I106: =SUMIF(Hotel_Performance!$A$2:$A$1153,$J106,Hotel_Performance!$F$2:$F$1153)/SUMIF(Hotel_Performance!$A$2:$A$1153,$J106,Hotel_Performance!$E$2:$E$1153) -> 0.71615974 | J106: H010
G107: =INDEX(Hotels!$B$2:$B$49,MATCH($J107,Hotels!$A$2:$A$49,0)) -> Heritage Palms Bengaluru | H107: =SUMIF(Hotel_Performance!$A$2:$A$1153,$J107,Hotel_Performance!$M$2:$M$1153)/10000000 -> 98.063082 | I107: =SUMIF(Hotel_Performance!$A$2:$A$1153,$J107,Hotel_Performance!$F$2:$F$1153)/SUMIF(Hotel_Performance!$A$2:$A$1153,$J107,Hotel_Performance!$E$2:$E$1153) -> 0.74027738 | J107: H028
G108: =INDEX(Hotels!$B$2:$B$49,MATCH($J108,Hotels!$A$2:$A$49,0)) -> Golden Sands New Delhi | H108: =SUMIF(Hotel_Performance!$A$2:$A$1153,$J108,Hotel_Performance!$M$2:$M$1153)/10000000 -> 116.30899 | I108: =SUMIF(Hotel_Performance!$A$2:$A$1153,$J108,Hotel_Performance!$F$2:$F$1153)/SUMIF(Hotel_Performance!$A$2:$A$1153,$J108,Hotel_Performance!$E$2:$E$1153) -> 0.73805605 | J108: H023

Sheet Tourism_Trends
A1: City | B1: Month | C1: Year | D1: Season | E1: Total_Arrivals | F1: Domestic_Arrivals | G1: International_Arrivals | H1: Avg_Stay_Nights | I1: Avg_Daily_Spend_INR | J1: Tourism_Revenue_Cr | K1: Hotel_Search_Index | L1: Avg_Temp_C | M1: Rainfall_mm | N1: Major_Event
A2: Goa | B2: 45566 | C2: =YEAR(B2) -> 2024 | D2: Shoulder | E2: =F2+G2 -> 634100 | F2: 515400 | G2: 118700 | H2: 4.2 | I2: 5450 | J2: =E2*H2*I2/10000000 -> 1451.4549 | K2: 43 | L2: 26.6 | M2: 9 | N2: Diwali Season
A3: Goa | B3: 45597 | C3: =YEAR(B3) -> 2024 | D3: Peak | E3: =F3+G3 -> 899800 | F3: 729200 | G3: 170600 | H3: 3.7 | I3: 5600 | J3: =E3*H3*I3/10000000 -> 1864.3856 | K3: 79 | L3: 26.5 | M3: 35 | N3: Diwali Season
A4: Goa | B4: 45627 | C4: =YEAR(B4) -> 2024 | D4: Peak | E4: =F4+G4 -> 869000 | F4: 705000 | G4: 164000 | H4: 4 | I4: 5350 | J4: =E4*H4*I4/10000000 -> 1859.66 | K4: 81 | L4: 25.5 | M4: 31 | N4: Christmas & New Year
A5: Goa | B5: 45658 | C5: =YEAR(B5) -> 2025 | D5: Peak | E5: =F5+G5 -> 967100 | F5: 801000 | G5: 166100 | H5: 3.8 | I5: 5750 | J5: =E5*H5*I5/10000000 -> 2113.1135 | K5: 74 | L5: 24.2 | M5: 14 | N5: None
A6: Goa | B6: 45689 | C6: =YEAR(B6) -> 2025 | D6: Peak | E6: =F6+G6 -> 868600 | F6: 706300 | G6: 162300 | H6: 4.2 | I6: 5450 | J6: =E6*H6*I6/10000000 -> 1988.2254 | K6: 66 | L6: 26.1 | M6: 0 | N6: Goa Carnival
A7: Goa | B7: 45717 | C7: =YEAR(B7) -> 2025 | D7: Shoulder | E7: =F7+G7 -> 605100 | F7: 501200 | G7: 103900 | H7: 4.1 | I7: 5350 | J7: =E7*H7*I7/10000000 -> 1327.2868 | K7: 44 | L7: 29.3 | M7: 26 | N7: Holi
A8: Goa | B8: 45748 | C8: =YEAR(B8) -> 2025 | D8: Shoulder | E8: =F8+G8 -> 632300 | F8: 527500 | G8: 104800 | H8: 3.8 | I8: 5900 | J8: =E8*H8*I8/10000000 -> 1417.6166 | K8: 51 | L8: 30.5 | M8: 37 | N8: None
A9: Goa | B9: 45778 | C9: =YEAR(B9) -> 2025 | D9: Shoulder | E9: =F9+G9 -> 630900 | F9: 518700 | G9: 112200 | H9: 4.3 | I9: 5600 | J9: =E9*H9*I9/10000000 -> 1519.2072 | K9: 54 | L9: 29.7 | M9: 8 | N9: Summer Vacation
A10: Goa | B10: 45809 | C10: =YEAR(B10) -> 2025 | D10: Off-Peak | E10: =F10+G10 -> 360900 | F10: 296400 | G10: 64500 | H10: 4.3 | I10: 5600 | J10: =E10*H10*I10/10000000 -> 869.0472 | K10: 24 | L10: 29.6 | M10: 566 | N10: Summer Vacation
A11: Goa | B11: 45839 | C11: =YEAR(B11) -> 2025 | D11: Off-Peak | E11: =F11+G11 -> 395600 | F11: 319300 | G11: 76300 | H11: 3.8 | I11: 5350 | J11: =E11*H11*I11/10000000 -> 804.2548 | K11: 27 | L11: 29.1 | M11: 628 | N11: None
A12: Goa | B12: 45870 | C12: =YEAR(B12) -> 2025 | D12: Off-Peak | E12: =F12+G12 -> 387700 | F12: 315000 | G12: 72700 | H12: 3.8 | I12: 5950 | J12: =E12*H12*I12/10000000 -> 876.5897 | K12: 32 | L12: 29.8 | M12: 718 | N12: None
A13: Goa | B13: 45901 | C13: =YEAR(B13) -> 2025 | D13: Off-Peak | E13: =F13+G13 -> 378000 | F13: 304100 | G13: 73900 | H13: 4.2 | I13: 5800 | J13: =E13*H13*I13/10000000 -> 920.808 | K13: 27 | L13: 26.5 | M13: 131 | N13: None
... A289: Varanasi | B289: 46266 | C289: =YEAR(B289) -> 2026 | D289: Off-Peak | E289: =F289+G289 -> 301000 | F289: 266100 | G289: 34900 | H289: 2.1 | I289: 3300 | J289: =E289*H289*I289/10000000 -> 208.593 | K289: 26 | L289: 26.6 | M289: 168 | N289: None

Sheet Tourism_Trends_Dashboard
B1: Tourism Trends - Dashboard
B3: Total Arrivals (Cr) | D3: International Share | F3: Tourism Revenue (INR Cr) | H3: Avg Stay (nights) | J3: Avg Daily Spend (INR) | L3: Avg Hotel Search Index | N3: Avg Temp (C)
B4: =SUM(Tourism_Trends!$E$2:$E$289)/10000000 -> 19.81976 | D4: =SUM(Tourism_Trends!$G$2:$G$289)/SUM(Tourism_Trends!$E$2:$E$289) -> 0.16595004 | F4: =SUM(Tourism_Trends!$J$2:$J$289) -> 278382.11 | H4: =AVERAGE(Tourism_Trends!$H$2:$H$289) -> 2.6916667 | J4: =AVERAGE(Tourism_Trends!$I$2:$I$289) -> 4904.3403 | L4: =AVERAGE(Tourism_Trends!$K$2:$K$289) -> 53.895833 | N4: =AVERAGE(Tourism_Trends!$L$2:$L$289) -> 23.526736
B52: Chart data (live formulas - charts above read from these tables)
B54: By month | I54: By city
B55: Month | C55: Arrivals (Lakh) | D55: Intl Share | E55: Revenue (Cr) | F55: Search Index | G55: Key | I55: City | J55: Domestic (Lakh) | K55: International (Lakh) | L55: Revenue (Cr) | M55: Avg Search Idx
B56: =TEXT($G56,"mmm yy") -> Oct 24 | C56: =SUMIF(Tourism_Trends!$B$2:$B$289,$G56,Tourism_Trends!$E$2:$E$289)/100000 -> 87.924 | D56: =SUMIF(Tourism_Trends!$B$2:$B$289,$G56,Tourism_Trends!$G$2:$G$289)/SUMIF(Tourism_Trends!$B$2:$B$289,$G56,Tourism_Trends!$E$2:$E$289) -> 0.18067877 | E56: =SUMIF(Tourism_Trends!$B$2:$B$289,$G56,Tourism_Trends!$J$2:$J$289) -> 11756.198 | F56: =AVERAGEIF(Tourism_Trends!$B$2:$B$289,$G56,Tourism_Trends!$K$2:$K$289) -> 60.583333 | G56: 45566 | I56: Rishikesh | J56: =SUMIF(Tourism_Trends!$A$2:$A$289,$I56,Tourism_Trends!$F$2:$F$289)/100000 -> 82.357 | K56: =SUMIF(Tourism_Trends!$A$2:$A$289,$I56,Tourism_Trends!$G$2:$G$289)/100000 -> 9.114 | L56: =SUMIF(Tourism_Trends!$A$2:$A$289,$I56,Tourism_Trends!$J$2:$J$289) -> 7460.3306 | M56: =AVERAGEIF(Tourism_Trends!$A$2:$A$289,$I56,Tourism_Trends!$K$2:$K$289) -> 54.375
B57: =TEXT($G57,"mmm yy") -> Nov 24 | C57: =SUMIF(Tourism_Trends!$B$2:$B$289,$G57,Tourism_Trends!$E$2:$E$289)/100000 -> 102.189 | D57: =SUMIF(Tourism_Trends!$B$2:$B$289,$G57,Tourism_Trends!$G$2:$G$289)/SUMIF(Tourism_Trends!$B$2:$B$289,$G57,Tourism_Trends!$E$2:$E$289) -> 0.17430448 | E57: =SUMIF(Tourism_Trends!$B$2:$B$289,$G57,Tourism_Trends!$J$2:$J$289) -> 13731.048 | F57: =AVERAGEIF(Tourism_Trends!$B$2:$B$289,$G57,Tourism_Trends!$K$2:$K$289) -> 69.083333 | G57: 45597 | I57: Varanasi | J57: =SUMIF(Tourism_Trends!$A$2:$A$289,$I57,Tourism_Trends!$F$2:$F$289)/100000 -> 109.598 | K57: =SUMIF(Tourism_Trends!$A$2:$A$289,$I57,Tourism_Trends!$G$2:$G$289)/100000 -> 14.777 | L57: =SUMIF(Tourism_Trends!$A$2:$A$289,$I57,Tourism_Trends!$J$2:$J$289) -> 7610.3462 | M57: =AVERAGEIF(Tourism_Trends!$A$2:$A$289,$I57,Tourism_Trends!$K$2:$K$289) -> 54.291667
B58: =TEXT($G58,"mmm yy") -> Dec 24 | C58: =SUMIF(Tourism_Trends!$B$2:$B$289,$G58,Tourism_Trends!$E$2:$E$289)/100000 -> 106.099 | D58: =SUMIF(Tourism_Trends!$B$2:$B$289,$G58,Tourism_Trends!$G$2:$G$289)/SUMIF(Tourism_Trends!$B$2:$B$289,$G58,Tourism_Trends!$E$2:$E$289) -> 0.17021838 | E58: =SUMIF(Tourism_Trends!$B$2:$B$289,$G58,Tourism_Trends!$J$2:$J$289) -> 15122.788 | F58: =AVERAGEIF(Tourism_Trends!$B$2:$B$289,$G58,Tourism_Trends!$K$2:$K$289) -> 76.25 | G58: 45627 | I58: Agra | J58: =SUMIF(Tourism_Trends!$A$2:$A$289,$I58,Tourism_Trends!$F$2:$F$289)/100000 -> 92.375 | K58: =SUMIF(Tourism_Trends!$A$2:$A$289,$I58,Tourism_Trends!$G$2:$G$289)/100000 -> 49.621 | L58: =SUMIF(Tourism_Trends!$A$2:$A$289,$I58,Tourism_Trends!$J$2:$J$289) -> 7908.7984 | M58: =AVERAGEIF(Tourism_Trends!$A$2:$A$289,$I58,Tourism_Trends!$K$2:$K$289) -> 55.75
B59: =TEXT($G59,"mmm yy") -> Jan 25 | C59: =SUMIF(Tourism_Trends!$B$2:$B$289,$G59,Tourism_Trends!$E$2:$E$289)/100000 -> 105.593 | D59: =SUMIF(Tourism_Trends!$B$2:$B$289,$G59,Tourism_Trends!$G$2:$G$289)/SUMIF(Tourism_Trends!$B$2:$B$289,$G59,Tourism_Trends!$E$2:$E$289) -> 0.17177275 | E59: =SUMIF(Tourism_Trends!$B$2:$B$289,$G59,Tourism_Trends!$J$2:$J$289) -> 13855.878 | F59: =AVERAGEIF(Tourism_Trends!$B$2:$B$289,$G59,Tourism_Trends!$K$2:$K$289) -> 71 | G59: 45658 | I59: Shimla | J59: =SUMIF(Tourism_Trends!$A$2:$A$289,$I59,Tourism_Trends!$F$2:$F$289)/100000 -> 80.49 | K59: =SUMIF(Tourism_Trends!$A$2:$A$289,$I59,Tourism_Trends!$G$2:$G$289)/100000 -> 2.525 | L59: =SUMIF(Tourism_Trends!$A$2:$A$289,$I59,Tourism_Trends!$J$2:$J$289) -> 10269.535 | M59: =AVERAGEIF(Tourism_Trends!$A$2:$A$289,$I59,Tourism_Trends!$K$2:$K$289) -> 52.541667
B60: =TEXT($G60,"mmm yy") -> Feb 25 | C60: =SUMIF(Tourism_Trends!$B$2:$B$289,$G60,Tourism_Trends!$E$2:$E$289)/100000 -> 104.595 | D60: =SUMIF(Tourism_Trends!$B$2:$B$289,$G60,Tourism_Trends!$G$2:$G$289)/SUMIF(Tourism_Trends!$B$2:$B$289,$G60,Tourism_Trends!$E$2:$E$289) -> 0.17277116 | E60: =SUMIF(Tourism_Trends!$B$2:$B$289,$G60,Tourism_Trends!$J$2:$J$289) -> 14292.861 | F60: =AVERAGEIF(Tourism_Trends!$B$2:$B$289,$G60,Tourism_Trends!$K$2:$K$289) -> 67.833333 | G60: 45689 | I60: Manali | J60: =SUMIF(Tourism_Trends!$A$2:$A$289,$I60,Tourism_Trends!$F$2:$F$289)/100000 -> 75.611 | K60: =SUMIF(Tourism_Trends!$A$2:$A$289,$I60,Tourism_Trends!$G$2:$G$289)/100000 -> 3.123 | L60: =SUMIF(Tourism_Trends!$A$2:$A$289,$I60,Tourism_Trends!$J$2:$J$289) -> 11584.155 | M60: =AVERAGEIF(Tourism_Trends!$A$2:$A$289,$I60,Tourism_Trends!$K$2:$K$289) -> 56.166667
B61: =TEXT($G61,"mmm yy") -> Mar 25 | C61: =SUMIF(Tourism_Trends!$B$2:$B$289,$G61,Tourism_Trends!$E$2:$E$289)/100000 -> 97.903 | D61: =SUMIF(Tourism_Trends!$B$2:$B$289,$G61,Tourism_Trends!$G$2:$G$289)/SUMIF(Tourism_Trends!$B$2:$B$289,$G61,Tourism_Trends!$E$2:$E$289) -> 0.16444848 | E61: =SUMIF(Tourism_Trends!$B$2:$B$289,$G61,Tourism_Trends!$J$2:$J$289) -> 12781.415 | F61: =AVERAGEIF(Tourism_Trends!$B$2:$B$289,$G61,Tourism_Trends!$K$2:$K$289) -> 62.5 | G61: 45717 | I61: Udaipur | J61: =SUMIF(Tourism_Trends!$A$2:$A$289,$I61,Tourism_Trends!$F$2:$F$289)/100000 -> 50.164 | K61: =SUMIF(Tourism_Trends!$A$2:$A$289,$I61,Tourism_Trends!$G$2:$G$289)/100000 -> 21.103 | L61: =SUMIF(Tourism_Trends!$A$2:$A$289,$I61,Tourism_Trends!$J$2:$J$289) -> 12407.015 | M61: =AVERAGEIF(Tourism_Trends!$A$2:$A$289,$I61,Tourism_Trends!$K$2:$K$289) -> 54.333333
B62: =TEXT($G62,"mmm yy") -> Apr 25 | C62: =SUMIF(Tourism_Trends!$B$2:$B$289,$G62,Tourism_Trends!$E$2:$E$289)/100000 -> 79.518 | D62: =SUMIF(Tourism_Trends!$B$2:$B$289,$G62,Tourism_Trends!$G$2:$G$289)/SUMIF(Tourism_Trends!$B$2:$B$289,$G62,Tourism_Trends!$E$2:$E$289) -> 0.15401544 | E62: =SUMIF(Tourism_Trends!$B$2:$B$289,$G62,Tourism_Trends!$J$2:$J$289) -> 11007.453 | F62: =AVERAGEIF(Tourism_Trends!$B$2:$B$289,$G62,Tourism_Trends!$K$2:$K$289) -> 53.5 | G62: 45748 | I62: Jaipur | J62: =SUMIF(Tourism_Trends!$A$2:$A$289,$I62,Tourism_Trends!$F$2:$F$289)/100000 -> 95.943 | K62: =SUMIF(Tourism_Trends!$A$2:$A$289,$I62,Tourism_Trends!$G$2:$G$289)/100000 -> 31.818 | L62: =SUMIF(Tourism_Trends!$A$2:$A$289,$I62,Tourism_Trends!$J$2:$J$289) -> 13991.261 | M62: =AVERAGEIF(Tourism_Trends!$A$2:$A$289,$I62,Tourism_Trends!$K$2:$K$289) -> 53.708333
B63: =TEXT($G63,"mmm yy") -> May 25 | C63: =SUMIF(Tourism_Trends!$B$2:$B$289,$G63,Tourism_Trends!$E$2:$E$289)/100000 -> 79.386 | D63: =SUMIF(Tourism_Trends!$B$2:$B$289,$G63,Tourism_Trends!$G$2:$G$289)/SUMIF(Tourism_Trends!$B$2:$B$289,$G63,Tourism_Trends!$E$2:$E$289) -> 0.15900789 | E63: =SUMIF(Tourism_Trends!$B$2:$B$289,$G63,Tourism_Trends!$J$2:$J$289) -> 11067.786 | F63: =AVERAGEIF(Tourism_Trends!$B$2:$B$289,$G63,Tourism_Trends!$K$2:$K$289) -> 54.666667 | G63: 45778 | I63: Kochi | J63: =SUMIF(Tourism_Trends!$A$2:$A$289,$I63,Tourism_Trends!$F$2:$F$289)/100000 -> 87.815 | K63: =SUMIF(Tourism_Trends!$A$2:$A$289,$I63,Tourism_Trends!$G$2:$G$289)/100000 -> 14.184 | L63: =SUMIF(Tourism_Trends!$A$2:$A$289,$I63,Tourism_Trends!$J$2:$J$289) -> 15417.492 | M63: =AVERAGEIF(Tourism_Trends!$A$2:$A$289,$I63,Tourism_Trends!$K$2:$K$289) -> 56.041667
B64: =TEXT($G64,"mmm yy") -> Jun 25 | C64: =SUMIF(Tourism_Trends!$B$2:$B$289,$G64,Tourism_Trends!$E$2:$E$289)/100000 -> 49.841 | D64: =SUMIF(Tourism_Trends!$B$2:$B$289,$G64,Tourism_Trends!$G$2:$G$289)/SUMIF(Tourism_Trends!$B$2:$B$289,$G64,Tourism_Trends!$E$2:$E$289) -> 0.14927469 | E64: =SUMIF(Tourism_Trends!$B$2:$B$289,$G64,Tourism_Trends!$J$2:$J$289) -> 7173.1564 | F64: =AVERAGEIF(Tourism_Trends!$B$2:$B$289,$G64,Tourism_Trends!$K$2:$K$289) -> 34.75 | G64: 45809 | I64: Bengaluru | J64: =SUMIF(Tourism_Trends!$A$2:$A$289,$I64,Tourism_Trends!$F$2:$F$289)/100000 -> 232.286 | K64: =SUMIF(Tourism_Trends!$A$2:$A$289,$I64,Tourism_Trends!$G$2:$G$289)/100000 -> 20.114 | L64: =SUMIF(Tourism_Trends!$A$2:$A$289,$I64,Tourism_Trends!$J$2:$J$289) -> 34655.05 | M64: =AVERAGEIF(Tourism_Trends!$A$2:$A$289,$I64,Tourism_Trends!$K$2:$K$289) -> 53.083333
B65: =TEXT($G65,"mmm yy") -> Jul 25 | C65: =SUMIF(Tourism_Trends!$B$2:$B$289,$G65,Tourism_Trends!$E$2:$E$289)/100000 -> 45.204 | D65: =SUMIF(Tourism_Trends!$B$2:$B$289,$G65,Tourism_Trends!$G$2:$G$289)/SUMIF(Tourism_Trends!$B$2:$B$289,$G65,Tourism_Trends!$E$2:$E$289) -> 0.17261747 | E65: =SUMIF(Tourism_Trends!$B$2:$B$289,$G65,Tourism_Trends!$J$2:$J$289) -> 6216.6565 | F65: =AVERAGEIF(Tourism_Trends!$B$2:$B$289,$G65,Tourism_Trends!$K$2:$K$289) -> 30.75 | G65: 45839 | I65: Goa | J65: =SUMIF(Tourism_Trends!$A$2:$A$289,$I65,Tourism_Trends!$F$2:$F$289)/100000 -> 130.254 | K65: =SUMIF(Tourism_Trends!$A$2:$A$289,$I65,Tourism_Trends!$G$2:$G$289)/100000 -> 28.814 | L65: =SUMIF(Tourism_Trends!$A$2:$A$289,$I65,Tourism_Trends!$J$2:$J$289) -> 36547.446 | M65: =AVERAGEIF(Tourism_Trends!$A$2:$A$289,$I65,Tourism_Trends!$K$2:$K$289) -> 50.041667
B66: =TEXT($G66,"mmm yy") -> Aug 25 | C66: =SUMIF(Tourism_Trends!$B$2:$B$289,$G66,Tourism_Trends!$E$2:$E$289)/100000 -> 46.441 | D66: =SUMIF(Tourism_Trends!$B$2:$B$289,$G66,Tourism_Trends!$G$2:$G$289)/SUMIF(Tourism_Trends!$B$2:$B$289,$G66,Tourism_Trends!$E$2:$E$289) -> 0.16526345 | E66: =SUMIF(Tourism_Trends!$B$2:$B$289,$G66,Tourism_Trends!$J$2:$J$289) -> 6728.4198 | F66: =AVERAGEIF(Tourism_Trends!$B$2:$B$289,$G66,Tourism_Trends!$K$2:$K$289) -> 29.25 | G66: 45870 | I66: Mumbai | J66: =SUMIF(Tourism_Trends!$A$2:$A$289,$I66,Tourism_Trends!$F$2:$F$289)/100000 -> 268.343 | K66: =SUMIF(Tourism_Trends!$A$2:$A$289,$I66,Tourism_Trends!$G$2:$G$289)/100000 -> 47.909 | L66: =SUMIF(Tourism_Trends!$A$2:$A$289,$I66,Tourism_Trends!$J$2:$J$289) -> 58068.703 | M66: =AVERAGEIF(Tourism_Trends!$A$2:$A$289,$I66,Tourism_Trends!$K$2:$K$289) -> 51.541667
B67: =TEXT($G67,"mmm yy") -> Sep 25 | C67: =SUMIF(Tourism_Trends!$B$2:$B$289,$G67,Tourism_Trends!$E$2:$E$289)/100000 -> 47.872 | D67: =SUMIF(Tourism_Trends!$B$2:$B$289,$G67,Tourism_Trends!$G$2:$G$289)/SUMIF(Tourism_Trends!$B$2:$B$289,$G67,Tourism_Trends!$E$2:$E$289) -> 0.15614555 | E67: =SUMIF(Tourism_Trends!$B$2:$B$289,$G67,Tourism_Trends!$J$2:$J$289) -> 6560.0264 | F67: =AVERAGEIF(Tourism_Trends!$B$2:$B$289,$G67,Tourism_Trends!$K$2:$K$289) -> 32 | G67: 45901 | I67: New Delhi | J67: =SUMIF(Tourism_Trends!$A$2:$A$289,$I67,Tourism_Trends!$F$2:$F$289)/100000 -> 347.831 | K67: =SUMIF(Tourism_Trends!$A$2:$A$289,$I67,Tourism_Trends!$G$2:$G$289)/100000 -> 85.807 | L67: =SUMIF(Tourism_Trends!$A$2:$A$289,$I67,Tourism_Trends!$J$2:$J$289) -> 62461.976 | M67: =AVERAGEIF(Tourism_Trends!$A$2:$A$289,$I67,Tourism_Trends!$K$2:$K$289) -> 54.875
B68: =TEXT($G68,"mmm yy") -> Oct 25 | C68: =SUMIF(Tourism_Trends!$B$2:$B$289,$G68,Tourism_Trends!$E$2:$E$289)/100000 -> 96.028 | D68: =SUMIF(Tourism_Trends!$B$2:$B$289,$G68,Tourism_Trends!$G$2:$G$289)/SUMIF(Tourism_Trends!$B$2:$B$289,$G68,Tourism_Trends!$E$2:$E$289) -> 0.17641729 | E68: =SUMIF(Tourism_Trends!$B$2:$B$289,$G68,Tourism_Trends!$J$2:$J$289) -> 13034.95 | F68: =AVERAGEIF(Tourism_Trends!$B$2:$B$289,$G68,Tourism_Trends!$K$2:$K$289) -> 63.25 | G68: 45931
B69: =TEXT($G69,"mmm yy") -> Nov 25 | C69: =SUMIF(Tourism_Trends!$B$2:$B$289,$G69,Tourism_Trends!$E$2:$E$289)/100000 -> 109.826 | D69: =SUMIF(Tourism_Trends!$B$2:$B$289,$G69,Tourism_Trends!$G$2:$G$289)/SUMIF(Tourism_Trends!$B$2:$B$289,$G69,Tourism_Trends!$E$2:$E$289) -> 0.16613552 | E69: =SUMIF(Tourism_Trends!$B$2:$B$289,$G69,Tourism_Trends!$J$2:$J$289) -> 16051.819 | F69: =AVERAGEIF(Tourism_Trends!$B$2:$B$289,$G69,Tourism_Trends!$K$2:$K$289) -> 68.75 | G69: 45962
B70: =TEXT($G70,"mmm yy") -> Dec 25 | C70: =SUMIF(Tourism_Trends!$B$2:$B$289,$G70,Tourism_Trends!$E$2:$E$289)/100000 -> 115.326 | D70: =SUMIF(Tourism_Trends!$B$2:$B$289,$G70,Tourism_Trends!$G$2:$G$289)/SUMIF(Tourism_Trends!$B$2:$B$289,$G70,Tourism_Trends!$E$2:$E$289) -> 0.16002463 | E70: =SUMIF(Tourism_Trends!$B$2:$B$289,$G70,Tourism_Trends!$J$2:$J$289) -> 16949.691 | F70: =AVERAGEIF(Tourism_Trends!$B$2:$B$289,$G70,Tourism_Trends!$K$2:$K$289) -> 74.166667 | G70: 45992
B71: =TEXT($G71,"mmm yy") -> Jan 26 | C71: =SUMIF(Tourism_Trends!$B$2:$B$289,$G71,Tourism_Trends!$E$2:$E$289)/100000 -> 113.744 | D71: =SUMIF(Tourism_Trends!$B$2:$B$289,$G71,Tourism_Trends!$G$2:$G$289)/SUMIF(Tourism_Trends!$B$2:$B$289,$G71,Tourism_Trends!$E$2:$E$289) -> 0.16594282 | E71: =SUMIF(Tourism_Trends!$B$2:$B$289,$G71,Tourism_Trends!$J$2:$J$289) -> 16614.454 | F71: =AVERAGEIF(Tourism_Trends!$B$2:$B$289,$G71,Tourism_Trends!$K$2:$K$289) -> 68.833333 | G71: 46023
B72: =TEXT($G72,"mmm yy") -> Feb 26 | C72: =SUMIF(Tourism_Trends!$B$2:$B$289,$G72,Tourism_Trends!$E$2:$E$289)/100000 -> 112.355 | D72: =SUMIF(Tourism_Trends!$B$2:$B$289,$G72,Tourism_Trends!$G$2:$G$289)/SUMIF(Tourism_Trends!$B$2:$B$289,$G72,Tourism_Trends!$E$2:$E$289) -> 0.16073161 | E72: =SUMIF(Tourism_Trends!$B$2:$B$289,$G72,Tourism_Trends!$J$2:$J$289) -> 15483.011 | F72: =AVERAGEIF(Tourism_Trends!$B$2:$B$289,$G72,Tourism_Trends!$K$2:$K$289) -> 68.75 | G72: 46054
B73: =TEXT($G73,"mmm yy") -> Mar 26 | C73: =SUMIF(Tourism_Trends!$B$2:$B$289,$G73,Tourism_Trends!$E$2:$E$289)/100000 -> 105.126 | D73: =SUMIF(Tourism_Trends!$B$2:$B$289,$G73,Tourism_Trends!$G$2:$G$289)/SUMIF(Tourism_Trends!$B$2:$B$289,$G73,Tourism_Trends!$E$2:$E$289) -> 0.17295436 | E73: =SUMIF(Tourism_Trends!$B$2:$B$289,$G73,Tourism_Trends!$J$2:$J$289) -> 15120.891 | F73: =AVERAGEIF(Tourism_Trends!$B$2:$B$289,$G73,Tourism_Trends!$K$2:$K$289) -> 65.916667 | G73: 46082
B74: =TEXT($G74,"mmm yy") -> Apr 26 | C74: =SUMIF(Tourism_Trends!$B$2:$B$289,$G74,Tourism_Trends!$E$2:$E$289)/100000 -> 85.857 | D74: =SUMIF(Tourism_Trends!$B$2:$B$289,$G74,Tourism_Trends!$G$2:$G$289)/SUMIF(Tourism_Trends!$B$2:$B$289,$G74,Tourism_Trends!$E$2:$E$289) -> 0.15740126 | E74: =SUMIF(Tourism_Trends!$B$2:$B$289,$G74,Tourism_Trends!$J$2:$J$289) -> 12722.683 | F74: =AVERAGEIF(Tourism_Trends!$B$2:$B$289,$G74,Tourism_Trends!$K$2:$K$289) -> 55.25 | G74: 46113
B75: =TEXT($G75,"mmm yy") -> May 26 | C75: =SUMIF(Tourism_Trends!$B$2:$B$289,$G75,Tourism_Trends!$E$2:$E$289)/100000 -> 84.551 | D75: =SUMIF(Tourism_Trends!$B$2:$B$289,$G75,Tourism_Trends!$G$2:$G$289)/SUMIF(Tourism_Trends!$B$2:$B$289,$G75,Tourism_Trends!$E$2:$E$289) -> 0.16378281 | E75: =SUMIF(Tourism_Trends!$B$2:$B$289,$G75,Tourism_Trends!$J$2:$J$289) -> 12274.52 | F75: =AVERAGEIF(Tourism_Trends!$B$2:$B$289,$G75,Tourism_Trends!$K$2:$K$289) -> 57.166667 | G75: 46143
B76: =TEXT($G76,"mmm yy") -> Jun 26 | C76: =SUMIF(Tourism_Trends!$B$2:$B$289,$G76,Tourism_Trends!$E$2:$E$289)/100000 -> 54.866 | D76: =SUMIF(Tourism_Trends!$B$2:$B$289,$G76,Tourism_Trends!$G$2:$G$289)/SUMIF(Tourism_Trends!$B$2:$B$289,$G76,Tourism_Trends!$E$2:$E$289) -> 0.15067619 | E76: =SUMIF(Tourism_Trends!$B$2:$B$289,$G76,Tourism_Trends!$J$2:$J$289) -> 8098.3039 | F76: =AVERAGEIF(Tourism_Trends!$B$2:$B$289,$G76,Tourism_Trends!$K$2:$K$289) -> 37.5 | G76: 46174
B77: =TEXT($G77,"mmm yy") -> Jul 26 | C77: =SUMIF(Tourism_Trends!$B$2:$B$289,$G77,Tourism_Trends!$E$2:$E$289)/100000 -> 49.973 | D77: =SUMIF(Tourism_Trends!$B$2:$B$289,$G77,Tourism_Trends!$G$2:$G$289)/SUMIF(Tourism_Trends!$B$2:$B$289,$G77,Tourism_Trends!$E$2:$E$289) -> 0.16622976 | E77: =SUMIF(Tourism_Trends!$B$2:$B$289,$G77,Tourism_Trends!$J$2:$J$289) -> 7050.2549 | F77: =AVERAGEIF(Tourism_Trends!$B$2:$B$289,$G77,Tourism_Trends!$K$2:$K$289) -> 30.583333 | G77: 46204
B78: =TEXT($G78,"mmm yy") -> Aug 26 | C78: =SUMIF(Tourism_Trends!$B$2:$B$289,$G78,Tourism_Trends!$E$2:$E$289)/100000 -> 49.076 | D78: =SUMIF(Tourism_Trends!$B$2:$B$289,$G78,Tourism_Trends!$G$2:$G$289)/SUMIF(Tourism_Trends!$B$2:$B$289,$G78,Tourism_Trends!$E$2:$E$289) -> 0.16678213 | E78: =SUMIF(Tourism_Trends!$B$2:$B$289,$G78,Tourism_Trends!$J$2:$J$289) -> 7119.6636 | F78: =AVERAGEIF(Tourism_Trends!$B$2:$B$289,$G78,Tourism_Trends!$K$2:$K$289) -> 28.916667 | G78: 46235
B79: =TEXT($G79,"mmm yy") -> Sep 26 | C79: =SUMIF(Tourism_Trends!$B$2:$B$289,$G79,Tourism_Trends!$E$2:$E$289)/100000 -> 52.683 | D79: =SUMIF(Tourism_Trends!$B$2:$B$289,$G79,Tourism_Trends!$G$2:$G$289)/SUMIF(Tourism_Trends!$B$2:$B$289,$G79,Tourism_Trends!$E$2:$E$289) -> 0.16513866 | E79: =SUMIF(Tourism_Trends!$B$2:$B$289,$G79,Tourism_Trends!$J$2:$J$289) -> 7568.1812 | F79: =AVERAGEIF(Tourism_Trends!$B$2:$B$289,$G79,Tourism_Trends!$K$2:$K$289) -> 32.25 | G79: 46266
B82: By season
B83: Season | C83: Avg Arrivals (Lakh) | D83: Avg Spend | E83: Avg Search Idx
B84: Peak | C84: =AVERAGEIF(Tourism_Trends!$D$2:$D$289,$B84,Tourism_Trends!$E$2:$E$289)/100000 -> 9.3336371 | D84: =AVERAGEIF(Tourism_Trends!$D$2:$D$289,$B84,Tourism_Trends!$I$2:$I$289) -> 4816.9355 | E84: =AVERAGEIF(Tourism_Trends!$D$2:$D$289,$B84,Tourism_Trends!$K$2:$K$289) -> 74.685484
B85: Off-Peak | C85: =AVERAGEIF(Tourism_Trends!$D$2:$D$289,$B85,Tourism_Trends!$E$2:$E$289)/100000 -> 4.0704889 | D85: =AVERAGEIF(Tourism_Trends!$D$2:$D$289,$B85,Tourism_Trends!$I$2:$I$289) -> 5040 | E85: =AVERAGEIF(Tourism_Trends!$D$2:$D$289,$B85,Tourism_Trends!$K$2:$K$289) -> 29.3
B86: Shoulder | C86: =AVERAGEIF(Tourism_Trends!$D$2:$D$289,$B86,Tourism_Trends!$E$2:$E$289)/100000 -> 6.1927162 | D86: =AVERAGEIF(Tourism_Trends!$D$2:$D$289,$B86,Tourism_Trends!$I$2:$I$289) -> 4885.8108 | E86: =AVERAGEIF(Tourism_Trends!$D$2:$D$289,$B86,Tourism_Trends!$K$2:$K$289) -> 48.972973

Sheet Executive_Summary
B1: Hotel & Tourism Analytics - Executive Summary
B4: 1. HOTELS > open Hotels_Dashboard
B6: Total Hotels | E6: Total Rooms
B7: =Hotels_Dashboard!$B$4 -> 48 | E7: =Hotels_Dashboard!$D$4 -> 6720
B9: Occupancy | E9: GOP Margin
B10: =Hotels_Dashboard!$L$4 -> 0.68968138 | E10: =Hotels_Dashboard!$N$4 -> 0.38413736
B12: ="Highest-occupancy city: "&INDEX(Hotels_Dashboard!$B$56:$B$67,MATCH(MAX(Hotels_Dashboard!$F$56:$F$67),Hotels_Dashboard!$F$56:$F$67,0))&" ("&TEXT(MAX(Hotels_Dashboard!$F$56:$F$67),"0.0%")&")" -> Highest-occupancy city: Bengaluru (72.4%)
B14: ="Lowest-occupancy city: "&INDEX(Hotels_Dashboard!$B$56:$B$67,MATCH(MIN(Hotels_Dashboard!$F$56:$F$67),Hotels_Dashboard!$F$56:$F$67,0))&" ("&TEXT(MIN(Hotels_Dashboard!$F$56:$F$67),"0.0%")&")" -> Lowest-occupancy city: Mumbai (65.0%)
B20: 2. CUSTOMERS > open Customers_Dashboard
B22: Total Customers | E22: Repeat Rate
B23: =Customers_Dashboard!$B$4 -> 1500 | E23: =Customers_Dashboard!$F$4 -> 0.79055258
B25: Avg CLV (INR) | E25: International Share
B26: =Customers_Dashboard!$J$4 -> 185725.78 | E26: =Customers_Dashboard!$L$4 -> 0.22
B28: ="Largest segment: "&INDEX(Customers_Dashboard!$B$56:$B$60,MATCH(MAX(Customers_Dashboard!$C$56:$C$60),Customers_Dashboard!$C$56:$C$60,0))&" ("&TEXT(MAX(Customers_Dashboard!$C$56:$C$60),"#,##0")&")" -> Largest segment: Leisure (548)
B30: ="Top acquisition source: "&INDEX(Customers_Dashboard!$B$65:$B$70,MATCH(MAX(Customers_Dashboard!$C$65:$C$70),Customers_Dashboard!$C$65:$C$70,0))&" ("&TEXT(MAX(Customers_Dashboard!$C$65:$C$70),"#,##0")&")" -> Top acquisition source: Travel Partner (290)
B36: 3. BOOKINGS > open Bookings_Dashboard
B38: Total Bookings | E38: Cancellation Rate
B39: =Bookings_Dashboard!$B$4 -> 5000 | E39: =Bookings_Dashboard!$D$4 -> 0.1544
B41: Avg Lead Time (days) | E41: Avg Booking Value
B42: =Bookings_Dashboard!$H$4 -> 41.0406 | E42: =Bookings_Dashboard!$L$4 -> 43144.195
B44: ="Top booking channel: "&INDEX(Bookings_Dashboard!$E$71:$E$78,MATCH(MAX(Bookings_Dashboard!$F$71:$F$78),Bookings_Dashboard!$F$71:$F$78,0))&" ("&TEXT(MAX(Bookings_Dashboard!$F$71:$F$78),"#,##0")&")" -> Top booking channel: Direct Website (897)
B46: ="Highest-cancellation channel: "&INDEX(Bookings_Dashboard!$E$71:$E$78,MATCH(MAX(Bookings_Dashboard!$G$71:$G$78),Bookings_Dashboard!$G$71:$G$78,0))&" ("&TEXT(MAX(Bookings_Dashboard!$G$71:$G$78),"0.0%")&")" -> Highest-cancellation channel: OTA - Booking.com (26.2%)
B52: 4. REVENUE > open Revenue_Dashboard
B54: Gross Revenue (Cr) | E54: Net Revenue (Cr)
B55: =Revenue_Dashboard!$B$4 -> 20.838432 | E55: =Revenue_Dashboard!$D$4 -> 19.39282
B57: Commission (Cr) | E57: Ancillary Share
B58: =Revenue_Dashboard!$F$4 -> 1.4456117 | E58: =Revenue_Dashboard!$H$4 -> 0.15299337
B60: ="Top revenue city (INR Cr): "&INDEX(Revenue_Dashboard!$L$56:$L$67,MATCH(MAX(Revenue_Dashboard!$M$56:$M$67),Revenue_Dashboard!$M$56:$M$67,0))&" ("&TEXT(MAX(Revenue_Dashboard!$M$56:$M$67),"0.00")&")" -> Top revenue city (INR Cr): New Delhi (2.45)
B62: ="Top revenue channel (INR Cr): "&INDEX(Revenue_Dashboard!$B$84:$B$91,MATCH(MAX(Revenue_Dashboard!$C$84:$C$91),Revenue_Dashboard!$C$84:$C$91,0))&" ("&TEXT(MAX(Revenue_Dashboard!$C$84:$C$91),"0.00")&")" -> Top revenue channel (INR Cr): Travel Agent (4.27)
B68: 5. REVIEWS > open Reviews_Dashboard
B70: Total Reviews | E70: Avg Overall Rating
B71: =Reviews_Dashboard!$B$4 -> 2581 | E71: =Reviews_Dashboard!$D$4 -> 4.105773
B73: NPS | E73: Positive Sentiment
B74: =Reviews_Dashboard!$F$4 -> 22.394421 | E74: =Reviews_Dashboard!$H$4 -> 0.77799303
B76: ="Best-rated category: "&INDEX(Reviews_Dashboard!$K$57:$K$60,MATCH(MAX(Reviews_Dashboard!$L$57:$L$60),Reviews_Dashboard!$L$57:$L$60,0))&" ("&TEXT(MAX(Reviews_Dashboard!$L$57:$L$60),"0.00")&")" -> Best-rated category: Cleanliness (4.05)
B78: ="Lowest-rated category: "&INDEX(Reviews_Dashboard!$K$57:$K$60,MATCH(MIN(Reviews_Dashboard!$L$57:$L$60),Reviews_Dashboard!$L$57:$L$60,0))&" ("&TEXT(MIN(Reviews_Dashboard!$L$57:$L$60),"0.00")&")" -> Lowest-rated category: Location (4.01)
B84: 6. HOTEL PERFORMANCE > open Hotel_Performance_Dashboard
B86: Occupancy | E86: ADR (INR)
B87: =Hotel_Performance_Dashboard!$B$4 -> 0.68968138 | E87: =Hotel_Performance_Dashboard!$D$4 -> 7281.5536
B89: RevPAR (INR) | E89: GOP Margin
B90: =Hotel_Performance_Dashboard!$F$4 -> 5021.952 | E90: =Hotel_Performance_Dashboard!$L$4 -> 0.38413736
B92: ="Top hotel by GOP (INR Cr): "&INDEX(Hotel_Performance_Dashboard!$G$99:$G$108,MATCH(MAX(Hotel_Performance_Dashboard!$H$99:$H$108),Hotel_Performance_Dashboard!$H$99:$H$108,0))&" ("&TEXT(MAX(Hotel_Performance_Dashboard!$H$99:$H$108),"0.00")&")" -> Top hotel by GOP (INR Cr): Golden Sands New Delhi (116.31)
B94: ="Best-occupancy city: "&INDEX(Hotel_Performance_Dashboard!$J$71:$J$82,MATCH(MAX(Hotel_Performance_Dashboard!$K$71:$K$82),Hotel_Performance_Dashboard!$K$71:$K$82,0))&" ("&TEXT(MAX(Hotel_Performance_Dashboard!$K$71:$K$82),"0.0%")&")" -> Best-occupancy city: Bengaluru (72.4%)
B100: 7. TOURISM TRENDS > open Tourism_Trends_Dashboard
B102: Total Arrivals (Cr) | E102: International Share
B103: =Tourism_Trends_Dashboard!$B$4 -> 19.81976 | E103: =Tourism_Trends_Dashboard!$D$4 -> 0.16595004
B105: Tourism Revenue (INR Cr) | E105: Avg Stay (nights)
B106: =Tourism_Trends_Dashboard!$F$4 -> 278382.11 | E106: =Tourism_Trends_Dashboard!$H$4 -> 2.6916667
B108: ="Top tourism-revenue city (INR Cr): "&INDEX(Tourism_Trends_Dashboard!$I$56:$I$67,MATCH(MAX(Tourism_Trends_Dashboard!$L$56:$L$67),Tourism_Trends_Dashboard!$L$56:$L$67,0))&" ("&TEXT(MAX(Tourism_Trends_Dashboard!$L$56:$L$67),"#,##0")&")" -> Top tourism-revenue city (INR Cr): New Delhi (62,462)
B110: ="Peak season (avg arrivals, Lakh): "&INDEX(Tourism_Trends_Dashboard!$B$84:$B$86,MATCH(MAX(Tourism_Trends_Dashboard!$C$84:$C$86),Tourism_Trends_Dashboard!$C$84:$C$86,0))&" ("&TEXT(MAX(Tourism_Trends_Dashboard!$C$84:$C$86),"0.00")&")" -> Peak season (avg arrivals, Lakh): Peak (9.33)
